Workbook

Sheet 8.1
A1: ތާވަލު 8.1: ހުށަހެޅިފައިވާ މައްސަލަތައް، 2011- 2015
A2: Table 8.1: LOGGED CASES FROM THE YEAR, 2011 - 2015
A3: Logged Cases | B3: 2008 | C3: 2009 | D3: 2011 | E3: 2012 | F3: 2013 | G3: 2014 | H3: 2015 | I3: ބެހިފައިވާ ގޮތް އިންސައްތައިން | J3: 2014އާއި އަޅާބަލާއިރު 2015ގައި އިތުރުވި މިންވަރު (%) | K3: ހުށަހެޅިފައިވާ މައްސަލަތައް
I4: % share 2015 | J4: % change over 2014
A5: Total | B5: 17674 | C5: 19259 | D5: =SUM(D6:D17) -> 17803 | E5: =SUM(E6:E17) -> 20512 | F5: =SUM(F6:F17) -> 21885 | G5: =SUM(G6:G17) -> 18193 | H5: 16363 | I5: =H5/$H$5*100 -> 100 | J5: =((H5-G5)/G5)*100 -> -10.058814 | K5: wlcmuj | V5: Theft | W5: =I6 -> 24.384282
A6: Theft | B6: 3903 | C6: 4007 | D6: 4734 | E6: 6571 | F6: 6683 | G6: 5080 | H6: 3990 | I6: =H6/$H$5*100 -> 24.384282 | J6: =((H6-G6)/G6)*100 -> -21.456693 | K6: ވައްކަން | V6: Drugs | W6: =I7 -> 12.497708
A7: Traffic accidents | B7: 3838 | C7: 3013 | D7: 2251 | E7: 1974 | F7: 1930 | G7: 2137 | H7: 2045 | I7: =H7/$H$5*100 -> 12.497708 | J7: =((H7-G7)/G7)*100 -> -4.3051006 | K7: ޓްރެފިކް | V7: Traffic accidents | W7: =I8 -> 12.699383
A8: Drugs | B8: 2484 | C8: 2366 | D8: 1823 | E8: 2534 | F8: 3965 | G8: 3140 | H8: 2078 | I8: =H8/$H$5*100 -> 12.699383 | J8: =((H8-G8)/G8)*100 -> -33.821656 | K8: މަސްތުވާތަކެތި | V8: Lost Items | W8: =I9 -> 10.493186
A9: Lost Items | B9: 1520 | C9: 2139 | D9: 1480 | E9: 1508 | F9: 1983 | G9: 2014 | H9: 1717 | I9: =H9/$H$5*100 -> 10.493186 | J9: =((H9-G9)/G9)*100 -> -14.746773 | K9: ގެއްލޭތަކެތި | V9: Assault | W9: =I10 -> 5.7141111
A10: Assault | B10: 1602 | C10: 2000 | D10: 1320 | E10: 1264 | F10: 1289 | G10: 1062 | H10: 935 | I10: =H10/$H$5*100 -> 5.7141111 | J10: =((H10-G10)/G10)*100 -> -11.958569 | K10: މާރާމާރީ | V10: Robbery | W10: =I11 -> 3.2634602
A11: Vandalism | B11: 648 | C11: 902 | D11: 775 | E11: 880 | F11: 728 | G11: 520 | H11: 534 | I11: =H11/$H$5*100 -> 3.2634602 | J11: =((H11-G11)/G11)*100 -> 2.6923077 | K11: މުދަލަށް ގެއްލުންދިނުން | V11: Vandalism | W11: =I12 -> 3.3245737
A12: Robbery | B12: 596 | C12: 589 | D12: 718 | E12: 972 | F12: 729 | G12: 620 | H12: 544 | I12: =H12/$H$5*100 -> 3.3245737 | J12: =((H12-G12)/G12)*100 -> -12.258065 | K12: ފޭރުން | V12: Sexual offences | W12: =I13 -> 3.2451262
A13: Sexual offences | B13: 455 | C13: 563 | D13: 642 | E13: 577 | F13: 573 | G13: 475 | H13: 531 | I13: =H13/$H$5*100 -> 3.2451262 | J13: =((H13-G13)/G13)*100 -> 11.789474 | K13: ބަދުއަޙްލާޤީ | V13: Embezzelment | W13: =I14 -> 4.5285094
A14: Embezzelment | B14: 313 | C14: 391 | D14: 364 | E14: 311 | F14: 391 | G14: 377 | H14: 741 | I14: =H14/$H$5*100 -> 4.5285094 | J14: =((H14-G14)/G14)*100 -> 96.551724 | K14: މަކަރާއި ޙީލަތް | V14: Domestic violence | W14: =I15 -> 2.0656359
A15: Domestic violence | B15: 172 | C15: 156 | D15: 146 | E15: 179 | F15: 207 | G15: 186 | H15: 338 | I15: =H15/$H$5*100 -> 2.0656359 | J15: =((H15-G15)/G15)*100 -> 81.72043 | K15: އާއިލީ | V15: Counterfiet and forgery | W15: =I16 -> 0.55613274
A16: Counterfiet and forgery | B16: 98 | C16: 133 | D16: 136 | E16: 126 | F16: 97 | G16: 77 | H16: 91 | I16: =H16/$H$5*100 -> 0.55613274 | J16: =((H16-G16)/G16)*100 -> 18.181818 | K16: ވަގުފައިސާ އަދި ފޯރޖްކުރުން | V16: Others | W16: =I17 -> 17.227892
A17: Others | B17: 1763 | C17: 2399 | D17: 3414 | E17: 3616 | F17: 3310 | G17: 2505 | H17: 2819 | I17: =H17/$H$5*100 -> 17.227892 | J17: =((H17-G17)/G17)*100 -> 12.53493 | K17: އެހެނިހެން
A18: Source: Maldives Police Service | K18: csivrws csilop cscviDclOm :Ivcaed utWmUluAwm
W21: 2010 | X21: 2011 | Y21: 2012 | Z21: 2013 | AA21: 2014 | AB21: 2015
V22: Theft | W22: -0.14973796 | X22: 18.32042 | Y22: 38.804394 | Z22: 1.704459 | AA22: -23.986234 | AB22: =((H6-G6)/G6)*100 -> -21.456693
V23: Traffic accidents | W23: -19.349486 | X23: -7.3662551 | Y23: -12.305642 | Z23: -2.2289767 | AA23: 10.725389 | AB23: =((H7-G7)/G7)*100 -> -4.3051006
V24: Drugs | W24: -31.656805 | X24: 12.739641 | Y24: 39.001646 | Z24: 56.471981 | AA24: -20.807062 | AB24: =((H8-G8)/G8)*100 -> -33.821656
V25: Lost Items | W25: -19.915849 | X25: -13.601868 | Y25: 1.8918919 | Z25: 31.498674 | AA25: 1.5632879 | AB25: =((H9-G9)/G9)*100 -> -14.746773
V26: Assault | W26: -23.7 | X26: -13.499345 | Y26: -4.2424242 | Z26: 1.9778481 | AA26: -17.610551 | AB26: =((H10-G10)/G10)*100 -> -11.958569

Sheet 8.2
A1: ތާވަލު 8.2: މާލެ އަދި އަތޮޅުތަކުން ހުށަހެޅިފައިވާ މައްސަލަތަކުގެ ޢަދަދު އަދި ބާވަތް، 2014- 2015
A2: TABLE 8.2 : NUMBER OF LOGGED CASES BY LOCALITY & TYPE OF CASES, 2014 - 2015
A3: Type of case | B3: 2014 | E3: 2015 | H3: ކުރީ އަހަރާއި އަޅާ ބަލާއިރު އިތުރުވި މިންވަރު | K3: ހުށަހެޅިފައިވާ މައްސަލަތައް
H4: % change over 2014
B5: ރާއްޖެ | C5: މާލެ | D5: އަތޮޅުތައް | E5: ރާއްޖެ | F5: މާލެ | G5: އަތޮޅުތައް | H5: ރާއްޖެ | I5: މާލެ | J5: އަތޮޅުތައް
B6: Republic | C6: Male' | D6: Atolls | E6: Republic | F6: Male' | G6: Atolls | H6: Republic | I6: Male' | J6: Atolls
A7: Total | B7: =SUM(C7:D7) -> 18193 | C7: =SUM(C8:C19) -> 12660 | D7: =SUM(D8:D19) -> 5533 | E7: =SUM(F7:G7) -> 16363 | F7: 11289 | G7: 5074 | H7: =(E7-B7)/B7*100 -> -10.058814 | I7: =(F7-C7)/C7*100 -> -10.829384 | J7: =(G7-D7)/D7*100 -> -8.2956805 | K7: wlcmuj
A8: Theft | B8: =SUM(C8:D8) -> 5080 | C8: 3662 | D8: 1418 | E8: =SUM(F8:G8) -> 3990 | F8: 2844 | G8: 1146 | H8: =(E8-B8)/B8*100 -> -21.456693 | I8: =(F8-C8)/C8*100 -> -22.33752 | J8: =(G8-D8)/D8*100 -> -19.181946 | K8: ވައްކަން
A9: Traffic Accidents | B9: =SUM(C9:D9) -> 2137 | C9: 1993 | D9: 144 | E9: =SUM(F9:G9) -> 2045 | F9: 1934 | G9: 111 | H9: =(E9-B9)/B9*100 -> -4.3051006 | I9: =(F9-C9)/C9*100 -> -2.9603613 | J9: =(G9-D9)/D9*100 -> -22.916667 | K9: ޓްރެފިކް އެކްސިޑެންޓްސް
A10: Drugs | B10: =SUM(C10:D10) -> 3140 | C10: 1906 | D10: 1234 | E10: =SUM(F10:G10) -> 2078 | F10: 1192 | G10: 886 | H10: =(E10-B10)/B10*100 -> -33.821656 | I10: =(F10-C10)/C10*100 -> -37.460651 | J10: =(G10-D10)/D10*100 -> -28.200972 | K10: މަސްތުވާތަކެތި
A11: Lost items | B11: =SUM(C11:D11) -> 2014 | C11: 1611 | D11: 403 | E11: =SUM(F11:G11) -> 1717 | F11: 1369 | G11: 348 | H11: =(E11-B11)/B11*100 -> -14.746773 | I11: =(F11-C11)/C11*100 -> -15.021726 | J11: =(G11-D11)/D11*100 -> -13.647643 | K11: ގެއްލޭތަކެތި
A12: Assault | B12: =SUM(C12:D12) -> 1062 | C12: 494 | D12: 568 | E12: =SUM(F12:G12) -> 935 | F12: 406 | G12: 529 | H12: =(E12-B12)/B12*100 -> -11.958569 | I12: =(F12-C12)/C12*100 -> -17.813765 | J12: =(G12-D12)/D12*100 -> -6.8661972 | K12: މާރާމާރީ
A13: Vandalism | B13: =SUM(C13:D13) -> 520 | C13: 277 | D13: 243 | E13: =SUM(F13:G13) -> 534 | F13: 291 | G13: 243 | H13: =(E13-B13)/B13*100 -> 2.6923077 | I13: =(F13-C13)/C13*100 -> 5.0541516 | J13: =(G13-D13)/D13*100 -> 0 | K13: މުދަލަށް ގެއްލުންދިނުން
A14: Robbery | B14: =SUM(C14:D14) -> 620 | C14: 561 | D14: 59 | E14: =SUM(F14:G14) -> 544 | F14: 495 | G14: 49 | H14: =(E14-B14)/B14*100 -> -12.258065 | I14: =(F14-C14)/C14*100 -> -11.764706 | J14: =(G14-D14)/D14*100 -> -16.949153 | K14: ފޭރުން
A15: Sexual offences | B15: =SUM(C15:D15) -> 475 | C15: 136 | D15: 339 | E15: =SUM(F15:G15) -> 531 | F15: 147 | G15: 384 | H15: =(E15-B15)/B15*100 -> 11.789474 | I15: =(F15-C15)/C15*100 -> 8.0882353 | J15: =(G15-D15)/D15*100 -> 13.274336 | K15: ބަދުއަޙްލާޤީ
A16: Embezzelment | B16: =SUM(C16:D16) -> 377 | C16: 288 | D16: 89 | E16: =SUM(F16:G16) -> 741 | F16: 612 | G16: 129 | H16: =(E16-B16)/B16*100 -> 96.551724 | I16: =(F16-C16)/C16*100 -> 112.5 | J16: =(G16-D16)/D16*100 -> 44.94382 | K16: މަކަރާއި ޙީލަތް
A17: Domestic violence | B17: =SUM(C17:D17) -> 186 | C17: 101 | D17: 85 | E17: =SUM(F17:G17) -> 338 | F17: 139 | G17: 199 | H17: =(E17-B17)/B17*100 -> 81.72043 | I17: =(F17-C17)/C17*100 -> 37.623762 | J17: =(G17-D17)/D17*100 -> 134.11765 | K17: އާއިލީ
A18: Counterfiet and forgery | B18: =SUM(C18:D18) -> 77 | C18: 65 | D18: 12 | E18: =SUM(F18:G18) -> 91 | F18: 79 | G18: 12 | H18: =(E18-B18)/B18*100 -> 18.181818 | I18: =(F18-C18)/C18*100 -> 21.538462 | J18: =(G18-D18)/D18*100 -> 0 | K18: ވަގުފައިސާ އަދި ފޯރޖްކުރުން
A19: Others | B19: =SUM(C19:D19) -> 2505 | C19: =SUM(C20:C30) -> 1566 | D19: =SUM(D20:D30) -> 939 | E19: =SUM(F19:G19) -> 2819 | F19: 1781 | G19: 1038 | H19: =(E19-B19)/B19*100 -> 12.53493 | I19: =(F19-C19)/C19*100 -> 13.729246 | J19: =(G19-D19)/D19*100 -> 10.543131 | K19: އެހެނިހެން
A20: Threatening | B20: =SUM(C20:D20) -> 592 | C20: 329 | D20: 263 | E20: =SUM(F20:G20) -> 532 | F20: 272 | G20: 260 | H20: =(E20-B20)/B20*100 -> -10.135135 | I20: =(F20-C20)/C20*100 -> -17.325228 | J20: =(G20-D20)/D20*100 -> -1.1406844 | K20: ބިރުދެއްކުން
A21: Fire incidents | B21: =SUM(C21:D21) -> 57 | C21: 22 | D21: 35 | E21: =SUM(F21:G21) -> 61 | F21: 31 | G21: 30 | H21: =(E21-B21)/B21*100 -> 7.0175439 | I21: =(F21-C21)/C21*100 -> 40.909091 | J21: =(G21-D21)/D21*100 -> -14.285714 | K21: އަލިފާނުގެ ހާދިސާ
A22: Environmental offences | B22: =SUM(C22:D22) -> 52 | C22: 4 | D22: 48 | E22: =SUM(F22:G22) -> 25 | F22: 8 | G22: 17 | H22: =(E22-B22)/B22*100 -> -51.923077 | I22: =(F22-C22)/C22*100 -> 100 | J22: =(G22-D22)/D22*100 -> -64.583333 | K22: ތިމާވެއްޓާއި ގުޅުންހުރި މައްސަލަތައް
A23: Illegal immigration | B23: =SUM(C23:D23) -> 40 | C23: 26 | D23: 14 | E23: =SUM(F23:G23) -> 38 | F23: 20 | G23: 18 | H23: =(E23-B23)/B23*100 -> -5 | I23: =(F23-C23)/C23*100 -> -23.076923 | J23: =(G23-D23)/D23*100 -> 28.571429 | K23: ރާއްޖެއަށް ނުވަތަ ރާއްޖޭގެ ސަރަހައްދަކަށް ޤަވާއިދާއި ހިލާފަށް ވަނުން
A24: Arson | B24: =SUM(C24:D24) -> 42 | C24: 5 | D24: 37 | E24: =SUM(F24:G24) -> 60 | F24: 14 | G24: 46 | H24: =(E24-B24)/B24*100 -> 42.857143 | I24: =(F24-C24)/C24*100 -> 180 | J24: =(G24-D24)/D24*100 -> 24.324324 | K24: ހުޅުޖެހުން
A25: Obstruction of Justice | B25: =SUM(C25:D25) -> 166 | C25: 70 | D25: 96 | E25: =SUM(F25:G25) -> 145 | F25: 79 | G25: 66 | H25: =(E25-B25)/B25*100 -> -12.650602 | I25: =(F25-C25)/C25*100 -> 12.857143 | J25: =(G25-D25)/D25*100 -> -31.25 | K25: ފުލުހުންގެ ވާޖިބަށް ހުރަސް އެޅުން
A26: Illegally entering households | B26: =SUM(C26:D26) -> 65 | C26: 39 | D26: 26 | E26: =SUM(F26:G26) -> 96 | F26: 58 | G26: 38 | H26: =(E26-B26)/B26*100 -> 47.692308 | I26: =(F26-C26)/C26*100 -> 48.717949 | J26: =(G26-D26)/D26*100 -> 46.153846 | K26: ޤަވާއިދާއި ޚިލާފަށް ގޯތިގެދޮރަށް ވަނުން
A27: Sudden death | B27: =SUM(C27:D27) -> 5 | C27: 3 | D27: 2 | E27: =SUM(F27:G27) -> 6 | F27: 0 | G27: 6 | H27: =(E27-B27)/B27*100 -> 20 | I27: =(F27-C27)/C27*100 -> -100 | J27: =(G27-D27)/D27*100 -> 200 | K27: ކުއްލި މަރު
A28: Attempt to suicide | B28: =SUM(C28:D28) -> 42 | C28: 22 | D28: 20 | E28: =SUM(F28:G28) -> 62 | F28: 29 | G28: 33 | H28: =(E28-B28)/B28*100 -> 47.619048 | I28: =(F28-C28)/C28*100 -> 31.818182 | J28: =(G28-D28)/D28*100 -> 65 | K28: އަމިއްލައަށް މަރުވާން އުޅުން
A29: Unlawful posession of weapons | B29: =SUM(C29:D29) -> 77 | C29: 48 | D29: 29 | E29: =SUM(F29:G29) -> 45 | F29: 23 | G29: 22 | H29: =(E29-B29)/B29*100 -> -41.558442 | I29: =(F29-C29)/C29*100 -> -52.083333 | J29: =(G29-D29)/D29*100 -> -24.137931 | K29: ހަތިޔާރު ގެންގުޅުން
A30: Others | B30: =SUM(C30:D30) -> 1367 | C30: 998 | D30: 369 | E30: =SUM(F30:G30) -> 1749 | F30: 1247 | G30: 502 | H30: =(E30-B30)/B30*100 -> 27.944404 | I30: =(F30-C30)/C30*100 -> 24.9499 | J30: =(G30-D30)/D30*100 -> 36.04336 | K30: އެހެނިހެން
A31: Source: Maldives Police Service | K31: csivrws csilop cscviDclOm :Ivcaed utWmUluAwm

Sheet 8.3
A1: ތާވަލު 8.3: އެކި އަތޮޅުތަކުން ހުށަހެޅިފައިވާ މައްސަލަތަކުގެ އަދަދު، 2010- 2015
A2: TABLE: 8.3: NUMBER OF LOGGED CASES BY ATOLL, 2010 - 2015
A3: Locality | B3: 2010 | C3: 2011 | D3: 2012 | E3: 2013 | F3: 2014 | G3: 2015 | I3: ކުރީ އަހަރާއި އަޅާ | J3: ތަން
I4: ބަލާއިރު އިތުރުވި މިންވަރު
I5: % change over 2014
A6: Republic | B6: =SUM(B7:B8) -> 16994 | C6: =SUM(C7:C8) -> 17803 | D6: =SUM(D7:D8) -> 20512 | E6: =SUM(E7:E8) -> 21885 | F6: =SUM(F7:F8) -> 18193 | G6: =SUM(G7:G8) -> 16363 | I6: =((G6-F6)/F6)*100 -> -10.058814 | J6: ejcaWriLum
A7: Male' | B7: 12238 | C7: 11907 | D7: 14555 | E7: 15284 | F7: 12660 | G7: 11289 | I7: =((G7-F7)/F7)*100 -> -10.829384 | J7: elWm
A8: Atolls | B8: =SUM(B9:B28) -> 4756 | C8: =SUM(C9:C28) -> 5896 | D8: =SUM(D9:D28) -> 5957 | E8: =SUM(E9:E28) -> 6601 | F8: =SUM(F9:F29) -> 5533 | G8: =SUM(G9:G28) -> 5074 | I8: =((G8-F8)/F8)*100 -> -8.2956805 | J8: އަތޮޅުތައް
A9: HA | B9: 269 | C9: 246 | D9: 236 | E9: 236 | F9: 210 | G9: 210 | I9: =((G9-F9)/F9)*100 -> 0 | J9: ah
A10: HDh | B10: 575 | C10: 726 | D10: 630 | E10: 608 | F10: 568 | G10: 394 | I10: =((G10-F10)/F10)*100 -> -30.633803 | J10: dh
A11: Sh | B11: 164 | C11: 186 | D11: 171 | E11: 138 | F11: 155 | G11: 145 | I11: =((G11-F11)/F11)*100 -> -6.4516129 | J11: S
A12: N | B12: 199 | C12: 232 | D12: 268 | E12: 260 | F12: 221 | G12: 142 | I12: =((G12-F12)/F12)*100 -> -35.746606 | J12: n
A13: R | B13: 205 | C13: 250 | D13: 220 | E13: 229 | F13: 242 | G13: 259 | I13: =((G13-F13)/F13)*100 -> 7.0247934 | J13: r
A14: B | B14: 173 | C14: 218 | D14: 245 | E14: 157 | F14: 167 | G14: 138 | I14: =((G14-F14)/F14)*100 -> -17.365269 | J14: b
A15: Lh | B15: 182 | C15: 185 | D15: 253 | E15: 208 | F15: 245 | G15: 235 | I15: =((G15-F15)/F15)*100 -> -4.0816327 | J15: L
A16: K | B16: 228 | C16: 363 | D16: 372 | E16: 281 | F16: 277 | G16: 369 | I16: =((G16-F16)/F16)*100 -> 33.212996 | J16: k
A17: AA | B17: 114 | C17: 111 | D17: 103 | E17: 135 | F17: 91 | G17: 121 | I17: =((G17-F17)/F17)*100 -> 32.967033 | J17: aa
A18: ADh | B18: 141 | C18: 187 | D18: 151 | E18: 500 | F18: 284 | G18: 252 | I18: =((G18-F18)/F18)*100 -> -11.267606 | J18: da
A19: V | B19: 15 | C19: 18 | D19: 27 | E19: 19 | F19: 32 | G19: 39 | I19: =((G19-F19)/F19)*100 -> 21.875 | J19: v
A20: M | B20: 83 | C20: 105 | D20: 108 | E20: 77 | F20: 64 | G20: 64 | I20: =((G20-F20)/F20)*100 -> 0 | J20: m
... A28: S | B28: 840 | C28: 996 | D28: 1105 | E28: 1349 | F28: 988 | G28: 903 | I28: =((G28-F28)/F28)*100 -> -8.6032389 | J28: s
A29: N/A | B29: - | C29: - | D29: - | E29: - | F29: 6 | G29: 0 | H29: 6 | I29: =((G29-F29)/F29)*100 -> -100
A30: Note: N/A - Not Applicable | J30: csivrws csilop cscviDclOm :Ivcaed utWmUluAwm
A31: Source: Maldives Police Service

Sheet 8.4
A1: ތާވަލު 8.4: އަތޮޅުތަކުން ހުށަހެޅިފައިވާ މައްސަލަތައް، 2015
A2: Table 8.4 : LOGGED CASES BY TYPE AND ATOLL, 2015
A3: Type of case | B3: ޖުމްލަ | C3: ah | D3: dh | E3: S | F3: n | G3: r | H3: b | I3: L | J3: k | K3: aa | L3: da | M3: v | N3: m | O3: f | P3: d | Q3: t | R3: l | S3: ag | T3: dg | U3: N | V3: s | W3: ހުށަހެޅިފައިވާ މައްސަލަތައް
B4: Total | C4: HA | D4: HDh | E4: Sh | F4: N | G4: R | H4: B | I4: Lh | J4: K | K4: AA | L4: ADh | M4: V | N4: M | O4: F | P4: Dh | Q4: Th | R4: L | S4: GA | T4: GDh | U4: Gn | V4: S
A5: Total | B5: =SUM(B6:B17) -> 5074 | C5: =SUM(C6:C17) -> 210 | D5: =SUM(D6:D17) -> 394 | E5: =SUM(E6:E17) -> 145 | F5: =SUM(F6:F17) -> 142 | G5: =SUM(G6:G17) -> 259 | H5: =SUM(H6:H17) -> 138 | I5: =SUM(I6:I17) -> 235 | ... V5: =SUM(V6:V17) -> 903 | W5: ޖުމްލަ
A6: Theft | B6: =SUM(C6:V6) -> 1146 | C6: 41 | D6: 94 | E6: 28 | F6: 28 | G6: 53 | H6: 31 | I6: 53 | J6: 78 | K6: 16 | L6: 42 | M6: 4 | N6: 13 | O6: 14 | P6: 9 | Q6: 27 | R6: 65 | S6: 98 | T6: 103 | U6: 95 | V6: 254 | W6: ވައްކަން
A7: Traffic Accidents | B7: =SUM(C7:V7) -> 111 | C7: 2 | D7: 14 | E7: 0 | F7: 1 | G7: 7 | H7: 1 | I7: 3 | J7: 3 | K7: 0 | L7: 3 | M7: 0 | N7: 1 | O7: 0 | P7: 0 | Q7: 0 | R7: 5 | S7: 5 | T7: 6 | U7: 8 | V7: 52 | W7: ޓްރެފިކް އެކްސިޑެންޓްސް
A8: Drugs | B8: =SUM(C8:V8) -> 886 | C8: 19 | D8: 51 | E8: 22 | F8: 40 | G8: 49 | H8: 7 | I8: 53 | J8: 79 | K8: 19 | L8: 35 | M8: 3 | N8: 16 | O8: 3 | P8: 11 | Q8: 40 | R8: 70 | S8: 84 | T8: 77 | U8: 68 | V8: 140 | W8: މަސްތުވާތަކެތި
A9: Lost items | B9: =SUM(C9:V9) -> 348 | C9: 12 | D9: 28 | E9: 10 | F9: 5 | G9: 8 | H9: 8 | I9: 15 | J9: 49 | K9: 9 | L9: 54 | M9: 4 | N9: 3 | O9: 9 | P9: 7 | Q9: 4 | R9: 11 | S9: 16 | T9: 18 | U9: 29 | V9: 49 | W9: ގެއްލޭތަކެތި
A10: Assault | B10: =SUM(C10:V10) -> 529 | C10: 16 | D10: 39 | E10: 11 | F10: 15 | G10: 36 | H10: 13 | I10: 26 | J10: 32 | K10: 12 | L10: 24 | M10: 4 | N10: 3 | O10: 11 | P10: 5 | Q10: 15 | R10: 46 | S10: 55 | T10: 47 | U10: 34 | V10: 85 | W10: މާރާމާރީ
A11: Vandalism | B11: =SUM(C11:V11) -> 243 | C11: 11 | D11: 23 | E11: 11 | F11: 7 | G11: 11 | H11: 7 | I11: 10 | J11: 9 | K11: 3 | L11: 9 | M11: 3 | N11: 1 | O11: 7 | P11: 8 | Q11: 5 | R11: 12 | S11: 22 | T11: 14 | U11: 16 | V11: 54 | W11: މުދަލަށް ގެއްލުންދިނުން
A12: Robbery | B12: =SUM(C12:V12) -> 49 | C12: 0 | D12: 11 | E12: 0 | F12: 0 | G12: 0 | H12: 1 | I12: 0 | J12: 2 | K12: 1 | L12: 0 | M12: 0 | N12: 0 | O12: 0 | P12: 0 | Q12: 0 | R12: 1 | S12: 6 | T12: 3 | U12: 7 | V12: 17 | W12: ފޭރުން
A13: Sexual offences | B13: =SUM(C13:V13) -> 384 | C13: 31 | D13: 28 | E13: 16 | F13: 10 | G13: 26 | H13: 12 | I13: 17 | J13: 28 | K13: 19 | L13: 12 | M13: 5 | N13: 4 | O13: 7 | P13: 6 | Q13: 7 | R13: 35 | S13: 32 | T13: 27 | U13: 18 | V13: 44 | W13: ބަދުއަޙްލާޤީ
A14: Embezzelment | B14: =SUM(C14:V14) -> 129 | C14: 13 | D14: 18 | E14: 9 | F14: 1 | G14: 6 | H14: 4 | I14: 8 | J14: 7 | K14: 0 | L14: 6 | M14: 1 | N14: 1 | O14: 2 | P14: 2 | Q14: 2 | R14: 7 | S14: 4 | T14: 6 | U14: 6 | V14: 26 | W14: މަކަރާއި ޙީލަތް
A15: Domestic violence | B15: =SUM(C15:V15) -> 199 | C15: 7 | D15: 15 | E15: 3 | F15: 4 | G15: 12 | H15: 7 | I15: 16 | J15: 11 | K15: 12 | L15: 6 | M15: 1 | N15: 3 | O15: 7 | P15: 3 | Q15: 5 | R15: 18 | S15: 12 | T15: 17 | U15: 8 | V15: 32 | W15: އާއިލީ
A16: Counterfiet | B16: =SUM(C16:V16) -> 12 | C16: 1 | D16: 0 | E16: 1 | F16: 0 | G16: 0 | H16: 0 | I16: 1 | J16: 0 | K16: 0 | L16: 0 | M16: 0 | N16: 1 | O16: 0 | P16: 0 | Q16: 0 | R16: 3 | S16: 0 | T16: 1 | U16: 1 | V16: 3 | W16: ވަގުފައިސާ
A17: Others | B17: =SUM(C17:V17) -> 1038 | C17: 57 | D17: 73 | E17: 34 | F17: 31 | G17: 51 | H17: 47 | I17: 33 | J17: 71 | K17: 30 | L17: 61 | M17: 14 | N17: 18 | O17: 12 | P17: 12 | Q17: 31 | R17: 90 | S17: 76 | T17: 75 | U17: 75 | V17: 147 | W17: އެހެނިހެން
A18: Source: Maldives Police Service | W18: csivrws csilop cscviDclOm :Ivcaed utWmUluAwm
A50: Theft | B50: 1146
A51: Drugs | B51: 111
A52: Assault | B52: 886
A53: Lost items | B53: 348
A54: Sexual offences | B54: 529
A55: Vandalism | B55: 243
A56: Traffic Accidents | B56: 49
A57: Embezzelment | B57: 384
A58: Domestic violence | B58: 129
A59: Robbery | B59: 199
A60: Counterfiet | B60: 12
A61: Others | B61: 1038

Sheet 8.5
A1: 2015 - 2009 ,cawtwlwscawm WviawfiLehwSuh : 8.5 ulwvWt
A2: Table 8.5: LOGGED CASES 2009 - 2015
A4: Number of cases logged | B4: 2009 | C4: 2010 | D4: 2011 | E4: 2012 | F4: 2013 | G4: 2014 | H4: 2015 | I4: cawtwlwscawm WviwފiLehwSuh
A5: Total | B5: =SUM(B6:B17) -> 19259 | C5: =SUM(C6:C17) -> 16994 | D5: =SUM(D6:D17) -> 17803 | E5: =SUM(E6:E17) -> 20512 | F5: =SUM(F6:F17) -> 21885 | G5: =SUM(G6:G17) -> 18193 | H5: =SUM(H6:H17) -> 16363 | I5: wlcmuj
A6: January | B6: 1834 | C6: 1495 | D6: 1490 | E6: 1688 | F6: 1676 | G6: 2011 | H6: 1371 | I6: ޖެނުއަރީ
A7: February | B7: 1601 | C7: 1327 | D7: 1404 | E7: 1423 | F7: 1597 | G7: 1552 | H7: 1414 | I7: ފެބްރުއަރީ
A8: March | B8: 1877 | C8: 1516 | D8: 1735 | E8: 1578 | F8: 1952 | G8: 1798 | H8: 1441 | I8: މާރޗް
A9: April | B9: 1701 | C9: 1621 | D9: 1477 | E9: 1959 | F9: 1796 | G9: 1650 | H9: 1271 | I9: އޭޕްރިލް
A10: May | B10: 1556 | C10: 1493 | D10: 1473 | E10: 1621 | F10: 1740 | G10: 1640 | H10: 1332 | I10: މެއި
A11: June | B11: 1663 | C11: 1366 | D11: 1505 | E11: 1668 | F11: 1942 | G11: 1489 | H11: 1263 | I11: ޖޫން
A12: July | B12: 1597 | C12: 1253 | D12: 1300 | E12: 1773 | F12: 2005 | G12: 1412 | H12: 1326 | I12: ޖުލައި
A13: August | B13: 1433 | C13: 1510 | D13: 1464 | E13: 2001 | F13: 2007 | G13: 1380 | H13: 1609 | I13: އޯގަސްޓް
A14: September | B14: 1699 | C14: 1395 | D14: 1460 | E14: 1732 | F14: 1833 | G14: 1245 | H14: 1428 | I14: ސެޕްޓެމްބަރ
A15: October | B15: 1574 | C15: 1517 | D15: 1712 | E15: 1704 | F15: 1727 | G15: 1497 | H15: 1369 | I15: އޮކްޓޯބަރ
A16: November | B16: 1387 | C16: 1252 | D16: 1374 | E16: 1724 | F16: 1706 | G16: 1349 | H16: 1285 | I16: ނޮވެމްބަރ
A17: December | B17: 1337 | C17: 1249 | D17: 1409 | E17: 1641 | F17: 1904 | G17: 1170 | H17: 1254 | I17: ޑިސެމްބަރ
A18: Source: Maldives Police Service | I18: csivrws csilop cscviDclOm :Ivcaed utWmUluAwm

Sheet 8.6
A2: ތާވަލު 8.6: 1992 އިން 2015 ށް މައްސަލަ ހުށަހެޅުމުން އައިގޮތް
A3: Table 8.6: TREND SHOWING LOGGED CASES, 1992 - 2015
A5: Year | B5: No. of Cases Logged
A6: އަހަރު | B6: ހުށަހެޅުނު އަދަދު
A7: 1992 | B7: 3843
A8: 1993 | B8: 5067
A9: 1994 | B9: 5344
A10: 1995 | B10: 5449
A11: 1996 | B11: 5287
A12: 1997 | B12: 6979
A13: 1998 | B13: 6266
A14: 1999 | B14: 4586
A15: 2000 | B15: 4567
A16: 2001 | B16: 6417
A17: 2002 | B17: 7045
A18: 2003 | B18: 9085
... A29: 2014 | B29: 18193
A30: 2015 | B30: ='8.5'!H5 -> 16363
A31: Source: Maldives Police Service | B31: މަޢުލޫމާތު ދެއްވީ: މޯލްޑިވްސް ޕޮލިސް ސަރވިސް

Sheet 8.7
A1: ތާވަލު 8.7: ހުށަހެޅިފައިވާ ވައްކަމުގެ މައްސަލަތަކުގެ ބާވަތް، 2011- 2015
A2: Table 8.7: THEFT CASES LOGGED BY TYPE, 2011 - 2015
A3: Type | B3: 2011 | C3: 2012 | D3: 2013 | E3: 2014 | F3: 2015 | H3: ކުރީ އަހަރާއި އަޅާ | I3: އިންސައްތަ | J3: މައްސަލައިގެ ބާވަތް
H4: ބަލާއިރު އިތުރުވި މިންވަރު | I4: Percenatge share
H5: %change over 2014 | I5: 2015
A6: Total | B6: =SUM(B7:B13) -> 4734 | C6: =SUM(C7:C13) -> 6571 | D6: =SUM(D7:D13) -> 6683 | E6: =SUM(E7:E13) -> 5080 | F6: =SUM(F7:F13) -> 3990 | H6: =((F6-E6)/E6*100) -> -21.456693 | I6: =F6/$F$6*100 -> 100
A7: Theft from places (not by forced entry) | B7: 2194 | C7: 3099 | D7: 3285 | E7: 2275 | F7: 1382 | H7: =((F7-E7)/E7*100) -> -39.252747 | I7: =F7/$F$6*100 -> 34.636591 | J7: ތަންތަނުން ކޮށްފައިވާ ވައްކަން (ފަޅާލައިގެންނޫން ގޮތްގޮތަށް)
A8: Vehicles | B8: 913 | C8: 1379 | D8: 1017 | E8: 602 | F8: 651 | H8: =((F8-E8)/E8*100) -> 8.1395349 | I8: =F8/$F$6*100 -> 16.315789 | J8: ދުއްވާތަކެތީގެ ވައްކަން
A9: Mobile phones | B9: 643 | C9: 865 | D9: 1022 | E9: 817 | F9: 807 | H9: =((F9-E9)/E9*100) -> -1.2239902 | I9: =F9/$F$6*100 -> 20.225564 | J9: މޯބަލް ފޯން
A10: Money | B10: 200 | C10: 278 | D10: 324 | E10: 258 | F10: 285 | H10: =((F10-E10)/E10*100) -> 10.465116 | I10: =F10/$F$6*100 -> 7.1428571 | J10: ފައިސާ
A11: Electronic items (except mobile phones) | B11: 174 | C11: 235 | D11: 218 | E11: 238 | F11: 166 | H11: =((F11-E11)/E11*100) -> -30.252101 | I11: =F11/$F$6*100 -> 4.160401 | J11: އިލެކްޓްރޯނިކް ސާމާނު
A12: Theft from places (by forced entry) | B12: 111 | C12: 73 | D12: 130 | E12: 237 | F12: 219 | H12: =((F12-E12)/E12*100) -> -7.5949367 | I12: =F12/$F$6*100 -> 5.4887218 | J12: ފަޅާލައިގެންވަދެ ތަންތަނުން ކޮށްފައިވާ ވައްކަން
A13: Other theft | B13: 499 | C13: 642 | D13: 687 | E13: 653 | F13: 480 | H13: =((F13-E13)/E13*100) -> -26.493109 | I13: =F13/$F$6*100 -> 12.030075 | J13: އެހެނިހެން ވައްކަން
A14: Source: Maldives Police Service | J14: csivrws csilop cscviDclOm :Ivcaed utWmUluAwm

Sheet 8.8
A1: ތާވަލު 8.8: ހުށަހެޅިފައިވާ މަސްތުވާތަކެތީގެ މައްސަލަތަކާއި އަދި ބާވަތް، 2011- 2015
A2: Table 8.8: DRUG CASES LOGGED BY TYPE, 2011 - 2015
A3: Type | B3: 2011 | C3: 2012 | D3: 2013 | E3: 2014 | F3: 2015 | H3: ކުރީ އަހަރާއި އަޅާ | I3: 2015 | J3: މައްސަލައިގެ ބާވަތް
H4: ބަލާއިރު އިތުރުވި މިންވަރު | I4: އިންސައްތަ
H5: % change over 2014 | I5: Percenatge share
A6: Total | B6: =B7+B14+B21 -> 1823 | C6: =C7+C14+C21 -> 2534 | D6: =D7+D14+D21 -> 3965 | E6: =E7+E14+E21 -> 3140 | F6: =F7+F14+F21 -> 2078 | H6: =((F6-E6)/E6*100) -> -33.821656 | I6: =F6/F6*100 -> 100 | J6: ޖުމްލަ
A7: Drugs | B7: =SUM(B8:B13) -> 1618 | C7: =SUM(C8:C13) -> 2349 | D7: =SUM(D8:D13) -> 3444 | E7: =SUM(E8:E13) -> 2868 | F7: =SUM(F8:F13) -> 1912 | H7: =((F7-E7)/E7*100) -> -33.333333 | I7: =F7/$F$6*100 -> 92.01155 | J7: މަސްތުވާތަކެތީގެ މައްސަލަތައް
A8: Use | B8: 660 | C8: 1374 | D8: 2139 | E8: 2036 | F8: 1152 | H8: =((F8-E8)/E8*100) -> -43.418468 | I8: =F8/$F$6*100 -> 55.437921 | J8: ބޭނުންކުރުން
A9: Possession | B9: 842 | C9: 809 | D9: 833 | E9: 597 | F9: 578 | H9: =((F9-E9)/E9*100) -> -3.1825796 | I9: =F9/$F$6*100 -> 27.815207 | J9: ގެންގުޅުން
A10: Production | B10: - | C10: - | D10: 2 | E10: 7 | F10: 2 | H10: =((F10-E10)/E10*100) -> -71.428571 | I10: =F10/$F$6*100 -> 0.096246391 | J10: އުފެއްދުން
A11: Import | B11: 87 | C11: 106 | D11: 130 | E11: 98 | F11: 71 | H11: =((F11-E11)/E11*100) -> -27.55102 | I11: =F11/$F$6*100 -> 3.4167469 | J11: އެތެރެކުރުން
A12: Sale | B12: 29 | C12: 60 | D12: 38 | E12: 27 | F12: 73 | H12: =((F12-E12)/E12*100) -> 170.37037 | I12: =F12/$F$6*100 -> 3.5129933 | J12: ވިޔަފާރިކުރުން
A13: others | B13: - | C13: - | D13: 302 | E13: 103 | F13: 36 | H13: =((F13-E13)/E13*100) -> -65.048544 | I13: =F13/$F$6*100 -> 1.732435 | J13: އެހެނިހެން
A14: Alcohol | B14: =SUM(B15:B20) -> 182 | C14: =SUM(C15:C20) -> 166 | D14: =SUM(D15:D20) -> 502 | E14: =SUM(E15:E20) -> 262 | F14: =SUM(F15:F20) -> 161 | H14: =((F14-E14)/E14*100) -> -38.549618 | I14: =F14/$F$6*100 -> 7.7478345 | J14: ރަލުގެ މައްސަލަތައް
A15: Use | B15: 65 | C15: 71 | D15: 75 | E15: 62 | F15: 63 | H15: =((F15-E15)/E15*100) -> 1.6129032 | I15: =F15/$F$6*100 -> 3.0317613 | J15: ބޭނުންކުރުން
A16: Possession | B16: 96 | C16: 55 | D16: 359 | E16: 170 | F16: 55 | H16: =((F16-E16)/E16*100) -> -67.647059 | I16: =F16/$F$6*100 -> 2.6467757 | J16: ގެންގުޅުން
A17: Production | B17: 8 | C17: 17 | D17: 17 | E17: 13 | F17: 13 | H17: =((F17-E17)/E17*100) -> 0 | I17: =F17/$F$6*100 -> 0.62560154 | J17: އުފެއްދުން
A18: Import | B18: 7 | C18: 11 | D18: 11 | E18: 3 | F18: 9 | H18: =((F18-E18)/E18*100) -> 200 | I18: =F18/$F$6*100 -> 0.43310876 | J18: އެތެރެކުރުން
A19: Sale | B19: 4 | C19: 12 | D19: 6 | E19: 3 | F19: 13 | H19: =((F19-E19)/E19*100) -> 333.33333 | I19: =F19/$F$6*100 -> 0.62560154 | J19: ވިޔަފާރިކުރުން
A20: Others | B20: 2 | C20: 0 | D20: 34 | E20: 11 | F20: 8 | H20: =((F20-E20)/E20*100) -> -27.272727 | I20: =F20/$F$6*100 -> 0.38498556 | J20: އެހެނިހެން
A21: Other cases related to drug offences | B21: 23 | C21: 19 | D21: 19 | E21: 10 | F21: 5 | H21: =((F21-E21)/E21*100) -> -50 | I21: =F21/$F$6*100 -> 0.24061598 | J21: ޑްރަގްސް އާއި ގުޅުން ހުރި އެހެނިހެން މައްސަލަތައް
A22: Source: Maldives Police Service | J22: csivrws csilop cscviDclOm :Ivcaed utWmUluAwm
R28: =SUM(R29:R31) -> 2078 | S28: =R28/R28*100 -> 100
Q29: Drugs | R29: =F7 -> 1912 | S29: =R29/R28*100 -> 92.01155
Q30: Alcohol | R30: =F14 -> 161 | S30: =R30/R28*100 -> 7.7478345
Q31: Other cases related to drug offences | R31: =F21 -> 5 | S31: =R31/R28*100 -> 0.24061598

Sheet 8.9
A1: ތާވަލު 8.9: މޯލްޑިވްސް ޕޮލިސް ސަރވިސްގެ ފަރާތުން އަތުލައިގަތް މަސްތުވާތަކެތީގެ އަދަދު، 2009 - 2015
A2: Table 8.9: DRUG CEASED BY MALDIVES POLICE SERVICE, 2009 - 2015
A4: Type of Drug | B4: Quantity ( grams ) | E4: އަދަދު (ގްރާމްއިން) | I4: ބާވަތް
B5: 2009 | C5: 2010 | D5: 2011 | E5: 2012 | F5: 2013 | G5: 2014 | H5: 2015
A6: Total | B6: =SUM(B7:B10) -> 5627.6267 | C6: =SUM(C7:C10) -> 3737.2701 | D6: =SUM(D7:D10) -> 10180.494 | E6: =SUM(E7:E10) -> 26936.36 | F6: =SUM(F7:F10) -> 10288.645 | G6: =SUM(G7:G10) -> 26925.248 | H6: =SUM(H7:H10) -> 0 | I6: ޖުމްލަ
A7: Opiates | B7: 1350.5147 | C7: 1754.8649 | D7: 0 | E7: 0 | F7: 0 | G7: 0 | I7: އޯޕިއޭޓްސް
A8: Heroin | B8: 0 | C8: 0 | D8: 5154.4754 | E8: 10107.068 | F8: 8869.9667 | G8: 21947.937 | I8: ހެރޮއިން
A9: Cannabis | B9: 3739.5271 | C9: 1957.8159 | D9: 5026.019 | E9: 16821.554 | F9: 1418.6786 | G9: 4977.311 | I9: ކެނަބިސް
A10: Benzodyziphine | B10: 537.5849 | C10: 24.5893 | D10: 0 | E10: 7.7378 | F10: 0 | G10: 0 | I10: ބެންޒޮޑީޒިފައިން
A11: Source: Maldives Police Service | I11: މަޢުލޫމާތު ދެއްވީ: މޯލްޑިވްސް ޕޮލިސް ސަރވިސް

Sheet 8.10
A1: ތާވަލު 8.10: ހުށަހެޅިފައިވާ މާރާމާރީގެ މައްސަލަތައް، 2011- 2015
A2: Table 8.10: ASSAULT CASES LOGGED BY TYPE, 2011 - 2015
A3: Type | B3: 2011 | C3: 2012 | D3: 2013 | E3: 2014 | F3: 2015 | H3: އިންސައްތަ 2015 | I3: ކުރީ އަހަރާއި އަޅާބަލާއިރު އިތުރުވި މިންވަރު | J3: މައްސަލައިގެ ބާވަތް
H4: Percentage share | I4: %change over 2014
A5: Total | B5: =B6+B10 -> 1320 | C5: =C6+C10 -> 1264 | D5: =D6+D10 -> 1289 | E5: =E6+E10 -> 1062 | F5: =F6+F10 -> 935 | H5: =F5/F5*100 -> 100 | I5: =((F5-E5)/E5*100) -> -11.958569 | J5: ޖުމްލަ
A6: Assault by group of persons | B6: =SUM(B7:B9) -> 207 | C6: =SUM(C7:C9) -> 158 | D6: =SUM(D7:D9) -> 192 | E6: =SUM(E7:E9) -> 268 | F6: =SUM(F7:F9) -> 195 | H6: =F6/$F$5*100 -> 20.855615 | I6: =((F6-E6)/E6*100) -> -27.238806 | J6: ގްރޫޕް މާރާމާރީ
A7: Using weapons | B7: 113 | C7: 34 | D7: 23 | E7: 20 | F7: 16 | H7: =F7/$F$5*100 -> 1.7112299 | I7: =((F7-E7)/E7*100) -> -20 | J7: ހަތިޔާރު ބޭނުންކޮށްގެން
A8: Using sharp weapons | B8: 49 | C8: 38 | D8: 26 | E8: 21 | F8: 20 | H8: =F8/$F$5*100 -> 2.1390374 | I8: =((F8-E8)/E8*100) -> -4.7619048 | J8: ތޫނު ހަތިޔާރު ބޭނުންކޮށްގެން
A9: Without use of weapons | B9: 45 | C9: 86 | D9: 143 | E9: 227 | F9: 159 | H9: =F9/$F$5*100 -> 17.005348 | I9: =((F9-E9)/E9*100) -> -29.955947 | J9: ހަތިޔާރު ބޭނުންނުކޮށް
A10: Other Assault | B10: 1113 | C10: 1106 | D10: 1097 | E10: 794 | F10: 740 | H10: =F10/$F$5*100 -> 79.144385 | I10: =((F10-E10)/E10*100) -> -6.8010076 | J10: އެހެނިހެން މާރާމާރީ
A11: Source: Maldives Police Service | J11: csivrws csilop cscviDclOm :Ivcaed utWmUluAwm
N30: Assault by group of persons | O30: =F6/F5*100 -> 20.855615
N31: Other Assault | O31: =F10/F5*100 -> 79.144385

Sheet 8.11
A1: ތާވަލު 8.11: ހުށަހެޅިފައިވާ މަރުގެ މައްސަލަތައް، 2011- 2015
A2: Table 8.11 : LOGGED CASES OF DEATH , 2011 - 2015
A3: Type | B3: 2011 | C3: 2012 | D3: 2013 | E3: 2014 | F3: 2015 | G3: ކުރީ އަހަރާއި އަޅާބަލާއިރު އިތުރުވި މިންވަރު | H3: ކުރީ އަހަރާއި އަޅާބަލާއިރު އިތުރުވި މިންވަރު | I3: މައްސަލައިގެ ބާވަތް
G4: % change over 2013 | H4: % change over 2014
A5: Total | B5: =SUM(B6:B11) -> 171 | C5: =SUM(C6:C11) -> 190 | D5: =SUM(D6:D11) -> 183 | E5: 174 | F5: =SUM(F6:F11) -> 171 | G5: =((E5-D5)/D5)*100 -> -4.9180328 | H5: =((F5-E5)/E5)*100 -> -1.7241379 | I5: ޖުމްލަ
A6: Homicide | B6: 3 | C6: 10 | D6: 3 | E6: 3 | F6: 11 | G6: =((E6-D6)/D6*100) -> 0 | H6: =((F6-E6)/E6*100) -> 266.66667 | I6: ގަސްތުގައި މީހުން މެރުން
A7: Suicide | B7: 13 | C7: 8 | D7: 19 | E7: 12 | F7: 15 | G7: =((E7-D7)/D7*100) -> -36.842105 | H7: =((F7-E7)/E7*100) -> 25 | I7: އަމިއްލައަށް މަރުވުން
A8: Diving/snorkeling accidents | B8: 13 | C8: 12 | D8: 15 | E8: 14 | F8: 11 | G8: =((E8-D8)/D8*100) -> -6.6666667 | H8: =((F8-E8)/E8*100) -> -21.428571 | I8: ޑައިވިންގ / ސްނޯކްލިންގ އެކްސިޑެންޓް
A9: Traffic accidents | B9: 7 | C9: 5 | D9: 2 | E9: 10 | F9: 11 | G9: =((E9-D9)/D9*100) -> 400 | H9: =((F9-E9)/E9*100) -> 10 | I9: ޓްރެފިކް އެކްސިޑެންޓް
A10: Drowning | B10: 8 | C10: 30 | D10: 15 | E10: 13 | F10: 18 | G10: =((E10-D10)/D10*100) -> -13.333333 | H10: =((F10-E10)/E10*100) -> 38.461538 | I10: ގެނބިގެން
A11: Other death cases logged | B11: 127 | C11: 125 | D11: 129 | E11: 122 | F11: 105 | G11: =((E11-D11)/D11*100) -> -5.4263566 | H11: =((F11-E11)/E11*100) -> -13.934426 | I11: އެހެނިހެން
A12: Break down: other death cases logged
A16: Source: Maldives Police Service | I16: csivrws csilop cscviDclOm :Ivcaed utWmUluAwm

Sheet 8.12
A1: ތާވަލު 8.12: ނިންމުނު މައްސަލަތައް، 2008- 2015
A2: Table 8.12: COMPLETED CASES BY TYPE, 2008 - 2015
A3: Type of case | B3: 2008 | C3: 2009 | D3: 2010 | E3: 2011 | F3: 2012 | G3: 2013 | H3: 2014 | I3: 2015 | J3: ކުރީ އަހަރާއި އަޅާބަލާއިރު އިތުރުވި މިންވަރު | L3: އިންސައްތަ 2015 | M3: މައްސަލައިގެ ބާވަތް
J4: %change over 2014 | L4: Percenatge share 2015
A5: Total | B5: 16499 | C5: 18904 | D5: 17601 | E5: 16255 | F5: 19741 | G5: 19614 | H5: 21984 | I5: =SUM(I6:I17) -> 20290 | J5: =((I5-H5)/H5*100) -> -7.7056041 | L5: =I5/$I$5*100 -> 100 | M5: wlcmuj
A6: Theft | B6: 3846 | C6: 4479 | D6: 3956 | E6: 4608 | F6: 6289 | G6: 5734 | H6: 6785 | I6: 4618 | J6: =((I6-H6)/H6*100) -> -31.938099 | L6: =I6/$I$5*100 -> 22.75998 | M6: ވައްކަން
A7: Traffic Accidents | B7: 2544 | C7: 2723 | D7: 2560 | E7: 2135 | F7: 2167 | G7: 1962 | H7: 2267 | I7: 1998 | J7: =((I7-H7)/H7*100) -> -11.865902 | L7: =I7/$I$5*100 -> 9.8472154 | M7: ޓްރެފިކް އެކްސިޑެންޓްސް
A8: Drugs | B8: 2531 | C8: 1804 | D8: 2002 | E8: 1172 | F8: 1736 | G8: 3237 | H8: 2939 | I8: 4528 | J8: =((I8-H8)/H8*100) -> 54.066009 | L8: =I8/$I$5*100 -> 22.316412 | M8: މަސްތުވާތަކެތި
A9: Lost items | B9: 1260 | C9: 2212 | D9: 1757 | E9: 1499 | F9: 1500 | G9: 1864 | H9: 2175 | I9: 1765 | J9: =((I9-H9)/H9*100) -> -18.850575 | L9: =I9/$I$5*100 -> 8.6988664 | M9: ގެއްލޭތަކެތި
A10: Assault | B10: 1370 | C10: 1679 | D10: 1580 | E10: 1265 | F10: 1342 | G10: 1149 | H10: 1507 | I10: 1200 | J10: =((I10-H10)/H10*100) -> -20.371599 | L10: =I10/$I$5*100 -> 5.9142435 | M10: މާރާމާރީ
A11: Vandalism | B11: 433 | C11: 866 | D11: 869 | E11: 757 | F11: 849 | G11: 681 | H11: 731 | I11: 617 | J11: =((I11-H11)/H11*100) -> -15.595075 | L11: =I11/$I$5*100 -> 3.0409069 | M11: މުދަލަށް ގެއްލުންދިނުން
A12: Robbery | B12: 608 | C12: 642 | D12: 564 | E12: 661 | F12: 961 | G12: 678 | H12: 823 | I12: 590 | J12: =((I12-H12)/H12*100) -> -28.311057 | L12: =I12/$I$5*100 -> 2.9078364 | M12: ފޭރުން
A13: Sexual offences | B13: 383 | C13: 435 | D13: 581 | E13: 547 | F13: 551 | G13: 610 | H13: 619 | I13: 647 | J13: =((I13-H13)/H13*100) -> 4.5234249 | L13: =I13/$I$5*100 -> 3.1887629 | M13: ބަދުއަޙްލާޤީ
A14: Embezzelment | B14: 326 | C14: 348 | D14: 402 | E14: 317 | F14: 311 | G14: 367 | H14: 489 | I14: 759 | J14: =((I14-H14)/H14*100) -> 55.214724 | L14: =I14/$I$5*100 -> 3.740759 | M14: މަކަރާއި ޙީލަތް
A15: Domestic violence | B15: 76 | C15: 86 | D15: 125 | E15: 116 | F15: 151 | G15: 171 | H15: 245 | I15: 335 | J15: =((I15-H15)/H15*100) -> 36.734694 | L15: =I15/$I$5*100 -> 1.6510596 | M15: އާއިލީ
A16: Counterfiet | B16: 88 | C16: 133 | D16: 153 | E16: 125 | F16: 135 | G16: 106 | H16: 106 | I16: 103 | J16: =((I16-H16)/H16*100) -> -2.8301887 | L16: =I16/$I$5*100 -> 0.50763923 | M16: ވަގުފައިސާ
A17: Others | B17: 3034 | C17: 3497 | D17: 3052 | E17: 3053 | F17: 3749 | G17: 3055 | H17: 3298 | I17: 3130 | J17: =((I17-H17)/H17*100) -> -5.0939964 | L17: =I17/$I$5*100 -> 15.426318 | M17: އެހެނިހެން
A18: Source: Maldives Police Service | M18: csivrws csilop cscviDclOm :Ivcaed utWmUluAwm
AD19: Logged cases | AE19: Completed cases
AC20: Theft | AD20: ='8.1'!H6 -> 3990 | AE20: =I6 -> 4618
AC21: Traffic accidents | AD21: ='8.1'!H7 -> 2045 | AE21: =I7 -> 1998
AC22: Drugs | AD22: ='8.1'!H8 -> 2078 | AE22: =I8 -> 4528
AC23: Lost Items | AD23: ='8.1'!H9 -> 1717 | AE23: =I9 -> 1765
AC24: Assault | AD24: ='8.1'!H10 -> 935 | AE24: =I10 -> 1200
AC25: Vandalism | AD25: ='8.1'!H11 -> 534 | AE25: =I11 -> 617
AC26: Robbery | AD26: ='8.1'!H12 -> 544 | AE26: =I12 -> 590
AC27: Sexual offences | AD27: ='8.1'!H13 -> 531 | AE27: =I13 -> 647
AC28: Embezzelment | AD28: ='8.1'!H14 -> 741 | AE28: =I14 -> 759
AC29: Domestic violence | AD29: ='8.1'!H15 -> 338 | AE29: =I15 -> 335
AC30: Counterfiet and forgery | AD30: ='8.1'!H16 -> 91 | AE30: =I16 -> 103
AC31: Others | AD31: ='8.1'!H17 -> 2819 | AE31: =I17 -> 3130

Sheet 8.13
A1: 2015 - 2014 ،ތާވަލު 8.13: ހުށަހެޅިފައިވާ މައްސަލަތަކުގެ ތެރެއިން ހައްޔަރުކުރެވުނު މީހުންގެ އަދަދު އަދި ޖިންސް
A2: Table 8.13: NUMBER OF DETAINEES REPORTED BY TYPE OF OFFENCE AND SEX, 2014 - 2015
A4: Type of offence | B4: 2014 | G4: 2015 | L4: ކުށުގެ ބާވަތް
B5: Number of Logged cases | D5: Number of Detainees ހައްޔަރުކުރެވުނު މީހުންގެ އަދަދު | G5: Number of Logged cases | I5: Number of Detainees ހައްޔަރުކުރެވުނު މީހުންގެ އަދަދު
D6: Both Sexes | E6: Male | F6: Female | I6: Both Sexes | J6: Male | K6: Female
B7: ހުށަހެޅިފައިވާ މައްސަލަތަކުގެ އަދަދު | D7: ދެޖިންސް | E7: ފިރިހެން | F7: އަންހެން | G7: ހުށަހެޅިފައިވާ މައްސަލަތަކުގެ އަދަދު | I7: ދެޖިންސް | J7: ފިރިހެން | K7: އަންހެން
A8: Total | B8: =SUM(B9:B20) -> 18193 | D8: =E8+F8 -> 6983 | E8: =SUM(E9:E20) -> 6709 | F8: =SUM(F9:F20) -> 274 | G8: =SUM(G9:G20) -> 16363 | I8: =J8+K8 -> 5827 | J8: =SUM(J9:J20) -> 5547 | K8: =SUM(K9:K20) -> 280 | L8: ޖުމްލަ
A9: Assault | B9: 1062 | D9: =SUM(E9:F9) -> 556 | E9: 547 | F9: 9 | G9: 935 | I9: 577 | J9: 564 | K9: 13 | L9: މާރާމާރީ
A10: Theft | B10: 5080 | D10: =SUM(E10:F10) -> 1593 | E10: 1554 | F10: 39 | G10: 3990 | I10: 1192 | J10: 1163 | K10: 29 | L10: ވައްކަން
A11: Robbery | B11: 620 | D11: =SUM(E11:F11) -> 243 | E11: 232 | F11: 11 | G11: 544 | I11: 143 | J11: 132 | K11: 11 | L11: ފޭރުން
A12: Drugs | B12: 3140 | D12: =SUM(E12:F12) -> 3316 | E12: 3158 | F12: 158 | G12: 2078 | I12: 2349 | J12: 2234 | K12: 115 | L12: މަސްތުވާތަކެތި
A13: Sexual Offences | B13: 475 | D13: =SUM(E13:F13) -> 310 | E13: 280 | F13: 30 | G13: 531 | I13: 325 | J13: 290 | K13: 35 | L13: ޖިންސީ މައްސަލަ
A14: Traffic accidents | B14: 2137 | D14: =SUM(E14:F14) -> 11 | E14: 11 | F14: 0 | G14: 2045 | I14: 9 | J14: 9 | K14: 0 | L14: ޓްރެފިކް
A15: Domestic violence | B15: 186 | D15: =SUM(E15:F15) -> 38 | E15: 36 | F15: 2 | G15: 338 | I15: 55 | J15: 43 | K15: 12 | L15: އާއިލީ
A16: Counterfeit and forgery | B16: 77 | D16: =SUM(E16:F16) -> 10 | E16: 9 | F16: 1 | G16: 91 | I16: 12 | J16: 12 | K16: 0 | L16: ވަގުފައިސާ
A17: Vandalism | B17: 520 | D17: =SUM(E17:F17) -> 147 | E17: 147 | F17: 0 | G17: 534 | I17: 126 | J17: 121 | K17: 5 | L17: މުދަލަށް ގެއްލުންދިނުން
A18: Embezzlement | B18: 377 | D18: =SUM(E18:F18) -> 80 | E18: 78 | F18: 2 | G18: 741 | I18: 63 | J18: 60 | K18: 3 | L18: މަކަރާއި ޙީލަތް
A19: Lost items | B19: 2014 | D19: =SUM(E19:F19) -> 2 | E19: 2 | F19: 0 | G19: 1717 | I19: 2 | J19: 1 | K19: 1 | L19: ގެއްލޭތަކެތި
A20: Others | B20: 2505 | D20: =SUM(E20:F20) -> 677 | E20: 655 | F20: 22 | G20: 2819 | I20: 974 | J20: 918 | K20: 56 | L20: އެހެނިހެން
A21: Source: Maldives Police Service | L21: csivrws csilop cscviDclOm :Ivcaed utWmUluAwm
V32: Male | W32: Female
U33: Assault | V33: =J9/I9*100 -> 97.746967 | W33: =K9/I9*100 -> 2.2530329
U34: Theft | V34: =J10/I10*100 -> 97.567114 | W34: =K10/I10*100 -> 2.4328859
U35: Robbery | V35: =J11/I11*100 -> 92.307692 | W35: =K11/I11*100 -> 7.6923077
U36: Drugs | V36: =J12/I12*100 -> 95.1043 | W36: =K12/I12*100 -> 4.8957003
U37: Sexual Offences | V37: =J13/I13*100 -> 89.230769 | W37: =K13/I13*100 -> 10.769231
U38: Traffic accidents | V38: =J14/I14*100 -> 100 | W38: =K14/I14*100 -> 0
U39: Domestic violence | V39: =J15/I15*100 -> 78.181818 | W39: =K15/I15*100 -> 21.818182
U40: Counterfeit and forgery | V40: =J16/I16*100 -> 100 | W40: =K16/I16*100 -> 0
U41: Vandalism | V41: =J17/I17*100 -> 96.031746 | W41: =K17/I17*100 -> 3.968254
U42: Embezzlement | V42: =J18/I18*100 -> 95.238095 | W42: =K18/I18*100 -> 4.7619048
U43: Lost items | V43: =J19/I19*100 -> 50 | W43: =K19/I19*100 -> 50
U44: Others | V44: =J20/I20*100 -> 94.250513 | W44: =K20/I20*100 -> 5.7494867

Sheet 8.14
A2: 2015 - 2009 ތާވަލު 8.14: އެކިއެކި މައްސަލަތަކުގައި ހައްޔަރުކުރެވުނު މީހުންގެ ތެރޭން ތަކުރާރުކޮށް ހައްޔަރުކުރެވުނު މީހުންގެ އަދަދު،
A3: Table 8.14: NUMBER OF DETAINEES BY NUMBER OF TIMES ARRESTED, 2009 - 2015
A4: No. of times arrested | B4: 2009 | C4: 2010 | D4: 2011 | E4: 2012 | F4: 2013 | G4: 2014 | H4: 2015 | I4: ހައްޔަރު ކުރެވުނު އަދަދު
A5: Total | B5: =SUM(B6:B15) -> 5081 | C5: =SUM(C6:C15) -> 4140 | D5: =SUM(D6:D15) -> 5279 | E5: =SUM(E6:E15) -> 6339 | F5: =SUM(F6:F18) -> 6981 | G5: =SUM(G6:G18) -> 6983 | H5: =SUM(H6:H18) -> 5827 | I5: ޖުމްލަ
A6: 1 | B6: 3700 | C6: 3347 | D6: 4086 | E6: 4710 | F6: 4666 | G6: 4443 | H6: 4118 | I6: 1
A7: 2 | B7: 840 | C7: 569 | D7: 810 | E7: 1031 | F7: 1255 | G7: 1274 | H7: 1002 | I7: 2
A8: 3 | B8: 326 | C8: 158 | D8: 263 | E8: 367 | F8: 543 | G8: 594 | H8: 362 | I8: 3
A9: 4 | B9: 141 | C9: 47 | D9: 84 | E9: 148 | F9: 258 | G9: 308 | H9: 157 | I9: 4
A10: 5 | B10: 51 | C10: 13 | D10: 26 | E10: 59 | F10: 124 | G10: 168 | H10: 81 | I10: 5
A11: 6 | B11: 14 | C11: 5 | D11: 7 | E11: 17 | F11: 68 | G11: 85 | H11: 47 | I11: 6
A12: 7 | B12: 6 | C12: 1 | D12: 2 | E12: 4 | F12: 33 | G12: 52 | H12: 26 | I12: 7
A13: 8 | B13: 2 | C13: 0 | D13: 1 | E13: 1 | F13: 15 | G13: 27 | H13: 13 | I13: 8
A14: 9 | B14: 1 | C14: 0 | D14: 0 | E14: 1 | F14: 9 | G14: 18 | H14: 12 | I14: 9
A15: 10 | B15: 0 | C15: 0 | D15: 0 | E15: 1 | F15: 6 | G15: 8 | H15: 5 | I15: 10
A16: 11 | B16: 0 | C16: 0 | D16: 0 | E16: 0 | F16: 2 | G16: 4 | H16: 3 | I16: 11
A17: 12 | B17: 0 | C17: 0 | D17: 0 | E17: 0 | F17: 1 | G17: 2 | H17: 1 | I17: 12
A18: 13 | B18: 0 | C18: 0 | D18: 0 | E18: 0 | F18: 1 | G18: 0 | H18: 0 | I18: 13
A19: Source: Maldives Police Service | I19: މަޢުލޫމާތު ދެއްވީ: މޯލްޑިވްސް ޕޮލިސް ސަރވިސް
R28: 1 | S28: 4118
R29: 2 | S29: 1002
R30: 3 | S30: 362
R31: 4 | S31: 157
R32: 5 | S32: 81
R33: more than 6 | S33: 107

Sheet 8.15
A2: ތާވަލު 8.15: ހުށަހެޅިފައިވާ މައްސަލަތަކުގެ ތެރެއިން ހައްޔަރުކުރެވުނު މީހުންގެ އަދަދު ޖިންސް އަދި އުމުރުފުރާއިން، 2015
A3: Table 8.15: NUMBER OF DETAINEES REPORTED BY TYPE OF OFFENCES, GENDER AND AGE GROUP, 2015
A5: Type of offence | B5: Both sexes | G5: Male | L5: Female | P5: ކުށުގެ ބާވަތް
B6: ދެޖިންސް | G6: ފިރިހެން | L6: އަންހެން
B7: Total | C7: < 18 | D7: 18 - 34 | E7: 35 + | G7: Total | H7: < 18 | I7: 18 - 34 | J7: 35 + | L7: Total | M7: < 18 | N7: 18 - 34 | O7: 35 +
B8: ޖުމްލަ | C8: 18 އަހަރުންދަށް | D8: 18-34 އަހަރާއި ދެމެދު | E8: 35 އަހަރުން މަތި | G8: ޖުމްލަ | H8: 18 އަހަރުންދަށް | I8: 18-34 އަހަރާއި ދެމެދު | J8: 35 އަހަރުން މަތި | L8: ޖުމްލަ | M8: 18 އަހަރުންދަށް | N8: 18-34 އަހަރާއި ދެމެދު | O8: 35 އަހަރުން މަތި
A9: Total | B9: =G9+L9 -> 5827 | C9: =H9+M9 -> 278 | D9: =I9+N9 -> 4365 | E9: =J9+O9 -> 1184 | G9: =SUM(H9:J9) -> 5547 | H9: =SUM(H10:H21) -> 255 | I9: =SUM(I10:I21) -> 4159 | J9: =SUM(J10:J21) -> 1133 | L9: =SUM(M9:O9) -> 280 | M9: =SUM(M10:M21) -> 23 | N9: =SUM(N10:N21) -> 206 | O9: =SUM(O10:O21) -> 51 | P9: ޖުމްލަ
A10: Assault | B10: =G10+L10 -> 577 | C10: =H10+M10 -> 41 | D10: =I10+N10 -> 464 | E10: =J10+O10 -> 72 | G10: =SUM(H10:J10) -> 564 | H10: 40 | I10: 453 | J10: 71 | L10: =SUM(M10:O10) -> 13 | M10: 1 | N10: 11 | O10: 1 | P10: މާރާމާރީ
A11: Theft | B11: =G11+L11 -> 1192 | C11: =H11+M11 -> 44 | D11: =I11+N11 -> 935 | E11: =J11+O11 -> 213 | G11: =SUM(H11:J11) -> 1163 | H11: 44 | I11: 913 | J11: 206 | L11: =SUM(M11:O11) -> 29 | M11: 0 | N11: 22 | O11: 7 | P11: ވައްކަން
A12: Robbery | B12: =G12+L12 -> 143 | C12: =H12+M12 -> 8 | D12: =I12+N12 -> 120 | E12: =J12+O12 -> 15 | G12: =SUM(H12:J12) -> 132 | H12: 8 | I12: 110 | J12: 14 | L12: =SUM(M12:O12) -> 11 | M12: 0 | N12: 10 | O12: 1 | P12: ފޭރުން | Z12: < 18 yrs | AA12: 18 - 34 yrs | AB12: 35 yrs and above
A13: Drugs | B13: =G13+L13 -> 2349 | C13: =H13+M13 -> 118 | D13: =I13+N13 -> 1773 | E13: =J13+O13 -> 458 | G13: =SUM(H13:J13) -> 2234 | H13: 107 | I13: 1686 | J13: 441 | L13: =SUM(M13:O13) -> 115 | M13: 11 | N13: 87 | O13: 17 | P13: މަސްތުވާތަކެތި | Z13: =C9 -> 278 | AA13: =D9 -> 4365 | AB13: =E9 -> 1184
A14: Sexual Offences | B14: =G14+L14 -> 325 | C14: =H14+M14 -> 14 | D14: =I14+N14 -> 196 | E14: =J14+O14 -> 115 | G14: =SUM(H14:J14) -> 290 | H14: 11 | I14: 170 | J14: 109 | L14: =SUM(M14:O14) -> 35 | M14: 3 | N14: 26 | O14: 6 | P14: ޖިންސީ މައްސަލަ
A15: Traffic | B15: =G15+L15 -> 9 | C15: =H15+M15 -> 4 | D15: =I15+N15 -> 4 | E15: =J15+O15 -> 1 | G15: =SUM(H15:J15) -> 9 | H15: 4 | I15: 4 | J15: 1 | L15: =SUM(M15:O15) -> 0 | M15: 0 | N15: 0 | O15: 0 | P15: ޓްރެފިކް | AA15: =SUM(AA16:AA17) -> 5827
A16: Domestic violence | B16: =G16+L16 -> 55 | C16: =H16+M16 -> 5 | D16: =I16+N16 -> 34 | E16: =J16+O16 -> 16 | G16: =SUM(H16:J16) -> 43 | H16: 5 | I16: 24 | J16: 14 | L16: =SUM(M16:O16) -> 12 | M16: 0 | N16: 10 | O16: 2 | P16: އާއިލީ | Z16: Male | AA16: =G9 -> 5547 | AB16: =AA16/AA15*100 -> 95.194783
A17: Counterfeit and forgery | B17: =G17+L17 -> 12 | C17: =H17+M17 -> 0 | D17: =I17+N17 -> 9 | E17: =J17+O17 -> 3 | G17: =SUM(H17:J17) -> 12 | H17: 0 | I17: 9 | J17: 3 | L17: =SUM(M17:O17) -> 0 | M17: 0 | N17: 0 | O17: 0 | P17: ވަގުފައިސާ | Z17: Female | AA17: =L9 -> 280 | AB17: =AA17/AA16*100 -> 5.0477736
A18: Vandalism | B18: =G18+L18 -> 126 | C18: =H18+M18 -> 18 | D18: =I18+N18 -> 92 | E18: =J18+O18 -> 16 | G18: =SUM(H18:J18) -> 121 | H18: 14 | I18: 91 | J18: 16 | L18: =SUM(M18:O18) -> 5 | M18: 4 | N18: 1 | O18: 0 | P18: މުދަލަށް ގެއްލުންދިނުން
A19: Embezzlement | B19: =G19+L19 -> 63 | C19: =H19+M19 -> 0 | D19: =I19+N19 -> 42 | E19: =J19+O19 -> 21 | G19: =SUM(H19:J19) -> 60 | H19: 0 | I19: 40 | J19: 20 | L19: =SUM(M19:O19) -> 3 | M19: 0 | N19: 2 | O19: 1 | P19: މަކަރާއި ޙީލަތް
A20: Lost items | B20: =G20+L20 -> 2 | C20: =H20+M20 -> 0 | D20: =I20+N20 -> 2 | E20: =J20+O20 -> 0 | G20: =SUM(H20:J20) -> 1 | H20: 0 | I20: 1 | J20: 0 | L20: =SUM(M20:O20) -> 1 | M20: 0 | N20: 1 | O20: 0 | P20: ގެއްލޭތަކެތި
A21: Others | B21: =G21+L21 -> 974 | C21: =H21+M21 -> 26 | D21: =I21+N21 -> 694 | E21: =J21+O21 -> 254 | G21: =SUM(H21:J21) -> 918 | H21: 22 | I21: 658 | J21: 238 | L21: =SUM(M21:O21) -> 56 | M21: 4 | N21: 36 | O21: 16 | P21: އެހެނިހެން | AA21: Male | AB21: Female
A22: Source: Maldives Police Service | P22: މަޢުލޫމާތު ދެއްވީ: މޯލްޑިވްސް ޕޮލިސް ސަރވިސް | Z22: < 18 yrs | AA22: =H9 -> 255 | AB22: =M9 -> 23
Z23: 18 - 34 yrs | AA23: =I9 -> 4159 | AB23: =N9 -> 206
Z24: 35 yrs and above | AA24: =J9 -> 1133 | AB24: =O9 -> 51

Sheet 8.16
A1: ތާވަލް 8.16: ހައްޔަރު ކުރެވުނު ދިވެހިންނާއި ބިދޭސީންގެ އަދަދު، 2011 - 2015
A2: Table: 8.16 NUMBER OF LOCAL AND FOREIGN DETAINEES BY TYPE OF OFFENCES, 2011 - 2015
A4: Type of Offence | B4: ޖުމްލަ | C4: ދިވެހިން | D4: ބިދޭސީ | E4: ޖުމްލަ | F4: ދިވެހިން | G4: ބިދޭސީ | H4: ޖުމްލަ | I4: ދިވެހިން | J4: ބިދޭސީ | K4: ޖުމްލަ | L4: ދިވެހިން | M4: ބިދޭސީ | N4: ޖުމްލަ | O4: ދިވެހިން | P4: ބިދޭސީ | Q4: ޖުމްލަ | R4: ދިވެހިން | S4: ބިދޭސީ | T4: ކުށުގެ ބާވަތް
B5: Total | C5: Locals | D5: Foreign | E5: Total | F5: Locals | G5: Foreign | H5: Total | I5: Locals | J5: Foreign | K5: Total | L5: Locals | M5: Foreign | N5: Total | O5: Locals | P5: Foreign | Q5: Total | R5: Locals | S5: Foreign
B6: 2010 | E6: 2011 | H6: 2012 | K6: 2013 | N6: 2014 | Q6: 2015 | W6: Locals | X6: Foreigners
A7: Total | B7: 4141 | C7: 3533 | D7: =SUM(D8:D19) -> 608 | E7: =SUM(E8:E19) -> 5279 | F7: =SUM(F8:F19) -> 4554 | G7: =SUM(G8:G19) -> 725 | H7: =I7+J7 -> 6339 | I7: =SUM(I8:I19) -> 5734 | J7: =SUM(J8:J19) -> 605 | K7: =L7+M7 -> 6981 | L7: =SUM(L8:L19) -> 6422 | M7: =SUM(M8:M19) -> 559 | N7: =O7+P7 -> 6983 | O7: =SUM(O8:O19) -> 6555 | P7: =SUM(P8:P19) -> 428 | Q7: =R7+S7 -> 5827 | R7: =SUM(R8:R19) -> 5446 | S7: =SUM(S8:S19) -> 381 | T7: ޖުމްލަ | W7: =R7/Q7*100 -> 93.461472 | X7: =S7/Q7*100 -> 6.5385275
A8: Assault | B8: 945 | C8: 857 | D8: 88 | E8: 967 | F8: 884 | G8: 83 | H8: =I8+J8 -> 677 | I8: 624 | J8: 53 | K8: =L8+M8 -> 668 | L8: 620 | M8: 48 | N8: =O8+P8 -> 556 | O8: 514 | P8: 42 | Q8: =R8+S8 -> 577 | R8: 538 | S8: 39 | T8: މާރާމާރީ
A9: Theft | B9: 774 | C9: 663 | D9: 111 | E9: 1149 | F9: 1034 | G9: 115 | H9: =I9+J9 -> 1474 | I9: 1379 | J9: 95 | K9: =L9+M9 -> 1613 | L9: 1523 | M9: 90 | N9: =O9+P9 -> 1593 | O9: 1501 | P9: 92 | Q9: =R9+S9 -> 1192 | R9: 1126 | S9: 66 | T9: ވައްކަން
A10: Robbery | B10: 199 | C10: 186 | D10: 13 | E10: 292 | F10: 263 | G10: 29 | H10: =I10+J10 -> 277 | I10: 272 | J10: 5 | K10: =L10+M10 -> 268 | L10: 258 | M10: 10 | N10: =O10+P10 -> 243 | O10: 240 | P10: 3 | Q10: =R10+S10 -> 143 | R10: 141 | S10: 2 | T10: ފޭރުން
A11: Drugs | B11: 1160 | C11: 1104 | D11: 56 | E11: 1453 | F11: 1394 | G11: 59 | H11: =I11+J11 -> 2073 | I11: 1969 | J11: 104 | K11: =L11+M11 -> 2906 | L11: 2799 | M11: 107 | N11: =O11+P11 -> 3316 | O11: 3209 | P11: 107 | Q11: =R11+S11 -> 2349 | R11: 2262 | S11: 87 | T11: މަސްތުވާތަކެތި
A12: Sexual Offences | B12: 299 | C12: 221 | D12: 78 | E12: 447 | F12: 328 | G12: 119 | H12: =I12+J12 -> 423 | I12: 290 | J12: 133 | K12: =L12+M12 -> 404 | L12: 302 | M12: 102 | N12: =O12+P12 -> 310 | O12: 235 | P12: 75 | Q12: =R12+S12 -> 325 | R12: 258 | S12: 67 | T12: ޖިންސީ މައްސަލަ
A13: Traffic | B13: 9 | C13: 9 | D13: 0 | E13: 9 | F13: 8 | G13: 1 | H13: =I13+J13 -> 12 | I13: 12 | J13: 0 | K13: =L13+M13 -> 6 | L13: 6 | M13: 0 | N13: =O13+P13 -> 11 | O13: 11 | P13: 0 | Q13: =R13+S13 -> 9 | R13: 9 | S13: 0 | T13: ޓްރެފިކް
A14: Domestic violence | B14: 11 | C14: 11 | D14: 0 | E14: 34 | F14: 30 | G14: 4 | H14: =I14+J14 -> 36 | I14: 35 | J14: 1 | K14: =L14+M14 -> 33 | L14: 33 | M14: 0 | N14: =O14+P14 -> 38 | O14: 37 | P14: 1 | Q14: =R14+S14 -> 55 | R14: 52 | S14: 3 | T14: އާއިލީ
A15: Counterfeit and forgery | B15: 31 | C15: 19 | D15: 12 | E15: 52 | F15: 25 | G15: 27 | H15: =I15+J15 -> 24 | I15: 16 | J15: 8 | K15: =L15+M15 -> 30 | L15: 23 | M15: 7 | N15: =O15+P15 -> 10 | O15: 9 | P15: 1 | Q15: =R15+S15 -> 12 | R15: 8 | S15: 4 | T15: ވަގުފައިސާ
A16: Vandalism | B16: 79 | C16: 78 | D16: 1 | E16: 106 | F16: 104 | G16: 2 | H16: =I16+J16 -> 149 | I16: 135 | J16: 14 | K16: =L16+M16 -> 122 | L16: 121 | M16: 1 | N16: =O16+P16 -> 147 | O16: 145 | P16: 2 | Q16: =R16+S16 -> 126 | R16: 123 | S16: 3 | T16: މުދަލަށް ގެއްލުންދިނުން
A17: Embezzlement | B17: 52 | C17: 29 | D17: 23 | E17: 60 | F17: 39 | G17: 21 | H17: =I17+J17 -> 40 | I17: 29 | J17: 11 | K17: =L17+M17 -> 59 | L17: 51 | M17: 8 | N17: =O17+P17 -> 80 | O17: 60 | P17: 20 | Q17: =R17+S17 -> 63 | R17: 44 | S17: 19 | T17: މަކަރާއި ޙީލަތް
A18: Lost items | B18: 12 | C18: 10 | D18: 2 | E18: 7 | F18: 5 | G18: 2 | H18: =I18+J18 -> 7 | I18: 4 | J18: 3 | K18: =L18+M18 -> 3 | L18: 3 | M18: 0 | N18: =O18+P18 -> 2 | O18: 2 | P18: 0 | Q18: =R18+S18 -> 2 | R18: 2 | S18: 0 | T18: ގެއްލޭތަކެތި
A19: Others | B19: 570 | C19: 346 | D19: 224 | E19: 703 | F19: 440 | G19: 263 | H19: =I19+J19 -> 1147 | I19: 969 | J19: 178 | K19: =L19+M19 -> 869 | L19: 683 | M19: 186 | N19: =O19+P19 -> 677 | O19: 592 | P19: 85 | Q19: =R19+S19 -> 974 | R19: 883 | S19: 91 | T19: އެހެނިހެން
A20: Source: Maldives Police Service | T20: މަޢުލޫމާތު ދެއްވީ: މޯލްޑިވްސް ޕޮލިސް ސަރވިސް

Sheet 8.17
A1: ތާވަލު 8.17: ފުލުހުންގެ ޚިދުމަތުގައި ތިބީ މީހުންގެ އަދަދު އަދި ހިނގި ޚަރަދު، 2010 - 2015
A2: TABLE 8.17: POLICE PERSONNEL BY SEX AND FINANCIAL RESOURCES, 2010 - 2015
A4: Details | B4: Year އަހަރު | H4: ތަފްސީލް
B5: 2010 | C5: 2011 | D5: 2012 | E5: 2013 | F5: 2014 | G5: 2015
A6: Total police personnel | B6: =SUM(B7:B8) -> 2933 | C6: =SUM(C7:C8) -> 2975 | D6: =SUM(D7:D8) -> 3217 | E6: =SUM(E7:E8) -> 3003 | F6: =SUM(F7:F8) -> 3214 | G6: =SUM(G7:G8) -> 3820 | H6: ޖުމްލަ ފުލުހުންގެ އަދަދު
A7: Male | B7: 2640 | C7: 2690 | D7: 2923 | E7: 2732 | F7: 2938 | G7: 3360 | H7: ފިރިހެން
A8: Female | B8: 293 | C8: 285 | D8: 294 | E8: 271 | F8: 276 | G8: 460 | H8: އަންހެން
A9: Total police expenditure (million MVR) | B9: 714.5059 | C9: 743.81639 | D9: 837.16104 | E9: 902.77046 | F9: 1049.5819 | G9: 1062.91 | H9: ފުލުހުންނަށް ހިނގި ޚަރަދު (މިލިއަން ރުފިޔާ)
A10: Source: Maldives Police Service | H10: މަޢުލޫމާތު ދެއްވީ: މޯލްޑިވްސް ޕޮލިސް ސަރވިސް

Sheet 8.20 workings
A1: ތާވަލު 8.9: ހުށަހެޅުނު، ނިމުނު އަދި ނުނިމެ ހުރި މައްސަލަތައް، 2012
A2: Table 8.9: CASES FILED, CONCLUDED AND PENDING BY CASE TYPE, 2012
C3: Criminal Cases | J3: Criminal Cases above 18 | P3: Criminal Cases below 18 | X3: Civil Cases | AE3: Family Cases
C4: Starting Balance | D4: New cases filed | E4: Total | F4: Concluded | G4: Ending Balance | H4: % share completed | I4: % share pending | J4: Starting Balance | K4: New cases filed | L4: Total | M4: Concluded | N4: Ending Balance | O4: % share completed | P4: Starting Balance | Q4: New cases filed | R4: Total | S4: Concluded | T4: Ending Balance | U4: % share completed | X4: Starting Balance | Y4: New cases filed | Z4: Total | AA4: Concluded | AB4: Ending Balance | AC4: % share completed | AE4: Starting Balance | AF4: New cases filed | AG4: Total | AH4: Concluded | AI4: Ending Balance | AJ4: % share completed
B5: Republic | C5: =J5+P5 -> 3010 | D5: =K5+Q5 -> 2381 | E5: =L5+R5 -> 5391 | F5: =M5+S5 -> 1774 | G5: =N5+T5 -> 3617 | H5: =F5/E5*100 -> 32.906696 | I5: =G5/E5*100 -> 67.093304 | J5: 2893 | K5: 2200 | L5: 5093 | M5: 1617 | N5: 3476 | O5: =M5/L5*100 -> 31.74946 | P5: 117 | Q5: 181 | R5: 298 | S5: 157 | T5: 141 | U5: =S5/R5*100 -> 52.684564 | W5: Republic | X5: 3628 | Y5: 6873 | Z5: 10500 | AA5: 6554 | AB5: 3946 | AC5: =AA5/Z5*100 -> 62.419048 | AD5: Republic | AE5: 890 | AF5: 6097 | AG5: 6987 | AH5: 5904 | AI5: 1083 | AJ5: =AH5/AG5*100 -> 84.499785
B6: Male' | C6: =J6+P6 -> 2247 | D6: =K6+Q6 -> 1246 | E6: =L6+R6 -> 3493 | F6: =M6+S6 -> 1084 | G6: =N6+T6 -> 2409 | H6: =F6/E6*100 -> 31.033496 | I6: =G6/E6*100 -> 68.966504 | J6: 2193 | K6: 1163 | L6: 3356 | M6: 990 | N6: 2366 | O6: =M6/L6*100 -> 29.499404 | P6: 54 | Q6: 83 | R6: 137 | S6: 94 | T6: 43 | U6: =S6/R6*100 -> 68.613139 | W6: Male' | X6: 1847 | Y6: 2725 | Z6: 4571 | AA6: 2719 | AB6: 1852 | AC6: =AA6/Z6*100 -> 59.483702 | AD6: Male' | AE6: 456 | AF6: 2367 | AG6: 2823 | AH6: 2296 | AI6: 527 | AJ6: =AH6/AG6*100 -> 81.331916
B7: Atoll | C7: =J7+P7 -> 763 | D7: =K7+Q7 -> 1135 | E7: =L7+R7 -> 1898 | F7: =M7+S7 -> 690 | G7: =N7+T7 -> 1208 | H7: =F7/E7*100 -> 36.354057 | I7: =G7/E7*100 -> 63.645943 | J7: 700 | K7: 1037 | L7: 1737 | M7: 627 | N7: 1110 | O7: =M7/L7*100 -> 36.096718 | P7: 63 | Q7: 98 | R7: 161 | S7: 63 | T7: 98 | U7: =S7/R7*100 -> 39.130435 | W7: Atoll | X7: 1781 | Y7: 4148 | Z7: 5929 | AA7: 3835 | AB7: 2094 | AC7: =AA7/Z7*100 -> 64.682071 | AD7: Atoll | AE7: 434 | AF7: 3730 | AG7: 4164 | AH7: 3608 | AI7: 556 | AJ7: =AH7/AG7*100 -> 86.647454
A8: HA | B8: Total | C8: =J8+P8 -> 68 | D8: =K8+Q8 -> 28 | E8: =L8+R8 -> 96 | F8: =M8+S8 -> 21 | G8: =N8+T8 -> 75 | J8: 61 | K8: 27 | L8: 88 | M8: 18 | N8: 70 | P8: 7 | Q8: 1 | R8: 8 | S8: 3 | T8: 5 | X8: 123 | Y8: 181 | Z8: 304 | AA8: 148 | AB8: 156 | AE8: 21 | AF8: 169 | AG8: 190 | AH8: 170 | AI8: 20
A9: HDh | B9: Total | C9: =J9+P9 -> 81 | D9: =K9+Q9 -> 73 | E9: =L9+R9 -> 154 | F9: =M9+S9 -> 41 | G9: =N9+T9 -> 113 | J9: 74 | K9: 69 | L9: 143 | M9: 34 | N9: 109 | P9: 7 | Q9: 4 | R9: 11 | S9: 7 | T9: 4 | X9: 93 | Y9: 178 | Z9: 271 | AA9: 104 | AB9: 167 | AE9: 34 | AF9: 233 | AG9: 267 | AH9: 222 | AI9: 45
A10: Sh | B10: Total | C10: =J10+P10 -> 10 | D10: =K10+Q10 -> 24 | E10: =L10+R10 -> 34 | F10: =M10+S10 -> 28 | G10: =N10+T10 -> 6 | J10: 10 | K10: 22 | L10: 32 | M10: 28 | N10: 4 | P10: 0 | Q10: 2 | R10: 2 | S10: 0 | T10: 2 | X10: 43 | Y10: 145 | Z10: 188 | AA10: 142 | AB10: 46 | AE10: 16 | AF10: 162 | AG10: 178 | AH10: 162 | AI10: 16
A11: N | B11: Total | C11: =J11+P11 -> 48 | D11: =K11+Q11 -> 62 | E11: =L11+R11 -> 110 | F11: =M11+S11 -> 45 | G11: =N11+T11 -> 65 | J11: 47 | K11: 58 | L11: 105 | M11: 42 | N11: 63 | P11: 1 | Q11: 4 | R11: 5 | S11: 3 | T11: 2 | X11: 117 | Y11: 186 | Z11: 303 | AA11: 174 | AB11: 129 | AE11: 30 | AF11: 215 | AG11: 245 | AH11: 188 | AI11: 57
A12: R | B12: Total | C12: =J12+P12 -> 73 | D12: =K12+Q12 -> 84 | E12: =L12+R12 -> 157 | F12: =M12+S12 -> 80 | G12: =N12+T12 -> 77 | J12: 70 | K12: 78 | L12: 148 | M12: 76 | N12: 72 | P12: 3 | Q12: 6 | R12: 9 | S12: 4 | T12: 5 | X12: 71 | Y12: 202 | Z12: 273 | AA12: 186 | AB12: 87 | AE12: 18 | AF12: 231 | AG12: 249 | AH12: 219 | AI12: 30
A13: B | B13: Total | C13: =J13+P13 -> 21 | D13: =K13+Q13 -> 26 | E13: =L13+R13 -> 47 | F13: =M13+S13 -> 10 | G13: =N13+T13 -> 37 | J13: 17 | K13: 23 | L13: 40 | M13: 9 | N13: 31 | P13: 4 | Q13: 3 | R13: 7 | S13: 1 | T13: 6 | X13: 38 | Y13: 183 | Z13: 221 | AA13: 119 | AB13: 102 | AE13: 20 | AF13: 135 | AG13: 155 | AH13: 124 | AI13: 31
A14: Lh | B14: Total | C14: =J14+P14 -> 77 | D14: =K14+Q14 -> 61 | E14: =L14+R14 -> 138 | F14: =M14+S14 -> 57 | G14: =N14+T14 -> 81 | J14: 72 | K14: 57 | L14: 129 | M14: 52 | N14: 77 | P14: 5 | Q14: 4 | R14: 9 | S14: 5 | T14: 4 | X14: 124 | Y14: 124 | Z14: 248 | AA14: 127 | AB14: 121 | AE14: 44 | AF14: 178 | AG14: 222 | AH14: 182 | AI14: 40
A15: K | B15: Total | C15: =J15+P15 -> 31 | D15: =K15+Q15 -> 41 | E15: =L15+R15 -> 72 | F15: =M15+S15 -> 31 | G15: =N15+T15 -> 41 | J15: 30 | K15: 37 | L15: 67 | M15: 30 | N15: 37 | P15: 1 | Q15: 4 | R15: 5 | S15: 1 | T15: 4 | X15: 67 | Y15: 145 | Z15: 212 | AA15: 153 | AB15: 59 | AE15: 17 | AF15: 218 | AG15: 235 | AH15: 217 | AI15: 18
A16: AA | B16: Total | C16: =J16+P16 -> 13 | D16: =K16+Q16 -> 13 | E16: =L16+R16 -> 26 | F16: =M16+S16 -> 11 | G16: =N16+T16 -> 15 | J16: 12 | K16: 11 | L16: 23 | M16: 11 | N16: 12 | P16: 1 | Q16: 2 | R16: 3 | S16: 0 | T16: 3 | X16: 58 | Y16: 123 | Z16: 181 | AA16: 142 | AB16: 39 | AE16: 9 | AF16: 123 | AG16: 132 | AH16: 126 | AI16: 6
A17: ADh | B17: Total | C17: =J17+P17 -> 14 | D17: =K17+Q17 -> 18 | E17: =L17+R17 -> 32 | F17: =M17+S17 -> 23 | G17: =N17+T17 -> 9 | J17: 13 | K17: 16 | L17: 29 | M17: 22 | N17: 7 | P17: 1 | Q17: 2 | R17: 3 | S17: 1 | T17: 2 | X17: 78 | Y17: 145 | Z17: 223 | AA17: 155 | AB17: 68 | AE17: 25 | AF17: 141 | AG17: 166 | AH17: 138 | AI17: 28
A18: V | B18: Total | C18: =J18+P18 -> 2 | D18: =K18+Q18 -> 1 | E18: =L18+R18 -> 3 | F18: =M18+S18 -> 2 | G18: =N18+T18 -> 1 | J18: 2 | K18: 1 | L18: 3 | M18: 2 | N18: 1 | P18: 0 | Q18: 0 | R18: 0 | S18: 0 | T18: 0 | X18: 6 | Y18: 33 | Z18: 39 | AA18: 28 | AB18: 11 | AE18: 2 | AF18: 19 | AG18: 21 | AH18: 21 | AI18: 0
A19: M | B19: Total | C19: =J19+P19 -> 4 | D19: =K19+Q19 -> 4 | E19: =L19+R19 -> 8 | F19: =M19+S19 -> 3 | G19: =N19+T19 -> 5 | J19: 4 | K19: 3 | L19: 7 | M19: 3 | N19: 4 | P19: 0 | Q19: 1 | R19: 1 | S19: 0 | T19: 1 | X19: 89 | Y19: 62 | Z19: 151 | AA19: 109 | AB19: 42 | AE19: 6 | AF19: 72 | AG19: 78 | AH19: 71 | AI19: 7
... A32: Male' | B32: HulhuMale' Court | C32: =J32+P32 -> 2 | D32: =K32+Q32 -> 5 | E32: =L32+R32 -> 7 | F32: =M32+S32 -> 0 | G32: =N32+T32 -> 7 | J32: 2 | K32: 5 | L32: 7 | M32: 0 | N32: 7 | P32: 0 | Q32: 0 | R32: 0 | S32: 0 | T32: 0 | X32: 111 | Y32: 448 | Z32: 558 | AA32: 307 | AB32: 251 | AE32: 5 | AF32: 116 | AG32: 121 | AH32: 102 | AI32: 19
A33: Source: Department of Judicial Administration | AI33: cnwxErcTcsinimcDea clwxiDuj cfoa cTcnwmcTWpiD : utWmUluAwm
B36: % share completed
B37: Criminal Cases | C37: Civil cases | D37: Family Cases
A38: Republic | B38: =H5 -> 32.906696 | C38: =AC5 -> 62.419048 | D38: =AJ5 -> 84.499785
A39: Male' | B39: =H6 -> 31.033496 | C39: =AC6 -> 59.483702 | D39: =AJ6 -> 81.331916
A40: Atoll | B40: =H7 -> 36.354057 | C40: =AC7 -> 64.682071 | D40: =AJ7 -> 86.647454
B42: ending balance
B43: Criminal Cases | C43: Civil cases | D43: Family Cases
A44: Republic | B44: =G5 -> 3617 | C44: =AB5 -> 3946 | D44: =AI5 -> 1083
A45: Male' | B45: =G6 -> 2409 | C45: =AB6 -> 1852 | D45: =AI6 -> 527
A46: Atoll | B46: =G7 -> 1208 | C46: =AB7 -> 2094 | D46: =AI7 -> 556
B49: concluded
B50: Criminal Cases | C50: Civil cases | D50: Family Cases
A51: Republic | B51: =F5 -> 1774 | C51: =AA5 -> 6554 | D51: =AH5 -> 5904
A52: Male' | B52: =F6 -> 1084 | C52: =AA6 -> 2719 | D52: =AH6 -> 2296
A53: Atoll | B53: =F7 -> 690 | C53: =AA7 -> 3835 | D53: =AH7 -> 3608
A55: Total
B56: Republic | C56: Male' | D56: Atolls
A57: Starting balance | B57: 7528 | C57: 4550 | D57: 2978
A58: new cases filed | B58: 15351 | C58: 6338 | D58: 9013
A59: concluded | B59: 14232 | C59: 6099 | D59: 8133
A60: ending balance | B60: 8646 | C60: 4788 | D60: 3858
B66: Atoll : All cases
H67: taken from table 8.19
C68: All cases submitted | D68: Completed | E68: Pending | F68: completion rate | H68: no. of majistrates | I68: cases per majistrate | J68: cases completed per majistrate
B69: HA | C69: 590 | D69: 339 | E69: 251 | F69: =D69/C69*100 -> 57.457627 | H69: 10 | I69: =C69/H69 -> 59 | J69: =D69/H69 -> 33.9
B70: HDh | C70: 692 | D70: 367 | E70: 325 | F70: =D70/C70*100 -> 53.034682 | H70: 8 | I70: =C70/H70 -> 86.5 | J70: =D70/H70 -> 45.875
B71: Sh | C71: 400 | D71: 332 | E71: 68 | F71: =D71/C71*100 -> 83 | H71: 4 | I71: =C71/H71 -> 100 | J71: =D71/H71 -> 83
B72: N | C72: 658 | D72: 407 | E72: 251 | F72: =D72/C72*100 -> 61.854103 | H72: 5 | I72: =C72/H72 -> 131.6 | J72: =D72/H72 -> 81.4
B73: R | C73: 679 | D73: 485 | E73: 194 | F73: =D73/C73*100 -> 71.428571 | H73: 7 | I73: =C73/H73 -> 97 | J73: =D73/H73 -> 69.285714
B74: B | C74: 423 | D74: 253 | E74: 170 | F74: =D74/C74*100 -> 59.810875 | H74: 5 | I74: =C74/H74 -> 84.6 | J74: =D74/H74 -> 50.6
B75: Lh | C75: 608 | D75: 366 | E75: 242 | F75: =D75/C75*100 -> 60.197368 | H75: 1 | I75: =C75/H75 -> 608 | J75: =D75/H75 -> 366
B76: K | C76: 519 | D76: 401 | E76: 118 | F76: =D76/C76*100 -> 77.263969 | H76: 8 | I76: =C76/H76 -> 64.875 | J76: =D76/H76 -> 50.125
B77: AA | C77: 339 | D77: 279 | E77: 60 | F77: =D77/C77*100 -> 82.300885 | H77: 7 | I77: =C77/H77 -> 48.428571 | J77: =D77/H77 -> 39.857143
B78: ADh | C78: 421 | D78: 316 | E78: 105 | F78: =D78/C78*100 -> 75.059382 | H78: 4 | I78: =C78/H78 -> 105.25 | J78: =D78/H78 -> 79
B79: V | C79: 63 | D79: 51 | E79: 12 | F79: =D79/C79*100 -> 80.952381 | H79: 2 | I79: =C79/H79 -> 31.5 | J79: =D79/H79 -> 25.5
B80: M | C80: 237 | D80: 183 | E80: 54 | F80: =D80/C80*100 -> 77.21519 | H80: 5 | I80: =C80/H80 -> 47.4 | J80: =D80/H80 -> 36.6
... B88: S | C88: 1123 | D88: 659 | E88: 464 | F88: =D88/C88*100 -> 58.682102 | H88: 8 | I88: =C88/H88 -> 140.375 | J88: =D88/H88 -> 82.375

Sheet 8.18
A1: 2015 - 2002 ,udwdwAeg WycaiFwq unumcnin iawgukwtuTOkuSwr iaWaelWm : 8.18 ulwvWt
A2: Table 8.18 : CASES DEALT BY JUDICIAL COURTS IN MALE' AND ISLANDS, 2002 - 2015
A3: Court | B3: 2002 | C3: 2003 | D3: 2004 | E3: 2005 | F3: 2006 | G3: 2007 | H3: 2008 | I3: 2009 | J3: 2010 | K3: 2011 | L3: 2012 | M3: 2013 | N3: 2014 | O3: 2015 | P3: ކޯޓުތައް
A4: Total | B4: =SUM(B5:B9) -> 12390 | C4: =SUM(C5:C9) -> 11317 | D4: =SUM(D5:D9) -> 10776 | E4: =SUM(E5:E9) -> 12107 | F4: =SUM(F5:F9) -> 14084 | G4: =SUM(G5:G9) -> 13820 | H4: =SUM(H5:H9) -> 12921 | I4: =SUM(I5:I10) -> 15997 | J4: =SUM(J5:J10) -> 15036 | K4: =SUM(K5:K10) -> 14710 | L4: =SUM(L5:L10) -> 14232 | M4: =SUM(M5:M10) -> 16189 | N4: =SUM(N5:N10) -> 18902 | O4: =SUM(O5:O10) -> 18101 | P4: wlcmuj
A5: Juvenile court | B5: 136 | C5: 210 | D5: 184 | E5: 86 | F5: 154 | G5: 103 | H5: 62 | I5: 105 | J5: 211 | K5: 123 | L5: 94 | M5: 122 | N5: 81 | O5: 26 | P5: ޖުވެނައިލް ކޯޓު
A6: Family court | B6: 1302 | C6: 1332 | D6: 1401 | E6: 1865 | F6: 2034 | G6: 1981 | H6: 2032 | I6: 2089 | J6: 2044 | K6: 1996 | L6: 2194 | M6: 2590 | N6: 2616 | O6: 2553 | P6: ފެމިލީ ކޯޓު
A7: Criminal court | B7: 1700 | C7: 1071 | D7: 798 | E7: 949 | F7: 1643 | G7: 2002 | H7: 1460 | I7: 2334 | J7: 1433 | K7: 1036 | L7: 990 | M7: 1669 | N7: 1957 | O7: 1069 | P7: ކްރިމިނަލް ކޯޓު
A8: Civil court | B8: 2292 | C8: 1953 | D8: 1618 | E8: 1940 | F8: 2119 | G8: 1958 | H8: 2181 | I8: 2754 | J8: 2493 | K8: 2262 | L8: 2412 | M8: 2154 | N8: 3203 | O8: 2283 | P8: ސިވިލް ކޯޓު
A9: Magistrate Courts | B9: 6960 | C9: 6751 | D9: 6775 | E9: 7267 | F9: 8134 | G9: 7776 | H9: 7186 | I9: 8661 | J9: 8747 | K9: 9178 | L9: 8133 | M9: 9159 | N9: 10529 | O9: 12170 | P9: އަތޮޅުތަކުގައި ހުރިމެޖިސްޓްރޭޓް ކޯޓުތައް
A10: Hulhu Male' court | B10: na | C10: na | D10: na | E10: na | F10: na | G10: na | H10: na | I10: 54 | J10: 108 | K10: 115 | L10: 409 | M10: 495 | N10: 516 | P10: ހުޅުމާލެ މެޖިސްޓްރޭޓް ކޯޓު
A11: Percentage share | P11: cniawtcaws ctogWviawfiheb
A12: Juvenile court | B12: =SUM(B5/B4)*100 -> 1.0976594 | C12: =SUM(C5/C4)*100 -> 1.8556154 | D12: =SUM(D5/D4)*100 -> 1.7074981 | E12: =SUM(E5/E4)*100 -> 0.71033287 | F12: =SUM(F5/F4)*100 -> 1.0934394 | G12: =SUM(G5/G4)*100 -> 0.74529667 | H12: =SUM(H5/H4)*100 -> 0.47983902 | I12: =SUM(I5/I4)*100 -> 0.65637307 | ... O12: =SUM(O5/O4)*100 -> 0.14363847 | P12: ޖުވެނައިލް ކޯޓު
A13: Family court | B13: =SUM(B6/B4)*100 -> 10.508475 | C13: =SUM(C6/C4)*100 -> 11.769904 | D13: =SUM(D6/D4)*100 -> 13.001114 | E13: =SUM(E6/E4)*100 -> 15.404312 | F13: =SUM(F6/F4)*100 -> 14.44192 | G13: =SUM(G6/G4)*100 -> 14.334298 | H13: =SUM(H6/H4)*100 -> 15.726337 | I13: =SUM(I6/I4)*100 -> 13.058699 | ... O13: =SUM(O6/O4)*100 -> 14.104193 | P13: ފެމިލީ ކޯޓު
A14: Criminal court | B14: =SUM(B7/B4)*100 -> 13.720743 | C14: =SUM(C7/C4)*100 -> 9.4636388 | D14: =SUM(D7/D4)*100 -> 7.4053452 | E14: =SUM(E7/E4)*100 -> 7.8384406 | F14: =SUM(F7/F4)*100 -> 11.66572 | G14: =SUM(G7/G4)*100 -> 14.486252 | H14: =SUM(H7/H4)*100 -> 11.299435 | I14: =SUM(I7/I4)*100 -> 14.590236 | ... O14: =SUM(O7/O4)*100 -> 5.9057511 | P14: ކްރިމިނަލް ކޯޓު
A15: Civil court | B15: =SUM(B8/B4)*100 -> 18.498789 | C15: =SUM(C8/C4)*100 -> 17.257224 | D15: =SUM(D8/D4)*100 -> 15.014848 | E15: =SUM(E8/E4)*100 -> 16.023788 | F15: =SUM(F8/F4)*100 -> 15.045442 | G15: =SUM(G8/G4)*100 -> 14.167873 | H15: =SUM(H8/H4)*100 -> 16.879498 | I15: =SUM(I8/I4)*100 -> 17.215728 | ... O15: =SUM(O8/O4)*100 -> 12.612563 | P15: ސިވިލް ކޯޓު
A16: Magistrate Courts | B16: =SUM(B9/B4)*100 -> 56.174334 | C16: =SUM(C9/C4)*100 -> 59.653618 | D16: =SUM(D9/D4)*100 -> 62.871195 | E16: =SUM(E9/E4)*100 -> 60.023127 | F16: =SUM(F9/F4)*100 -> 57.753479 | G16: =SUM(G9/G4)*100 -> 56.266281 | H16: =SUM(H9/H4)*100 -> 55.61489 | I16: =SUM(I9/I4)*100 -> 54.141402 | ... O16: =SUM(O9/O4)*100 -> 67.233854 | P16: އަތޮޅުތަކުގައި ހުރިމެޖިސްޓްރޭޓް ކޯޓުތައް
A17: Hulhu Male' court | B17: na | C17: na | D17: na | E17: na | F17: na | G17: na | H17: na | I17: 54 | J17: =SUM(J10/J4)*100 -> 0.71827614 | K17: =SUM(K10/K4)*100 -> 0.7817811 | L17: =SUM(L10/L4)*100 -> 2.8738055 | M17: =SUM(M10/M4)*100 -> 3.0576317 | N17: =SUM(N10/N4)*100 -> 2.7298699 | O17: =SUM(O10/O4)*100 -> 0 | P17: ހުޅުމާލެ މެޖިސްޓްރޭޓް ކޯޓު
A18: % Change over previous year | B18: 7 | C18: =(C4-B4)*100/B4 -> -8.6602098 | D18: =(D4-C4)*100/C4 -> -4.7804188 | E18: =(E4-D4)*100/D4 -> 12.351522 | F18: =(F4-E4)*100/E4 -> 16.329396 | G18: =(G4-F4)*100/F4 -> -1.8744675 | H18: =(H4-G4)*100/G4 -> -6.5050651 | I18: =(I4-H4)*100/H4 -> 23.806207 | J18: =(J4-I4)*100/I4 -> -6.0073764 | ... O18: =(O4-N4)*100/N4 -> -4.2376468 | P18: urwvcnim ivurutia eruvcSwrwhwa Iruk
A19: Juvenile court | B19: 27 | C19: =(C5-B5)*100/B5 -> 54.411765 | D19: =(D5-C5)*100/C5 -> -12.380952 | E19: =(E5-D5)*100/D5 -> -53.26087 | F19: =(F5-E5)*100/E5 -> 79.069767 | G19: =(G5-F5)*100/F5 -> -33.116883 | H19: =(H5-G5)*100/G5 -> -39.805825 | I19: =(I5-H5)*100/H5 -> 69.354839 | J19: =(J5-I5)*100/I5 -> 100.95238 | ... O19: =(O5-N5)*100/N5 -> -67.901235 | P19: ޖުވެނައިލް ކޯޓު
A20: Family court | B20: 58 | C20: =(C6-B6)*100/B6 -> 2.3041475 | D20: =(D6-C6)*100/C6 -> 5.1801802 | E20: =(E6-D6)*100/D6 -> 33.119201 | F20: =(F6-E6)*100/E6 -> 9.0616622 | G20: =(G6-F6)*100/F6 -> -2.605703 | H20: =(H6-G6)*100/G6 -> 2.5744573 | I20: =(I6-H6)*100/H6 -> 2.8051181 | J20: =(J6-I6)*100/I6 -> -2.1541407 | ... O20: =(O6-N6)*100/N6 -> -2.4082569 | P20: ފެމިލީ ކޯޓު
A21: Criminal court | B21: 3 | C21: =(C7-B7)*100/B7 -> -37 | D21: =(D7-C7)*100/C7 -> -25.490196 | E21: =(E7-D7)*100/D7 -> 18.922306 | F21: =(F7-E7)*100/E7 -> 73.12961 | G21: =(G7-F7)*100/F7 -> 21.850274 | H21: =(H7-G7)*100/G7 -> -27.072927 | I21: =(I7-H7)*100/H7 -> 59.863014 | J21: =(J7-I7)*100/I7 -> -38.603256 | ... O21: =(O7-N7)*100/N7 -> -45.375575 | P21: ކްރިމިނަލް ކޯޓު
A22: Civil court | B22: 0 | C22: =(C8-B8)*100/B8 -> -14.790576 | D22: =(D8-C8)*100/C8 -> -17.153098 | E22: =(E8-D8)*100/D8 -> 19.901112 | F22: =(F8-E8)*100/E8 -> 9.2268041 | G22: =(G8-F8)*100/F8 -> -7.5979235 | H22: =(H8-G8)*100/G8 -> 11.389173 | I22: =(I8-H8)*100/H8 -> 26.272352 | J22: =(J8-I8)*100/I8 -> -9.4771242 | ... O22: =(O8-N8)*100/N8 -> -28.723072 | P22: ސިވިލް ކޯޓު
A23: Magistrate Courts | B23: 4 | C23: -3.0028736 | D23: 0.35550289 | E23: 7.2619926 | F23: 11.930645 | G23: -4.4012786 | H23: -7.5874486 | I23: =(I9-H9)*100/H9 -> 20.526023 | J23: =(J9-I9)*100/I9 -> 0.99295693 | K23: =(K9-J9)*100/J9 -> 4.9274037 | L23: =(L9-K9)*100/K9 -> -11.385923 | M23: =(M9-L9)*100/L9 -> 12.615271 | N23: =(N9-M9)*100/M9 -> 14.957965 | O23: =(O9-N9)*100/N9 -> 15.585526 | P23: އަތޮޅުތަކުގައި ހުރިމެޖިސްޓްރޭޓް ކޯޓުތައް
A24: Hulhu Male' court | B24: na | C24: na | D24: na | E24: na | F24: na | G24: na | H24: na | I24: na | J24: =(J10-I10)*100/I10 -> 100 | K24: =(K10-J10)*100/J10 -> 6.4814815 | L24: =(L10-K10)*100/K10 -> 255.65217 | M24: =(M10-L10)*100/L10 -> 21.026895 | N24: =(N10-M10)*100/M10 -> 4.2424242 | O24: =(O10-N10)*100/N10 -> -100 | P24: ހުޅުމާލެ މެޖިސްޓްރޭޓް ކޯޓު
A25: Source: Department of Judicial Administration | P25: cnwxErcTcsinimcDea clwxiDuj cfoa cTcnwmcTWpiD : utWmUluAwm
J69: 2010 | K69: 2011 | L69: 2012 | M69: 2012 | N69: 2012 | O69: 2012 | P69: 2013 | Q69: 2014
I70: Juvenile court | J70: 211 | K70: 123 | L70: 94 | M70: 94 | N70: 94 | O70: 94 | P70: 122 | Q70: 81
I71: Family court | J71: 2044 | K71: 1996 | L71: 2194 | M71: 2194 | N71: 2194 | O71: 2194 | P71: 2590 | Q71: 2616
I72: Criminal court | J72: 1433 | K72: 1036 | L72: 990 | M72: 990 | N72: 990 | O72: 990 | P72: 1669 | Q72: 1957
I73: Civil court | J73: 2493 | K73: 2262 | L73: 2412 | M73: 2412 | N73: 2412 | O73: 2412 | P73: 2154 | Q73: 3203
I74: Magistrate Courts | J74: 8747 | K74: 9178 | L74: 8133 | M74: 8133 | N74: 8133 | O74: 8133 | P74: 9159 | Q74: 10529
I75: Hulhu Male' court | J75: 108 | K75: 115 | L75: 409 | M75: 409 | N75: 409 | O75: 409 | P75: 495 | Q75: 516

Sheet 8.19
A2: 2015 - 2014 ,wlwscawm unuLehwSuh cSwTOkiawh : 8.19 ulwvWt
A3: Table 8.19: CASES HANDLED BY THE HIGH COURT, 2014 - 2015
A5: Type of Cases | B5: 2013 | H5: 2014 | N5: 2015 | T5: ހުށައެޅުނު މައްސަލަތައް
B6: 2012 ނިމުނު އިރު ހުރި ބާކީ Cases awaiting trial 2012 | C6: 2013 ގައި ހުށަހެޅުނު Cases logged | D6: Cases logged trial including 2012 | E6: 2012 ވަނަ އަހަރުގެ ބާކީއާއެކު ޖުމުލަ ހުށަހެޅުނު | F6: 2013 ގައި ނިމުނު Cases dealt | G6: 2012 ވަނަ އަހަރުގެ ބާކީ އާއެކު 2013 ގައި ނުނިމިހުރި ޖުމުލަ Cases awaiting trial including 2012 | H6: 2013 ނިމުނު އިރު ހުރި ބާކީ، Cases awaiting trial 2013 | I6: 2014 ގައި ހުށަހެޅުނު Cases logged | J6: Cases logged trial including 2013 | K6: 2013 ވަނަ އަހަރުގެ ބާކީއާއެކު ޖުމުލަ ހުށަހެޅުނު | L6: 2014 ގައި ނިމުނު Cases dealt | M6: 2013 ވަނަ އަހަރުގެ ބާކީ އާއެކު 2014 ގައި ނުނިމިހުރި ޖުމުލަ Cases awaiting trial including 2013 | N6: 2014 ނިމުނު އިރު ހުރި ބާކީ، Cases awaiting trial 2014 | O6: 2015 ގައި ހުށަހެޅުނު Cases logged | P6: Cases logged trial including 2014 | Q6: 2014 ވަނަ އަހަރުގެ ބާކީއާއެކު ޖުމުލަ ހުށަހެޅުނު | R6: 2015 ގައި ނިމުނު Cases dealt | S6: 2014 ވަނަ އަހަރުގެ ބާކީ އާއެކު 2015 ގައި ނުނިމިހުރި ޖުމުލަ Cases awaiting trial including 2014
A7: Total | B7: 277 | C7: 401 | D7: 678 | F7: 389 | G7: 289 | H7: 289 | I7: 365 | J7: 654 | L7: 414 | M7: 238 | N7: 238 | O7: 413 | P7: 651 | R7: 329 | S7: 323 | T7: ޖުމްލަ
A8: No of cases appealed by private individuals | B8: 232 | C8: 306 | D8: 538 | F8: 325 | G8: 213 | H8: 213 | I8: 280 | J8: 493 | L8: 302 | M8: 198 | N8: 198 | O8: 355 | P8: 553 | R8: 277 | S8: 276 | T8: އިސްތިއުނާފްކުރުމަށް އަމިއްލަ ފަރާތްތަކުން ހުށަހެޅި މައްސަލަތަކުގެ އަދަދު (ވަކިވަކި ފަރުދުން/ކުންފުނި/ކޮމިޝަން/ކައުންސިލްތައް)
A9: No of cases appealed by the state | B9: 37 | C9: 84 | D9: 121 | F9: 55 | G9: 66 | H9: 66 | I9: 64 | J9: 130 | L9: 89 | M9: 33 | N9: 33 | O9: 51 | P9: 84 | R9: 46 | S9: 38 | T9: udwdwa egukwtwlwscawmi LehwSuh cnutwluawd cSwmurukufWnuaitcsia
A10: No of cases re heare or reviewed by the high court | B10: 1 | C10: 1 | D10: 2 | F10: 1 | G10: 1 | H10: 1 | I10: 0 | J10: 1 | L10: 1 | M10: 0 | N10: 0 | O10: 5 | P10: 5 | R10: 0 | S10: 5 | T10: udwdwa egukwtwlwscawm unuLehwSuh cSwrwhwfwnwved cSwTOkiawh
A11: No of cases filed on election offences | B11: 0 | C11: 2 | D11: 2 | F11: 2 | G11: 0 | H11: 0 | I11: 0 | J11: 0 | L11: 0 | M11: 0 | N11: 0 | O11: 0 | P11: 0 | R11: 0 | S11: 0 | T11: udwdwa egukwtwlwscawm unuLehwSuh WvuawdeguSuk EhebWbWhitcnia
A12: No. of cases on Complains on elections | B12: 0 | C12: 2 | D12: 2 | F12: 2 | G12: 0 | H12: 0 | I12: 15 | J12: 0 | L12: 15 | M12: 0 | N12: 0 | O12: 0 | P12: 0 | R12: 0 | S12: 0 | T12: އިންތިޚާބާއިބެހޭ ޝަކުވާގެ ދަޢުވާ ހުށަހެޅުނު މައްސަލަތަކުގެ އަދަދު
A13: No. of cases on Political parties | B13: 0 | C13: 0 | D13: 0 | F13: 0 | G13: 0 | H13: 0 | I13: 0 | J13: 0 | L13: 0 | M13: 0 | N13: 0 | O13: 0 | P13: 0 | R13: 0 | S13: 0 | T13: ސިޔާސީ ޕާޓީތަކާބެހޭ ގޮތުން ހުށަހެޅުނު މައްސަލަތަކުގެ އަދަދު
A14: No of cases filed on constitutional issues | B14: 7 | C14: 6 | D14: 13 | F14: 4 | G14: 9 | H14: 9 | I14: 6 | J14: 15 | L14: 7 | M14: 7 | N14: 7 | O14: 2 | P14: 9 | R14: 6 | S14: 4 | T14: udwdއަ egukwtwlwscawm IrUtcsud
A15: Source: The High Court of the Republic of Maldives | T15: cTOkiawh egEjcaWrihevid :Ivcaed utWmUluAwm

Sheet 8.20
A1: ތާވަލު 8.20: ހުށަހެޅުނު، ނިމުނު އަދި ނުނިމި ހުރި މައްސަލަތައް، 2015
A2: Table 8.20: CASES FILED, CONCLUDED AND PENDING BY CASE TYPE, 2015
A3: Atoll | B3: Court | C3: Criminal Cases above 18 | I3: Criminal Cases below 18 | O3: Civil Cases | U3: Family Cases
C4: Starting Balance | D4: New cases filed | E4: Total | F4: Concluded | G4: Ending Balance | I4: Starting Balance | J4: New cases filed | K4: Total | L4: Concluded | M4: Ending Balance | O4: Starting Balance | P4: New cases filed | Q4: Total | R4: Concluded | S4: Ending Balance | U4: Starting Balance | V4: New cases filed | W4: Total | X4: Concluded | Y4: Ending Balance
B5: Grand Total | C5: =C6+C13 -> 2576 | D5: =D6+D13 -> 1976 | E5: =E6+E13 -> 4552 | F5: =F6+F13 -> 2539 | G5: =G6+G13 -> 2013 | I5: =I6+I13 -> 91 | J5: =J6+J13 -> 57 | K5: =K6+K13 -> 148 | L5: =L6+L13 -> 95 | M5: =M6+M13 -> 53 | O5: =O6+O13 -> 3827 | P5: =P6+P13 -> 5290 | Q5: =Q6+Q13 -> 9117 | R5: =R6+R13 -> 5756 | S5: =S6+S13 -> 2210 | U5: =U6+U13 -> 1388 | V5: =V6+V13 -> 9477 | W5: =W6+W13 -> 10865 | X5: =X6+X13 -> 9711 | Y5: =Y6+Y13 -> 2168
A6: Male' | B6: Male' Total | C6: =SUM(C8:C12) -> 1207 | D6: =SUM(D8:D12) -> 830 | E6: =SUM(E8:E12) -> 2037 | F6: =SUM(F8:F12) -> 1121 | G6: =SUM(G8:G12) -> 916 | I6: =SUM(I8:I12) -> 7 | J6: =SUM(J8:J12) -> 25 | K6: =SUM(K8:K12) -> 32 | L6: =SUM(L8:L12) -> 26 | M6: =SUM(M8:M12) -> 6 | O6: =SUM(O8:O12) -> 1604 | P6: =SUM(P8:P12) -> 2543 | Q6: =SUM(Q8:Q12) -> 4147 | R6: =SUM(R8:R12) -> 2701 | S6: =SUM(S8:S12) -> 1304 | U6: =SUM(U8:U12) -> 443 | V6: =SUM(V8:V12) -> 3044 | W6: =SUM(W8:W12) -> 3487 | X6: =SUM(X8:X12) -> 2924 | Y6: =SUM(Y8:Y12) -> 568
B7: Magistrate Courts
A8: Male' | B8: Civil Court | C8: 0 | D8: 0 | E8: 0 | F8: 0 | G8: 0 | I8: 0 | J8: 0 | K8: 0 | L8: 0 | M8: 0 | O8: 1286 | P8: 2377 | Q8: 3663 | R8: 2283 | S8: 1243 | U8: 0 | V8: 0 | W8: 0 | X8: 0 | Y8: 0
A9: Male' | B9: Criminal Court | C9: 1153 | D9: 806 | E9: 1959 | F9: 1069 | G9: 890 | I9: 0 | J9: 0 | K9: 0 | L9: 0 | M9: 0 | O9: 0 | P9: 0 | Q9: 0 | R9: 0 | S9: 0 | U9: 0 | V9: 0 | W9: 0 | X9: 0 | Y9: 0
A10: Male' | B10: Family Court | C10: 0 | D10: 0 | E10: 0 | F10: 0 | G10: 0 | I10: 0 | J10: 0 | K10: 0 | L10: 0 | M10: 0 | O10: 0 | P10: 0 | Q10: 0 | R10: 0 | S10: 0 | U10: 404 | V10: 2706 | W10: 3110 | X10: 2553 | Y10: 557
A11: Male' | B11: Juvenile Court | C11: 0 | D11: 0 | E11: 0 | F11: 0 | G11: 0 | I11: 7 | J11: 25 | K11: 32 | L11: 26 | M11: 6 | O11: 0 | P11: 0 | Q11: 0 | R11: 0 | S11: 0 | U11: 0 | V11: 0 | W11: 0 | X11: 0 | Y11: 0
A12: Male' | B12: HulhuMale' Court | C12: 54 | D12: 24 | E12: 78 | F12: 52 | G12: 26 | I12: 0 | J12: 0 | K12: 0 | L12: 0 | M12: 0 | O12: 318 | P12: 166 | Q12: 484 | R12: 418 | S12: 61 | U12: 39 | V12: 338 | W12: 377 | X12: 371 | Y12: 11 | AQ12: Atoll | AR12: Court | AS12: Criminal Cases above 18 | AY12: Criminal Cases below 18 | BE12: Civil Cases | BK12: Family Cases
B13: Atoll Total | C13: =C14+C29+C43+C58+C73+C89+C103+C108+C118+C127+C138+C144+C153+C159+C166+C180+C195+C205+C215+C217 -> 1369 | D13: =D14+D29+D43+D58+D73+D89+D103+D108+D118+D127+D138+D144+D153+D159+D166+D180+D195+D205+D215+D217 -> 1146 | E13: =E14+E29+E43+E58+E73+E89+E103+E108+E118+E127+E138+E144+E153+E159+E166+E180+E195+E205+E215+E217 -> 2515 | F13: =F14+F29+F43+F58+F73+F89+F103+F108+F118+F127+F138+F144+F153+F159+F166+F180+F195+F205+F215+F217 -> 1418 | G13: =G14+G29+G43+G58+G73+G89+G103+G108+G118+G127+G138+G144+G153+G159+G166+G180+G195+G205+G215+G217 -> 1097 | I13: =I14+I29+I43+I58+I73+I89+I103+I108+I118+I127+I138+I144+I153+I159+I166+I180+I195+I205+I215+I217 -> 84 | J13: =J14+J29+J43+J58+J73+J89+J103+J108+J118+J127+J138+J144+J153+J159+J166+J180+J195+J205+J215+J217 -> 32 | K13: =K14+K29+K43+K58+K73+K89+K103+K108+K118+K127+K138+K144+K153+K159+K166+K180+K195+K205+K215+K217 -> 116 | L13: =L14+L29+L43+L58+L73+L89+L103+L108+L118+L127+L138+L144+L153+L159+L166+L180+L195+L205+L215+L217 -> 69 | M13: =M14+M29+M43+M58+M73+M89+M103+M108+M118+M127+M138+M144+M153+M159+M166+M180+M195+M205+M215+M217 -> 47 | O13: =O14+O29+O43+O58+O73+O89+O103+O108+O118+O127+O138+O144+O153+O159+O166+O180+O195+O205+O215+O217 -> 2223 | P13: =P14+P29+P43+P58+P73+P89+P103+P108+P118+P127+P138+P144+P153+P159+P166+P180+P195+P205+P215+P217 -> 2747 | Q13: =Q14+Q29+Q43+Q58+Q73+Q89+Q103+Q108+Q118+Q127+Q138+Q144+Q153+Q159+Q166+Q180+Q195+Q205+Q215+Q217 -> 4970 | R13: =R14+R29+R43+R58+R73+R89+R103+R108+R118+R127+R138+R144+R153+R159+R166+R180+R195+R205+R215+R217 -> 3055 | S13: =S14+S29+S43+S58+S73+S89+S103+S108+S118+S127+S138+S144+S153+S159+S166+S180+S195+S205+S215+S217 -> 906 | U13: =U14+U29+U43+U58+U73+U89+U103+U108+U118+U127+U138+U144+U153+U159+U166+U180+U195+U205+U215+U217 -> 945 | V13: =V14+V29+V43+V58+V73+V89+V103+V108+V118+V127+V138+V144+V153+V159+V166+V180+V195+V205+V215+V217 -> 6433 | W13: =W14+W29+W43+W58+W73+W89+W103+W108+W118+W127+W138+W144+W153+W159+W166+W180+W195+W205+W215+W217 -> 7378 | X13: =X14+X29+X43+X58+X73+X89+X103+X108+X118+X127+X138+X144+X153+X159+X166+X180+X195+X205+X215+X217 -> 6787 | Y13: =Y14+Y29+Y43+Y58+Y73+Y89+Y103+Y108+Y118+Y127+Y138+Y144+Y153+Y159+Y166+Y180+Y195+Y205+Y215+Y217 -> 1600 | AS13: Starting Balance | AT13: New cases filed | AU13: Total | AV13: Concluded | AW13: Ending Balance | AY13: Starting Balance | AZ13: New cases filed | BA13: Total | BB13: Concluded | BC13: Ending Balance | BE13: Starting Balance | BF13: New cases filed | BG13: Total | BH13: Concluded | BI13: Ending Balance | BK13: Starting Balance | BL13: New cases filed | BM13: Total | BN13: Concluded | BO13: Ending Balance
A14: HA | B14: Total | C14: =SUM(C15:C28) -> 123 | D14: =SUM(D15:D28) -> 41 | E14: =SUM(E15:E28) -> 164 | F14: =SUM(F15:F28) -> 83 | G14: =SUM(G15:G28) -> 81 | I14: =SUM(I15:I28) -> 4 | J14: =SUM(J15:J28) -> 1 | K14: =SUM(K15:K28) -> 5 | L14: =SUM(L15:L28) -> 3 | M14: =SUM(M15:M28) -> 2 | O14: =SUM(O15:O28) -> 160 | P14: =SUM(P15:P28) -> 79 | Q14: =SUM(Q15:Q28) -> 239 | R14: =SUM(R15:R28) -> 115 | S14: =SUM(S15:S28) -> 44 | U14: =SUM(U15:U28) -> 37 | V14: =SUM(V15:V28) -> 257 | W14: =SUM(W15:W28) -> 294 | X14: =SUM(X15:X28) -> 267 | Y14: =SUM(Y15:Y28) -> 107 | AR14: Grand Total | AS14: 2576 | AT14: 1976 | AU14: 4552 | AV14: 2539 | AW14: 2013 | AY14: 91 | AZ14: 57 | BA14: 148 | BB14: 95 | BC14: 53 | BE14: 3827 | BF14: 5290 | BG14: 9117 | BH14: 5756 | BI14: 2210 | BK14: 1388 | BL14: 9477 | BM14: 10865 | BN14: 9711 | BO14: 2168
A15: HA | B15: Thuraakunu | C15: 0 | D15: 0 | E15: 0 | F15: 0 | G15: 0 | I15: 0 | J15: 0 | K15: 0 | L15: 0 | M15: 0 | O15: 0 | P15: 1 | Q15: 1 | R15: 0 | S15: 0 | U15: 0 | V15: 6 | W15: 6 | X15: 7 | Y15: 0 | AQ15: Male' | AR15: Male' Total | AS15: 1207 | AT15: 830 | AU15: 2037 | AV15: 1121 | AW15: 916 | AY15: 7 | AZ15: 25 | BA15: 32 | BB15: 26 | BC15: 6 | BE15: 1604 | BF15: 2543 | BG15: 4147 | BH15: 2701 | BI15: 1304 | BK15: 443 | BL15: 3044 | BM15: 3487 | BN15: 2924 | BO15: 568
A16: HA | B16: Uligamu | C16: 0 | D16: 2 | E16: 2 | F16: 2 | G16: 0 | I16: 0 | J16: 0 | K16: 0 | L16: 0 | M16: 0 | O16: 1 | P16: 1 | Q16: 2 | R16: 1 | S16: 0 | U16: 2 | V16: 4 | W16: 6 | X16: 7 | Y16: 0 | AR16: Atoll Total | AS16: 1369 | AT16: 1146 | AU16: 2515 | AV16: 1418 | AW16: 1097 | AX16: =AV16/AU16*100 -> 56.38171 | AY16: 84 | AZ16: 32 | BA16: 116 | BB16: 69 | BC16: 47 | BE16: 2223 | BF16: 2747 | BG16: 4970 | BH16: 3055 | BI16: 906 | BK16: 945 | BL16: 6433 | BM16: 7378 | BN16: 6787 | BO16: 1600
A17: HA | B17: Molhadhoo | C17: 3 | D17: 2 | E17: 5 | F17: 1 | G17: 4 | I17: 0 | J17: 0 | K17: 0 | L17: 0 | M17: 0 | O17: 2 | P17: 2 | Q17: 4 | R17: 2 | S17: 0 | U17: 3 | V17: 12 | W17: 15 | X17: 15 | Y17: 2 | AQ17: HA | AR17: Total | AS17: 123 | AT17: 41 | AU17: 164 | AV17: 83 | AW17: 81 | AX17: =AV17/AU17*100 -> 50.609756 | AY17: 4 | AZ17: 1 | BA17: 5 | BB17: 3 | BC17: 2 | BE17: 160 | BF17: 79 | BG17: 239 | BH17: 115 | BI17: 44 | BK17: 37 | BL17: 257 | BM17: 294 | BN17: 267 | BO17: 107
A18: HA | B18: Hoarafushi | C18: 28 | D18: 11 | E18: 39 | F18: 19 | G18: 20 | I18: 2 | J18: 1 | K18: 3 | L18: 1 | M18: 2 | O18: 23 | P18: 16 | Q18: 39 | R18: 17 | S18: 6 | U18: 5 | V18: 61 | W18: 66 | X18: 57 | Y18: 25 | AQ18: HDh | AR18: Total | AS18: 293 | AT18: 64 | AU18: 357 | AV18: 60 | AW18: 297 | AX18: =AV18/AU18*100 -> 16.806723 | AY18: 13 | AZ18: 2 | BA18: 15 | BB18: 1 | BC18: 14 | BE18: 179 | BF18: 112 | BG18: 291 | BH18: 106 | BI18: 64 | BK18: 87 | BL18: 440 | BM18: 527 | BN18: 509 | BO18: 139
A19: HA | B19: Ihavandhoo | C19: 25 | D19: 4 | E19: 29 | F19: 29 | G19: 0 | I19: 0 | J19: 0 | K19: 0 | L19: 0 | M19: 0 | O19: 23 | P19: 19 | Q19: 42 | R19: 28 | S19: 4 | U19: 1 | V19: 33 | W19: 34 | X19: 31 | Y19: 13 | AQ19: Sh | AR19: Total | AS19: 7 | AT19: 36 | AU19: 43 | AV19: 28 | AW19: 15 | AX19: =AV19/AU19*100 -> 65.116279 | AY19: 3 | AZ19: 0 | BA19: 3 | BB19: 2 | BC19: 1 | BE19: 55 | BF19: 67 | BG19: 122 | BH19: 67 | BI19: 25 | BK19: 33 | BL19: 262 | BM19: 295 | BN19: 256 | BO19: 69
A20: HA | B20: Kela | C20: 13 | D20: 3 | E20: 16 | F20: 16 | G20: 0 | I20: 1 | J20: 0 | K20: 1 | L20: 1 | M20: 0 | O20: 11 | P20: 3 | Q20: 14 | R20: 3 | S20: 4 | U20: 4 | V20: 19 | W20: 23 | X20: 18 | Y20: 12 | AQ20: N | AR20: Total | AS20: 63 | AT20: 93 | AU20: 156 | AV20: 57 | AW20: 99 | AX20: =AV20/AU20*100 -> 36.538462 | AY20: 4 | AZ20: 4 | BA20: 8 | BB20: 4 | BC20: 4 | BE20: 129 | BF20: 133 | BG20: 262 | BH20: 138 | BI20: 55 | BK20: 65 | BL20: 383 | BM20: 448 | BN20: 395 | BO20: 122
A21: HA | B21: Vashafaru | C21: 1 | D21: 2 | E21: 3 | F21: 0 | G21: 3 | I21: 0 | J21: 0 | K21: 0 | L21: 0 | M21: 0 | O21: 24 | P21: 6 | Q21: 30 | R21: 12 | S21: 12 | U21: 6 | V21: 9 | W21: 15 | X21: 11 | Y21: 10 | AQ21: R | AR21: Total | AS21: 82 | AT21: 56 | AU21: 138 | AV21: 70 | AW21: 68 | AX21: =AV21/AU21*100 -> 50.724638 | AY21: 3 | AZ21: 0 | BA21: 3 | BB21: 3 | BC21: 0 | BE21: 138 | BF21: 153 | BG21: 291 | BH21: 189 | BI21: 46 | BK21: 54 | BL21: 359 | BM21: 413 | BN21: 384 | BO21: 85
A22: HA | B22: Dhidhdhoo | C22: 16 | D22: 2 | E22: 18 | F22: 3 | G22: 15 | I22: 1 | J22: 0 | K22: 1 | L22: 1 | M22: 0 | O22: 35 | P22: 13 | Q22: 48 | R22: 26 | S22: 6 | U22: 1 | V22: 36 | W22: 37 | X22: 41 | Y22: 12 | AQ22: B | AR22: Total | AS22: 22 | AT22: 21 | AU22: 43 | AV22: 25 | AW22: 18 | AX22: =AV22/AU22*100 -> 58.139535 | AY22: 2 | AZ22: 0 | BA22: 2 | BB22: 1 | BC22: 1 | BE22: 68 | BF22: 79 | BG22: 147 | BH22: 92 | BI22: 23 | BK22: 36 | BL22: 175 | BM22: 211 | BN22: 220 | BO22: 23
A23: HA | B23: Filladhoo | C23: 7 | D23: 4 | E23: 11 | F23: 3 | G23: 8 | I23: 0 | J23: 0 | K23: 0 | L23: 0 | M23: 0 | O23: 6 | P23: 2 | Q23: 8 | R23: 2 | S23: 0 | U23: 0 | V23: 11 | W23: 11 | X23: 15 | Y23: 2 | AQ23: Lh | AR23: Total | AS23: 81 | AT23: 32 | AU23: 113 | AV23: 111 | AW23: 2 | AX23: =AV23/AU23*100 -> 98.230088 | AY23: 3 | AZ23: 4 | BA23: 7 | BB23: 7 | BC23: 0 | BE23: 143 | BF23: 111 | BG23: 254 | BH23: 106 | BI23: 80 | BK23: 64 | BL23: 307 | BM23: 371 | BN23: 312 | BO23: 127
A24: HA | B24: Maarandhoo | C24: 0 | D24: 0 | E24: 0 | F24: 0 | G24: 0 | I24: 0 | J24: 0 | K24: 0 | L24: 0 | M24: 0 | O24: 8 | P24: 0 | Q24: 8 | R24: 7 | S24: 0 | U24: 0 | V24: 11 | W24: 11 | X24: 7 | Y24: 5 | AQ24: K | AR24: Total | AS24: 11 | AT24: 61 | AU24: 72 | AV24: 21 | AW24: 51 | AX24: =AV24/AU24*100 -> 29.166667 | AY24: 4 | AZ24: 1 | BA24: 5 | BB24: 0 | BC24: 5 | BE24: 110 | BF24: 102 | BG24: 212 | BH24: 117 | BI24: 41 | BK24: 67 | BL24: 388 | BM24: 455 | BN24: 433 | BO24: 76
A25: HA | B25: Thakandhoo | C25: 4 | D25: 1 | E25: 5 | F25: 5 | G25: 0 | I25: 0 | J25: 0 | K25: 0 | L25: 0 | M25: 0 | O25: 10 | P25: 1 | Q25: 11 | R25: 2 | S25: 2 | U25: 6 | V25: 9 | W25: 15 | X25: 13 | Y25: 9 | AQ25: AA | AR25: Total | AS25: 19 | AT25: 15 | AU25: 34 | AV25: 17 | AW25: 17 | AX25: =AV25/AU25*100 -> 50 | AY25: 0 | AZ25: 0 | BA25: 0 | BB25: 0 | BC25: 0 | BE25: 39 | BF25: 115 | BG25: 154 | BH25: 110 | BI25: 23 | BK25: 18 | BL25: 234 | BM25: 252 | BN25: 248 | BO25: 25
A26: HA | B26: Utheemu | C26: 2 | D26: 1 | E26: 3 | F26: 2 | G26: 1 | I26: 0 | J26: 0 | K26: 0 | L26: 0 | M26: 0 | O26: 0 | P26: 2 | Q26: 2 | R26: 0 | S26: 1 | U26: 3 | V26: 7 | W26: 10 | X26: 8 | Y26: 3 | AQ26: ADh | AR26: Total | AS26: 12 | AT26: 21 | AU26: 33 | AV26: 19 | AW26: 14 | AX26: =AV26/AU26*100 -> 57.575758 | AY26: 3 | AZ26: 4 | BA26: 7 | BB26: 6 | BC26: 1 | BE26: 96 | BF26: 133 | BG26: 229 | BH26: 150 | BI26: 37 | BK26: 30 | BL26: 284 | BM26: 314 | BN26: 281 | BO26: 75
A27: HA | B27: Muraidhoo | C27: 1 | D27: 0 | E27: 1 | F27: 0 | G27: 1 | I27: 0 | J27: 0 | K27: 0 | L27: 0 | M27: 0 | O27: 3 | P27: 0 | Q27: 3 | R27: 1 | S27: 0 | U27: 3 | V27: 14 | W27: 17 | X27: 11 | Y27: 8 | AQ27: V | AR27: Total | AS27: 0 | AT27: 0 | AU27: 0 | AV27: 0 | AW27: 0 | AX27: 0 | AY27: 0 | AZ27: 0 | BA27: 0 | BB27: 0 | BC27: 0 | BE27: 7 | BF27: 23 | BG27: 30 | BH27: 24 | BI27: 0 | BK27: 3 | BL27: 47 | BM27: 50 | BN27: 43 | BO27: 13
A28: HA | B28: Baarashu | C28: 23 | D28: 9 | E28: 32 | F28: 3 | G28: 29 | I28: 0 | J28: 0 | K28: 0 | L28: 0 | M28: 0 | O28: 14 | P28: 13 | Q28: 27 | R28: 14 | S28: 9 | U28: 3 | V28: 25 | W28: 28 | X28: 26 | Y28: 6 | AQ28: M | AR28: Total | AS28: 23 | AT28: 5 | AU28: 28 | AV28: 20 | AW28: 8 | AX28: =AV28/AU28*100 -> 71.428571 | AY28: 0 | AZ28: 0 | BA28: 0 | BB28: 0 | BC28: 0 | BE28: 26 | BF28: 52 | BG28: 78 | BH28: 50 | BI28: 16 | BK28: 16 | BL28: 130 | BM28: 146 | BN28: 136 | BO28: 22
A29: HDh | B29: Total | C29: =SUM(C30:C42) -> 293 | D29: =SUM(D30:D42) -> 64 | E29: =SUM(E30:E42) -> 357 | F29: =SUM(F30:F42) -> 60 | G29: =SUM(G30:G42) -> 297 | I29: =SUM(I30:I42) -> 13 | J29: =SUM(J30:J42) -> 2 | K29: =SUM(K30:K42) -> 15 | L29: =SUM(L30:L42) -> 1 | M29: =SUM(M30:M42) -> 14 | O29: =SUM(O30:O42) -> 179 | P29: =SUM(P30:P42) -> 112 | Q29: =SUM(Q30:Q42) -> 291 | R29: =SUM(R30:R42) -> 106 | S29: =SUM(S30:S42) -> 64 | U29: =SUM(U30:U42) -> 87 | V29: =SUM(V30:V42) -> 440 | W29: =SUM(W30:W42) -> 527 | X29: =SUM(X30:X42) -> 509 | Y29: =SUM(Y30:Y42) -> 139 | AQ29: F | AR29: Total | AS29: 12 | AT29: 4 | AU29: 16 | AV29: 11 | AW29: 5 | AX29: =AV29/AU29*100 -> 68.75 | AY29: 0 | AZ29: 0 | BA29: 0 | BB29: 0 | BC29: 0 | BE29: 22 | BF29: 53 | BG29: 75 | BH29: 43 | BI29: 22 | BK29: 16 | BL29: 129 | BM29: 145 | BN29: 119 | BO29: 36
A30: HDh | B30: Finey | C30: 0 | D30: 1 | E30: 1 | F30: 0 | G30: 1 | I30: 0 | J30: 0 | K30: 0 | L30: 0 | M30: 0 | O30: 3 | P30: 1 | Q30: 4 | R30: 0 | S30: 1 | U30: 1 | V30: 5 | W30: 6 | X30: 5 | Y30: 4 | AQ30: Dh | AR30: Total | AS30: 4 | AT30: 4 | AU30: 8 | AV30: 5 | AW30: 3 | AX30: =AV30/AU30*100 -> 62.5 | AY30: 0 | AZ30: 0 | BA30: 0 | BB30: 0 | BC30: 0 | BE30: 27 | BF30: 44 | BG30: 71 | BH30: 38 | BI30: 19 | BK30: 12 | BL30: 145 | BM30: 157 | BN30: 137 | BO30: 34
A31: HDh | B31: Makunudhoo | C31: 0 | D31: 4 | E31: 4 | F31: 0 | G31: 4 | I31: 0 | J31: 0 | K31: 0 | L31: 0 | M31: 0 | O31: 3 | P31: 5 | Q31: 8 | R31: 4 | S31: 3 | U31: 6 | V31: 43 | W31: 49 | X31: 40 | Y31: 10 | AQ31: Th | AR31: Total | AS31: 96 | AT31: 27 | AU31: 123 | AV31: 62 | AW31: 61 | AX31: =AV31/AU31*100 -> 50.406504 | AY31: 4 | AZ31: 0 | BA31: 4 | BB31: 2 | BC31: 2 | BE31: 106 | BF31: 101 | BG31: 207 | BH31: 106 | BI31: 56 | BK31: 49 | BL31: 277 | BM31: 326 | BN31: 270 | BO31: 101
A32: HDh | B32: Naavaidhoo | C32: 2 | D32: 0 | E32: 2 | F32: 2 | G32: 0 | I32: 0 | J32: 0 | K32: 0 | L32: 0 | M32: 0 | O32: 3 | P32: 1 | Q32: 4 | R32: 1 | S32: 1 | U32: 3 | V32: 8 | W32: 11 | X32: 10 | Y32: 3 | AQ32: L | AR32: Total | AS32: 148 | AT32: 113 | AU32: 261 | AV32: 252 | AW32: 9 | AX32: =AV32/AU32*100 -> 96.551724 | AY32: 11 | AZ32: 3 | BA32: 14 | BB32: 14 | BC32: 0 | BE32: 216 | BF32: 224 | BG32: 440 | BH32: 293 | BI32: 71 | BK32: 100 | BL32: 633 | BM32: 733 | BN32: 659 | BO32: 150
A33: HDh | B33: Kumundhoo | C33: 0 | D33: 3 | E33: 3 | F33: 2 | G33: 1 | I33: 0 | J33: 0 | K33: 0 | L33: 0 | M33: 0 | O33: 4 | P33: 4 | Q33: 8 | R33: 5 | S33: 1 | U33: 3 | V33: 19 | W33: 22 | X33: 24 | Y33: 0 | AQ33: GA | AR33: Total | AS33: 32 | AT33: 94 | AU33: 126 | AV33: 62 | AW33: 64 | AX33: =AV33/AU33*100 -> 49.206349 | AY33: 2 | AZ33: 3 | BA33: 5 | BB33: 4 | BC33: 1 | BE33: 145 | BF33: 412 | BG33: 557 | BH33: 399 | BI33: 113 | BK33: 38 | BL33: 372 | BM33: 410 | BN33: 381 | BO33: 74
A34: HDh | B34: Kulhudhuffushi | C34: 227 | D34: 45 | E34: 272 | F34: 20 | G34: 252 | I34: 6 | J34: 2 | K34: 8 | L34: 0 | M34: 8 | O34: 69 | P34: 43 | Q34: 112 | R34: 36 | S34: 36 | U34: 31 | V34: 173 | W34: 204 | X34: 166 | Y34: 78 | AQ34: GDh | AR34: Total | AS34: 74 | AT34: 79 | AU34: 153 | AV34: 102 | AW34: 51 | AX34: =AV34/AU34*100 -> 66.666667 | AY34: 1 | AZ34: 2 | BA34: 3 | BB34: 2 | BC34: 1 | BE34: 139 | BF34: 180 | BG34: 319 | BH34: 226 | BI34: 38 | BK34: 71 | BL34: 505 | BM34: 576 | BN34: 553 | BO34: 78
A35: HDh | B35: Hirimaradhoo | C35: 1 | D35: 0 | E35: 1 | F35: 1 | G35: 0 | I35: 0 | J35: 0 | K35: 0 | L35: 0 | M35: 0 | O35: 1 | P35: 4 | Q35: 5 | R35: 4 | S35: 0 | U35: 1 | V35: 5 | W35: 6 | X35: 7 | Y35: 0 | AQ35: Gn | AR35: Total | AS35: 166 | AT35: 134 | AU35: 300 | AV35: 162 | AW35: 138 | AX35: =AV35/AU35*100 -> 54 | AY35: 20 | AZ35: 4 | BA35: 24 | BB35: 10 | BC35: 14 | BE35: 172 | BF35: 212 | BG35: 384 | BH35: 251 | BI35: 84 | BK35: 76 | BL35: 356 | BM35: 432 | BN35: 383 | BO35: 98
A36: HDh | B36: Nolhivaramfaru | C36: 15 | D36: 1 | E36: 16 | F36: 3 | G36: 13 | I36: 3 | J36: 0 | K36: 3 | L36: 0 | M36: 3 | O36: 33 | P36: 10 | Q36: 43 | R36: 8 | S36: 5 | U36: 1 | V36: 19 | W36: 20 | X36: 43 | Y36: 7 | AQ36: S | AR36: Total | AS36: 101 | AT36: 246 | AU36: 347 | AV36: 251 | AW36: 96 | AX36: =AV36/AU36*100 -> 72.334294 | AY36: 7 | AZ36: 4 | BA36: 11 | BB36: 10 | BC36: 1 | BE36: 246 | BF36: 362 | BG36: 608 | BH36: 435 | BI36: 49 | BK36: 73 | BL36: 750 | BM36: 823 | BN36: 801 | BO36: 146
A37: HDh | B37: Vaikaradhoo | C37: 1 | D37: 3 | E37: 4 | F37: 4 | G37: 0 | I37: 0 | J37: 0 | K37: 0 | L37: 0 | M37: 0 | O37: 3 | P37: 4 | Q37: 7 | R37: 4 | S37: 0 | U37: 2 | V37: 20 | W37: 22 | X37: 18 | Y37: 7
A38: HDh | B38: Hanimaadhoo | C38: 21 | D38: 0 | E38: 21 | F38: 0 | G38: 21 | I38: 2 | J38: 0 | K38: 2 | L38: 0 | M38: 2 | O38: 21 | P38: 5 | Q38: 26 | R38: 3 | S38: 9 | U38: 7 | V38: 31 | W38: 38 | X38: 39 | Y38: 13
A39: HDh | B39: Kurinbee | C39: 0 | D39: 0 | E39: 0 | F39: 0 | G39: 0 | I39: 0 | J39: 0 | K39: 0 | L39: 0 | M39: 0 | O39: 1 | P39: 1 | Q39: 2 | R39: 1 | S39: 1 | U39: 1 | V39: 4 | W39: 5 | X39: 4 | Y39: 1
A40: HDh | B40: Nolhivaram | C40: 15 | D40: 1 | E40: 16 | F40: 12 | G40: 4 | I40: 2 | J40: 0 | K40: 2 | L40: 1 | M40: 1 | O40: 27 | P40: 21 | Q40: 48 | R40: 29 | S40: 3 | U40: 20 | V40: 57 | W40: 77 | X40: 85 | Y40: 8
A41: HDh | B41: Neykurendhoo | C41: 11 | D41: 5 | E41: 16 | F41: 16 | G41: 0 | I41: 0 | J41: 0 | K41: 0 | L41: 0 | M41: 0 | O41: 5 | P41: 2 | Q41: 7 | R41: 2 | S41: 1 | U41: 8 | V41: 26 | W41: 34 | X41: 32 | Y41: 6
A42: HDh | B42: Nehlaidhoo | C42: 0 | D42: 1 | E42: 1 | F42: 0 | G42: 1 | I42: 0 | J42: 0 | K42: 0 | L42: 0 | M42: 0 | O42: 6 | P42: 11 | Q42: 17 | R42: 9 | S42: 3 | U42: 3 | V42: 30 | W42: 33 | X42: 36 | Y42: 2
A43: Sh | B43: Total | C43: =SUM(C44:C57) -> 7 | D43: =SUM(D44:D57) -> 36 | E43: =SUM(E44:E57) -> 43 | F43: =SUM(F44:F57) -> 28 | G43: =SUM(G44:G57) -> 15 | I43: =SUM(I44:I57) -> 3 | J43: =SUM(J44:J57) -> 0 | K43: =SUM(K44:K57) -> 3 | L43: =SUM(L44:L57) -> 2 | M43: =SUM(M44:M57) -> 1 | O43: =SUM(O44:O57) -> 55 | P43: =SUM(P44:P57) -> 67 | Q43: =SUM(Q44:Q57) -> 122 | R43: =SUM(R44:R57) -> 67 | S43: =SUM(S44:S57) -> 25 | U43: =SUM(U44:U57) -> 33 | V43: =SUM(V44:V57) -> 262 | W43: =SUM(W44:W57) -> 295 | X43: =SUM(X44:X57) -> 256 | Y43: =SUM(Y44:Y57) -> 69
A44: Sh | B44: Kanditheemu | C44: 0 | D44: 1 | E44: 1 | F44: 0 | G44: 1 | I44: 0 | J44: 0 | K44: 0 | L44: 0 | M44: 0 | O44: 5 | P44: 6 | Q44: 11 | R44: 6 | S44: 3 | U44: 7 | V44: 24 | W44: 31 | X44: 19 | Y44: 14
A45: Sh | B45: Goidhoo | C45: 1 | D45: 0 | E45: 1 | F45: 1 | G45: 0 | I45: 0 | J45: 0 | K45: 0 | L45: 0 | M45: 0 | O45: 1 | P45: 2 | Q45: 3 | R45: 3 | S45: 0 | U45: 0 | V45: 4 | W45: 4 | X45: 3 | Y45: 1
A46: Sh | B46: Feevaku | C46: 1 | D46: 0 | E46: 1 | F46: 1 | G46: 0 | I46: 0 | J46: 0 | K46: 0 | L46: 0 | M46: 0 | O46: 6 | P46: 7 | Q46: 13 | R46: 3 | S46: 5 | U46: 0 | V46: 26 | W46: 26 | X46: 25 | Y46: 6
A47: Sh | B47: Foakaidhoo | C47: 1 | D47: 7 | E47: 8 | F47: 6 | G47: 2 | I47: 1 | J47: 0 | K47: 1 | L47: 1 | M47: 0 | O47: 14 | P47: 9 | Q47: 23 | R47: 11 | S47: 6 | U47: 10 | V47: 21 | W47: 31 | X47: 24 | Y47: 13
A48: Sh | B48: Lhaimagu | C48: 0 | D48: 1 | E48: 1 | F48: 1 | G48: 0 | I48: 0 | J48: 0 | K48: 0 | L48: 0 | M48: 0 | O48: 0 | P48: 2 | Q48: 2 | R48: 1 | S48: 0 | U48: 0 | V48: 4 | W48: 4 | X48: 4 | Y48: 1
A49: Sh | B49: Komandoo | C49: 0 | D49: 1 | E49: 1 | F49: 1 | G49: 0 | I49: 0 | J49: 0 | K49: 0 | L49: 0 | M49: 0 | O49: 5 | P49: 3 | Q49: 8 | R49: 3 | S49: 2 | U49: 0 | V49: 8 | W49: 8 | X49: 9 | Y49: 2
A50: Sh | B50: Funadhoo | C50: 1 | D50: 15 | E50: 16 | F50: 10 | G50: 6 | I50: 0 | J50: 0 | K50: 0 | L50: 0 | M50: 0 | O50: 0 | P50: 11 | Q50: 11 | R50: 9 | S50: 1 | U50: 1 | V50: 37 | W50: 38 | X50: 37 | Y50: 2
A51: Sh | B51: Noomaraa | C51: 0 | D51: 2 | E51: 2 | F51: 2 | G51: 0 | I51: 0 | J51: 0 | K51: 0 | L51: 0 | M51: 0 | O51: 0 | P51: 3 | Q51: 3 | R51: 1 | S51: 2 | U51: 2 | V51: 0 | W51: 2 | X51: 2 | Y51: 0
A52: Sh | B52: Feydhoo | C52: 0 | D52: 3 | E52: 3 | F52: 2 | G52: 1 | I52: 0 | J52: 0 | K52: 0 | L52: 0 | M52: 0 | O52: 0 | P52: 4 | Q52: 4 | R52: 4 | S52: 0 | U52: 2 | V52: 38 | W52: 40 | X52: 38 | Y52: 2
A53: Sh | B53: Bileffahi | C53: 1 | D53: 0 | E53: 1 | F53: 1 | G53: 0 | I53: 0 | J53: 0 | K53: 0 | L53: 0 | M53: 0 | O53: 6 | P53: 4 | Q53: 10 | R53: 5 | S53: 1 | U53: 3 | V53: 7 | W53: 10 | X53: 12 | Y53: 2
A54: Sh | B54: Narudhoo | C54: 0 | D54: 0 | E54: 0 | F54: 0 | G54: 0 | I54: 0 | J54: 0 | K54: 0 | L54: 0 | M54: 0 | O54: 2 | P54: 1 | Q54: 3 | R54: 1 | S54: 1 | U54: 2 | V54: 6 | W54: 8 | X54: 6 | Y54: 3
A55: Sh | B55: Maroshi | C55: 0 | D55: 0 | E55: 0 | F55: 0 | G55: 0 | I55: 1 | J55: 0 | K55: 1 | L55: 0 | M55: 1 | O55: 8 | P55: 5 | Q55: 13 | R55: 7 | S55: 2 | U55: 1 | V55: 8 | W55: 9 | X55: 7 | Y55: 6
... A57: Sh | B57: Milandhoo | C57: 2 | D57: 4 | E57: 6 | F57: 2 | G57: 4 | I57: 1 | J57: 0 | K57: 1 | L57: 1 | M57: 0 | O57: 8 | P57: 8 | Q57: 16 | R57: 11 | S57: 2 | U57: 4 | V57: 56 | W57: 60 | X57: 54 | Y57: 9
A58: N | B58: Total | C58: =SUM(C59:C72) -> 63 | D58: =SUM(D59:D72) -> 93 | E58: =SUM(E59:E72) -> 156 | F58: =SUM(F59:F72) -> 57 | G58: =SUM(G59:G72) -> 99 | I58: =SUM(I59:I72) -> 4 | J58: =SUM(J59:J72) -> 4 | K58: =SUM(K59:K72) -> 8 | L58: =SUM(L59:L72) -> 4 | M58: =SUM(M59:M72) -> 4 | O58: =SUM(O59:O72) -> 129 | P58: =SUM(P59:P72) -> 133 | Q58: =SUM(Q59:Q72) -> 262 | R58: =SUM(R59:R72) -> 138 | S58: =SUM(S59:S72) -> 55 | U58: =SUM(U59:U72) -> 65 | V58: =SUM(V59:V72) -> 383 | W58: =SUM(W59:W72) -> 448 | X58: =SUM(X59:X72) -> 395 | Y58: =SUM(Y59:Y72) -> 122
A59: N | B59: Henbadhoo | C59: 0 | D59: 0 | E59: 0 | F59: 0 | G59: 0 | I59: 1 | J59: 0 | K59: 1 | L59: 1 | M59: 0 | O59: 6 | P59: 4 | Q59: 10 | R59: 3 | S59: 4 | U59: 1 | V59: 5 | W59: 6 | X59: 7 | Y59: 2
A60: N | B60: Kendhikulhudhoo | C60: 3 | D60: 4 | E60: 7 | F60: 3 | G60: 4 | I60: 0 | J60: 0 | K60: 0 | L60: 0 | M60: 0 | O60: 1 | P60: 3 | Q60: 4 | R60: 3 | S60: 0 | U60: 0 | V60: 17 | W60: 17 | X60: 15 | Y60: 3
A61: N | B61: Kulhudhoo Avashu Section | C61: 0 | D61: 0 | E61: 0 | F61: 0 | G61: 0 | I61: 0 | J61: 0 | K61: 0 | L61: 0 | M61: 0 | O61: 3 | P61: 4 | Q61: 7 | R61: 5 | S61: 0 | U61: 3 | V61: 17 | W61: 20 | X61: 21 | Y61: 1
A62: N | B62: Maalhendhoo | C62: 5 | D62: 2 | E62: 7 | F62: 1 | G62: 6 | I62: 0 | J62: 0 | K62: 0 | L62: 0 | M62: 0 | O62: 6 | P62: 3 | Q62: 9 | R62: 4 | S62: 2 | U62: 3 | V62: 13 | W62: 16 | X62: 16 | Y62: 3
A63: N | B63: Kudafari | C63: 2 | D63: 1 | E63: 3 | F63: 0 | G63: 3 | I63: 0 | J63: 0 | K63: 0 | L63: 0 | M63: 0 | O63: 9 | P63: 6 | Q63: 15 | R63: 2 | S63: 4 | U63: 3 | V63: 14 | W63: 17 | X63: 19 | Y63: 7
A64: N | B64: Landhoo | C64: 5 | D64: 11 | E64: 16 | F64: 3 | G64: 13 | I64: 1 | J64: 0 | K64: 1 | L64: 0 | M64: 1 | O64: 9 | P64: 4 | Q64: 13 | R64: 3 | S64: 3 | U64: 9 | V64: 20 | W64: 29 | X64: 27 | Y64: 9
A65: N | B65: Maafaru | C65: 3 | D65: 5 | E65: 8 | F65: 0 | G65: 8 | I65: 1 | J65: 0 | K65: 1 | L65: 0 | M65: 1 | O65: 11 | P65: 16 | Q65: 27 | R65: 12 | S65: 11 | U65: 4 | V65: 21 | W65: 25 | X65: 19 | Y65: 10
A66: N | B66: Lhohi | C66: 6 | D66: 8 | E66: 14 | F66: 3 | G66: 11 | I66: 0 | J66: 0 | K66: 0 | L66: 0 | M66: 0 | O66: 4 | P66: 5 | Q66: 9 | R66: 5 | S66: 1 | U66: 1 | V66: 22 | W66: 23 | X66: 15 | Y66: 11
A67: N | B67: Miladhoo | C67: 6 | D67: 14 | E67: 20 | F67: 2 | G67: 18 | I67: 0 | J67: 1 | K67: 1 | L67: 0 | M67: 1 | O67: 25 | P67: 24 | Q67: 49 | R67: 31 | S67: 7 | U67: 7 | V67: 50 | W67: 57 | X67: 51 | Y67: 17
A68: N | B68: Magoodhoo | C68: 0 | D68: 2 | E68: 2 | F68: 1 | G68: 1 | I68: 0 | J68: 0 | K68: 0 | L68: 0 | M68: 0 | O68: 1 | P68: 1 | Q68: 2 | R68: 0 | S68: 2 | U68: 1 | V68: 2 | W68: 3 | X68: 2 | Y68: 1
A69: N | B69: Manadhoo | C69: 2 | D69: 5 | E69: 7 | F69: 2 | G69: 5 | I69: 0 | J69: 0 | K69: 0 | L69: 0 | M69: 0 | O69: 10 | P69: 9 | Q69: 19 | R69: 11 | S69: 5 | U69: 15 | V69: 69 | W69: 84 | X69: 66 | Y69: 21
A70: N | B70: Holhudhoo | C70: 8 | D70: 15 | E70: 23 | F70: 10 | G70: 13 | I70: 0 | J70: 0 | K70: 0 | L70: 0 | M70: 0 | O70: 16 | P70: 11 | Q70: 27 | R70: 12 | S70: 6 | U70: 7 | V70: 58 | W70: 65 | X70: 44 | Y70: 30
... A72: N | B72: Velidhoo | C72: 23 | D72: 25 | E72: 48 | F72: 31 | G72: 17 | I72: 1 | J72: 3 | K72: 4 | L72: 3 | M72: 1 | O72: 27 | P72: 43 | Q72: 70 | R72: 47 | S72: 10 | U72: 10 | V72: 74 | W72: 84 | X72: 91 | Y72: 6
A73: R | B73: Total | C73: =SUM(C74:C88) -> 82 | D73: =SUM(D74:D88) -> 56 | E73: =SUM(E74:E88) -> 138 | F73: =SUM(F74:F88) -> 70 | G73: =SUM(G74:G88) -> 68 | I73: =SUM(I74:I88) -> 3 | J73: =SUM(J74:J88) -> 0 | K73: =SUM(K74:K88) -> 3 | L73: =SUM(L74:L88) -> 3 | M73: =SUM(M74:M88) -> 0 | O73: =SUM(O74:O88) -> 138 | P73: =SUM(P74:P88) -> 153 | Q73: =SUM(Q74:Q88) -> 291 | R73: =SUM(R74:R88) -> 189 | S73: =SUM(S74:S88) -> 46 | U73: =SUM(U74:U88) -> 54 | V73: =SUM(V74:V88) -> 359 | W73: =SUM(W74:W88) -> 413 | X73: =SUM(X74:X88) -> 384 | Y73: =SUM(Y74:Y88) -> 85
A74: R | B74: Alifushee | C74: 11 | D74: 5 | E74: 16 | F74: 5 | G74: 11 | I74: 0 | J74: 0 | K74: 0 | L74: 0 | M74: 0 | O74: 27 | P74: 8 | Q74: 35 | R74: 11 | S74: 4 | U74: 8 | V74: 34 | W74: 42 | X74: 45 | Y74: 17
A75: R | B75: Vaadhoo | C75: 0 | D75: 0 | E75: 0 | F75: 0 | G75: 0 | I75: 0 | J75: 0 | K75: 0 | L75: 0 | M75: 0 | O75: 0 | P75: 1 | Q75: 1 | R75: 1 | S75: 0 | U75: 1 | V75: 16 | W75: 17 | X75: 15 | Y75: 2
A76: R | B76: Rasgetheemu | C76: 2 | D76: 2 | E76: 4 | F76: 2 | G76: 2 | I76: 0 | J76: 0 | K76: 0 | L76: 0 | M76: 0 | O76: 7 | P76: 11 | Q76: 18 | R76: 15 | S76: 2 | U76: 0 | V76: 28 | W76: 28 | X76: 20 | Y76: 9
A77: R | B77: Angolhitheemu | C77: 0 | D77: 2 | E77: 2 | F77: 0 | G77: 2 | I77: 0 | J77: 0 | K77: 0 | L77: 0 | M77: 0 | O77: 2 | P77: 4 | Q77: 6 | R77: 4 | S77: 1 | U77: 0 | V77: 9 | W77: 9 | X77: 8 | Y77: 2
A78: R | B78: Hulhduffaaru | C78: 7 | D78: 4 | E78: 11 | F78: 5 | G78: 6 | I78: 0 | J78: 0 | K78: 0 | L78: 0 | M78: 0 | O78: 1 | P78: 11 | Q78: 12 | R78: 8 | S78: 1 | U78: 1 | V78: 22 | W78: 23 | X78: 25 | Y78: 1
A79: R | B79: Ungoofaaru | C79: 5 | D79: 5 | E79: 10 | F79: 5 | G79: 5 | I79: 0 | J79: 0 | K79: 0 | L79: 0 | M79: 0 | O79: 15 | P79: 16 | Q79: 31 | R79: 25 | S79: 6 | U79: 11 | V79: 24 | W79: 35 | X79: 30 | Y79: 5
A80: R | B80: Dhuvaafaru | C80: 22 | D80: 13 | E80: 35 | F80: 17 | G80: 18 | I80: 0 | J80: 0 | K80: 0 | L80: 0 | M80: 0 | O80: 14 | P80: 35 | Q80: 49 | R80: 36 | S80: 12 | U80: 10 | V80: 78 | W80: 88 | X80: 83 | Y80: 6
A81: R | B81: Maakurathu | C81: 7 | D81: 2 | E81: 9 | F81: 8 | G81: 1 | I81: 0 | J81: 0 | K81: 0 | L81: 0 | M81: 0 | O81: 3 | P81: 6 | Q81: 9 | R81: 5 | S81: 3 | U81: 3 | V81: 14 | W81: 17 | X81: 15 | Y81: 3
A82: R | B82: Rasmaadhoo | C82: 2 | D82: 0 | E82: 2 | F82: 2 | G82: 0 | I82: 0 | J82: 0 | K82: 0 | L82: 0 | M82: 0 | O82: 5 | P82: 7 | Q82: 12 | R82: 8 | S82: 2 | U82: 3 | V82: 17 | W82: 20 | X82: 18 | Y82: 4
A83: R | B83: Innamaadhoo | C83: 1 | D83: 1 | E83: 2 | F83: 2 | G83: 0 | I83: 0 | J83: 0 | K83: 0 | L83: 0 | M83: 0 | O83: 0 | P83: 15 | Q83: 15 | R83: 14 | S83: 1 | U83: 0 | V83: 19 | W83: 19 | X83: 18 | Y83: 1
A84: R | B84: Maduvvaree | C84: 17 | D84: 7 | E84: 24 | F84: 21 | G84: 3 | I84: 2 | J84: 0 | K84: 2 | L84: 2 | M84: 0 | O84: 20 | P84: 13 | Q84: 33 | R84: 21 | S84: 3 | U84: 6 | V84: 35 | W84: 41 | X84: 40 | Y84: 10
A85: R | B85: Inguraidhoo | C85: 6 | D85: 8 | E85: 14 | F85: 0 | G85: 14 | I85: 0 | J85: 0 | K85: 0 | L85: 0 | M85: 0 | O85: 19 | P85: 14 | Q85: 33 | R85: 16 | S85: 9 | U85: 9 | V85: 27 | W85: 36 | X85: 30 | Y85: 14
... A88: R | B88: Kinolhas | C88: 0 | D88: 1 | E88: 1 | F88: 1 | G88: 0 | I88: 0 | J88: 0 | K88: 0 | L88: 0 | M88: 0 | O88: 5 | P88: 3 | Q88: 8 | R88: 5 | S88: 0 | U88: 0 | V88: 6 | W88: 6 | X88: 6 | Y88: 3
A89: B | B89: Total | C89: =SUM(C90:C102) -> 22 | D89: =SUM(D90:D102) -> 21 | E89: =SUM(E90:E102) -> 43 | F89: =SUM(F90:F102) -> 25 | G89: =SUM(G90:G102) -> 18 | I89: =SUM(I90:I102) -> 2 | J89: =SUM(J90:J102) -> 0 | K89: =SUM(K90:K102) -> 2 | L89: =SUM(L90:L102) -> 1 | M89: =SUM(M90:M102) -> 1 | O89: =SUM(O90:O102) -> 68 | P89: =SUM(P90:P102) -> 79 | Q89: =SUM(Q90:Q102) -> 147 | R89: =SUM(R90:R102) -> 92 | S89: =SUM(S90:S102) -> 23 | U89: =SUM(U90:U102) -> 36 | V89: =SUM(V90:V102) -> 175 | W89: =SUM(W90:W102) -> 211 | X89: =SUM(X90:X102) -> 220 | Y89: =SUM(Y90:Y102) -> 23
A90: B | B90: Kudarikilu | C90: 0 | D90: 1 | E90: 1 | F90: 0 | G90: 1 | I90: 0 | J90: 0 | K90: 0 | L90: 0 | M90: 0 | O90: 2 | P90: 2 | Q90: 4 | R90: 2 | S90: 1 | U90: 1 | V90: 5 | W90: 6 | X90: 6 | Y90: 1
A91: B | B91: Kamadhoo | C91: 1 | D91: 2 | E91: 3 | F91: 1 | G91: 2 | I91: 0 | J91: 0 | K91: 0 | L91: 0 | M91: 0 | O91: 4 | P91: 2 | Q91: 6 | R91: 4 | S91: 0 | U91: 4 | V91: 20 | W91: 24 | X91: 24 | Y91: 2
A92: B | B92: Kendhoo | C92: 3 | D92: 2 | E92: 5 | F92: 3 | G92: 2 | I92: 0 | J92: 0 | K92: 0 | L92: 0 | M92: 0 | O92: 4 | P92: 7 | Q92: 11 | R92: 6 | S92: 2 | U92: 2 | V92: 15 | W92: 17 | X92: 19 | Y92: 1
A93: B | B93: Kihaadhoo | C93: 0 | D93: 0 | E93: 0 | F93: 0 | G93: 0 | I93: 0 | J93: 0 | K93: 0 | L93: 0 | M93: 0 | O93: 0 | P93: 1 | Q93: 1 | R93: 0 | S93: 1 | U93: 0 | V93: 2 | W93: 2 | X93: 2 | Y93: 0
A94: B | B94: Dhonfanu | C94: 1 | D94: 0 | E94: 1 | F94: 1 | G94: 0 | I94: 0 | J94: 0 | K94: 0 | L94: 0 | M94: 0 | O94: 2 | P94: 3 | Q94: 5 | R94: 3 | S94: 1 | U94: 0 | V94: 5 | W94: 5 | X94: 5 | Y94: 1
A95: B | B95: Dharavandhoo | C95: 4 | D95: 1 | E95: 5 | F95: 4 | G95: 1 | I95: 0 | J95: 0 | K95: 0 | L95: 0 | M95: 0 | O95: 5 | P95: 15 | Q95: 20 | R95: 13 | S95: 1 | U95: 1 | V95: 31 | W95: 32 | X95: 35 | Y95: 3
A96: B | B96: Maalhohu | C96: 0 | D96: 1 | E96: 1 | F96: 0 | G96: 1 | I96: 0 | J96: 0 | K96: 0 | L96: 0 | M96: 0 | O96: 3 | P96: 2 | Q96: 5 | R96: 1 | S96: 0 | U96: 3 | V96: 14 | W96: 17 | X96: 20 | Y96: 1
A97: B | B97: Eydhafushi | C97: 4 | D97: 6 | E97: 10 | F97: 8 | G97: 2 | I97: 0 | J97: 0 | K97: 0 | L97: 0 | M97: 0 | O97: 7 | P97: 17 | Q97: 24 | R97: 17 | S97: 4 | U97: 2 | V97: 31 | W97: 33 | X97: 34 | Y97: 2
A98: B | B98: Thulhaadhoo | C98: 8 | D98: 4 | E98: 12 | F98: 5 | G98: 7 | I98: 2 | J98: 0 | K98: 2 | L98: 1 | M98: 1 | O98: 29 | P98: 14 | Q98: 43 | R98: 26 | S98: 8 | U98: 19 | V98: 18 | W98: 37 | X98: 40 | Y98: 6
A99: B | B99: Hithaadhoo | C99: 1 | D99: 2 | E99: 3 | F99: 1 | G99: 2 | I99: 0 | J99: 0 | K99: 0 | L99: 0 | M99: 0 | O99: 4 | P99: 2 | Q99: 6 | R99: 6 | S99: 0 | U99: 1 | V99: 19 | W99: 20 | X99: 19 | Y99: 1
A100: B | B100: Fulhadhoo | C100: 0 | D100: 0 | E100: 0 | F100: 0 | G100: 0 | I100: 0 | J100: 0 | K100: 0 | L100: 0 | M100: 0 | O100: 4 | P100: 8 | Q100: 12 | R100: 8 | S100: 3 | U100: 1 | V100: 3 | W100: 4 | X100: 4 | Y100: 1
A101: B | B101: Fehendhoo | C101: 0 | D101: 0 | E101: 0 | F101: 0 | G101: 0 | I101: 0 | J101: 0 | K101: 0 | L101: 0 | M101: 0 | O101: 3 | P101: 2 | Q101: 5 | R101: 2 | S101: 1 | U101: 1 | V101: 6 | W101: 7 | X101: 5 | Y101: 4
A102: B | B102: Goidhoo | C102: 0 | D102: 2 | E102: 2 | F102: 2 | G102: 0 | I102: 0 | J102: 0 | K102: 0 | L102: 0 | M102: 0 | O102: 1 | P102: 4 | Q102: 5 | R102: 4 | S102: 1 | U102: 1 | V102: 6 | W102: 7 | X102: 7 | Y102: 0
A103: Lh | B103: Total | C103: =SUM(C104:C107) -> 81 | D103: =SUM(D104:D107) -> 32 | E103: =SUM(E104:E107) -> 113 | F103: =SUM(F104:F107) -> 111 | G103: =SUM(G104:G107) -> 2 | I103: =SUM(I104:I107) -> 3 | J103: =SUM(J104:J107) -> 4 | K103: =SUM(K104:K107) -> 7 | L103: =SUM(L104:L107) -> 7 | M103: =SUM(M104:M107) -> 0 | O103: =SUM(O104:O107) -> 143 | P103: =SUM(P104:P107) -> 111 | Q103: =SUM(Q104:Q107) -> 254 | R103: =SUM(R104:R107) -> 106 | S103: =SUM(S104:S107) -> 80 | U103: =SUM(U104:U107) -> 64 | V103: =SUM(V104:V107) -> 307 | W103: =SUM(W104:W107) -> 371 | X103: =SUM(X104:X107) -> 312 | Y103: =SUM(Y104:Y107) -> 127
A104: Lh | B104: Olhuvelifushi | C104: 0 | D104: 1 | E104: 1 | F104: 0 | G104: 1 | I104: 0 | J104: 0 | K104: 0 | L104: 0 | M104: 0 | O104: 7 | P104: 1 | Q104: 8 | R104: 4 | S104: 0 | U104: 3 | V104: 21 | W104: 24 | X104: 13 | Y104: 15
...

Sheet 8.21
A1: ތާވަލް 8.21: މާލެއާއި ރަށްރަށުގެ ކޯޓުތަކަށް ހުށައެޅިފައިވާ މައްސަލަތައް، 2014 -2015
A2: Table 8.21: SUMMARY OF ALL NEW CASES FILED IN COURTS IN MALE' AND ATOLLS, 2014 - 2015
A3: Atolls | B3: 2011 | H3: 2012 | M3: 2013 | R3: 2014 | W3: 2015 | AB3: އަތޮޅޮތައް
B4: Criminal Cases | C4: Civil Cases | D4: Family Cases | E4: Marriage | F4: Divorce | H4: Criminal Cases | I4: Civil Cases | J4: Family Cases | K4: Marriage | L4: Divorce | M4: Criminal Cases | N4: Civil Cases | O4: Family Cases | P4: Marriage | Q4: Divorce | R4: Criminal Cases | S4: Civil Cases | T4: Family Cases | U4: Marriage | V4: Divorce | W4: Criminal Cases | X4: Civil Cases | Y4: Family Cases | Z4: Marriage | AA4: Divorce
B5: ކްރިމިނަލް މައްސަލަ | C5: ސިވިލް މައްސަލަ | D5: އާއިލީ މައްސަލަ | E5: ކައިވެނި | F5: ވަރި | H5: ކްރިމިނަލް މައްސަލަ | I5: ސިވިލް މައްސަލަ | J5: އާއިލީ މައްސަލަ | K5: ކައިވެނި | L5: ވަރި | M5: ކްރިމިނަލް މައްސަލަ | N5: ސިވިލް މައްސަލަ | O5: އާއިލީ މައްސަލަ | P5: ކައިވެނި | Q5: ވަރި | R5: ޖިނާއީ މައްސަލަ | S5: މަދަނީ މައްސަލަ | T5: އާއިލީ މައްސަލަ | U5: ކައިވެނި | V5: ވަރި | W5: ޖިނާއީ މައްސަލަ | X5: މަދަނީ މައްސަލަ | Y5: އާއިލީ މައްސަލަ | Z5: ކައިވެނި | AA5: ވަރި | AP5: Marriage | AR5: Divorce
A6: Republic | B6: =B7+B13 -> 2766 | C6: =C7+C13 -> 7012 | D6: =D7+D13 -> 6309 | E6: =E7+E13 -> 6015 | F6: =F7+F13 -> 3013 | H6: =H7+H13 -> 2381 | I6: =I7+I13 -> 6873 | J6: =J7+J13 -> 6097 | K6: =K7+K13 -> 5699 | L6: =L7+L13 -> 3011 | M6: =M7+M13 -> 5640 | N6: =N7+N13 -> 4177 | O6: =O7+O13 -> 6678 | ... AA6: =AA7+AA13 -> 3358 | AB6: ޖުމްލަ | AP6: 2011 | AQ6: 2012 | AR6: 2011 | AS6: 2012
A7: Male' | B7: =SUM(B8:B12) -> 1572 | C7: =SUM(C8:C12) -> 2743 | D7: =SUM(D8:D12) -> 2083 | E7: =SUM(E8:E12) -> 2366 | F7: =SUM(F8:F12) -> 1209 | H7: =SUM(H8:H12) -> 1246 | I7: =SUM(I8:I12) -> 2725 | J7: =SUM(J8:J12) -> 2367 | K7: =SUM(K8:K12) -> 2404 | L7: =SUM(L8:L12) -> 1320 | M7: =SUM(M8:M12) -> 1655 | N7: =SUM(N8:N12) -> 2861 | O7: =SUM(O8:O12) -> 2668 | ... AA7: =SUM(AA8:AA12) -> 1455 | AB7: މާލެ | AO7: Republic | AP7: 6015 | AQ7: 5701 | AR7: 3013 | AS7: 3011
A8: Juvenile court | B8: 108 | C8: 0 | D8: 0 | E8: 0 | F8: 0 | H8: 83 | I8: 0 | J8: 0 | K8: 0 | L8: 0 | M8: 103 | N8: 0 | O8: 0 | P8: 0 | Q8: 0 | R8: 64 | S8: 0 | T8: 0 | U8: 0 | V8: 0 | W8: 25 | X8: 0 | Y8: 0 | Z8: 0 | AA8: 0 | AB8: ޖުވެނައިލް ކޯޓް | AO8: Male' | AP8: 2366 | AQ8: 2404 | AR8: 1209 | AS8: 1320
A9: Family court | B9: 0 | C9: 0 | D9: 2038 | E9: 2311 | F9: 1181 | H9: 0 | I9: 0 | J9: 2251 | K9: 2305 | L9: 1254 | M9: 0 | N9: 0 | O9: 2502 | P9: 2362 | Q9: 1411 | R9: 0 | S9: 0 | T9: 2603 | U9: 2357 | V9: 1426 | W9: 0 | X9: 0 | Y9: 2706 | Z9: 2417 | AA9: 1288 | AB9: ފެމިލީކޯޓް | AO9: Atolls | AP9: 3649 | AQ9: 3297 | AR9: 1804 | AS9: 1691
A10: Criminal court | B10: 1462 | C10: 0 | D10: 0 | E10: 0 | F10: 0 | H10: 1158 | I10: 0 | J10: 0 | K10: 0 | L10: 0 | M10: 1546 | N10: 0 | O10: 0 | P10: 0 | Q10: 0 | R10: 874 | S10: 0 | T10: 0 | U10: 0 | V10: 0 | W10: 806 | X10: 0 | Y10: 0 | Z10: 0 | AA10: 0 | AB10: ކްރިމިނަލްކޯޓް
A11: Civil court | B11: 0 | C11: 2558 | D11: 0 | E11: 0 | F11: 0 | H11: 0 | I11: 2277 | J11: 0 | K11: 0 | L11: 0 | M11: 0 | N11: 2453 | O11: 0 | P11: 0 | Q11: 0 | R11: 0 | S11: 2589 | T11: 0 | U11: 0 | V11: 0 | W11: 0 | X11: 2377 | Y11: 0 | Z11: 0 | AA11: 0 | AB11: ސިވިލް ކޯޓް
A12: HulhuMale' Court | B12: 2 | C12: 185 | D12: 45 | E12: 55 | F12: 28 | H12: 5 | I12: 448 | J12: 116 | K12: 99 | L12: 66 | M12: 6 | N12: 408 | O12: 166 | P12: 101 | Q12: 97 | R12: 47 | S12: 265 | T12: 252 | U12: 125 | V12: 98 | W12: 24 | X12: 166 | Y12: 338 | Z12: 193 | AA12: 167 | AB12: ހުޅުމާލޭ ކޯޓް
A13: Atolls | B13: =SUM(B14:B33) -> 1194 | C13: =SUM(C14:C33) -> 4269 | D13: =SUM(D14:D33) -> 4226 | E13: =SUM(E14:E33) -> 3649 | F13: =SUM(F14:F33) -> 1804 | H13: =SUM(H14:H33) -> 1135 | I13: =SUM(I14:I33) -> 4148 | J13: =SUM(J14:J33) -> 3730 | K13: =SUM(K14:K33) -> 3295 | L13: =SUM(L14:L33) -> 1691 | M13: =SUM(M14:M33) -> 3985 | N13: =SUM(N14:N33) -> 1316 | O13: =SUM(O14:O33) -> 4010 | ... AA13: =SUM(AA14:AA33) -> 1903 | AB13: އަތޮޅޮތައް
A14: HA | B14: 59 | C14: 193 | D14: 176 | E14: 219 | F14: 67 | H14: 28 | I14: 181 | J14: 169 | K14: 236 | L14: 87 | M14: 196 | N14: 75 | O14: 176 | P14: 206 | Q14: 86 | R14: 61 | S14: 177 | T14: 204 | U14: 177 | V14: 89 | W14: 42 | X14: 79 | Y14: 257 | Z14: 169 | AA14: 91 | AB14: ހއ
A15: HDh | B15: 112 | C15: 177 | D15: 277 | E15: 339 | F15: 153 | H15: 73 | I15: 178 | J15: 233 | K15: 287 | L15: 120 | M15: 135 | N15: 232 | O15: 273 | P15: 279 | Q15: 149 | R15: 183 | S15: 205 | T15: 339 | U15: 279 | V15: 126 | W15: 66 | X15: 112 | Y15: 440 | Z15: 274 | AA15: 170 | AB15: ހދ | AR15: Marriage | AS15: Divorce
A16: Sh | B16: 57 | C16: 182 | D16: 151 | E16: 193 | F16: 73 | H16: 24 | I16: 145 | J16: 162 | K16: 199 | L16: 88 | M16: 148 | N16: 30 | O16: 164 | P16: 188 | Q16: 75 | R16: 23 | S16: 138 | T16: 195 | U16: 148 | V16: 95 | W16: 36 | X16: 67 | Y16: 262 | Z16: 166 | AA16: 82 | AB16: ށ | AQ16: Republic | AR16: 5763 | AS16: 3358
A17: N | B17: 54 | C17: 194 | D17: 236 | E17: 195 | F17: 107 | H17: 62 | I17: 186 | J17: 215 | K17: 193 | L17: 95 | M17: 175 | N17: 52 | O17: 213 | P17: 187 | Q17: 101 | R17: 97 | S17: 219 | T17: 290 | U17: 167 | V17: 104 | W17: 97 | X17: 133 | Y17: 383 | Z17: 171 | AA17: 103 | AB17: ނ | AQ17: Male' | AR17: 2610 | AS17: 1455
A18: R | B18: 128 | C18: 191 | D18: 231 | E18: 270 | F18: 100 | H18: 84 | I18: 202 | J18: 231 | K18: 259 | L18: 118 | M18: 201 | N18: 67 | O18: 219 | P18: 233 | Q18: 117 | R18: 99 | S18: 225 | T18: 326 | U18: 254 | V18: 113 | W18: 56 | X18: 153 | Y18: 359 | Z18: 255 | AA18: 103 | AB18: ރ | AQ18: Atolls | AR18: 3153 | AS18: 1903
A19: B | B19: 29 | C19: 97 | D19: 137 | E19: 158 | F19: 63 | H19: 26 | I19: 183 | J19: 135 | K19: 151 | L19: 57 | M19: 133 | N19: 27 | O19: 136 | P19: 125 | Q19: 63 | R19: 43 | S19: 119 | T19: 171 | U19: 124 | V19: 64 | W19: 21 | X19: 79 | Y19: 175 | Z19: 111 | AA19: 62 | AB19: ބ
A20: Lh | B20: 71 | C20: 99 | D20: 165 | E20: 168 | F20: 72 | H20: 61 | I20: 124 | J20: 178 | K20: 160 | L20: 93 | M20: 201 | N20: 68 | O20: 180 | P20: 141 | Q20: 85 | R20: 60 | S20: 171 | T20: 244 | U20: 127 | V20: 82 | W20: 36 | X20: 111 | Y20: 307 | Z20: 129 | AA20: 96 | AB20: ޅ
A21: K | B21: 52 | C21: 183 | D21: 258 | E21: 226 | F21: 133 | H21: 41 | I21: 145 | J21: 218 | K21: 213 | L21: 112 | M21: 207 | N21: 42 | O21: 259 | P21: 201 | Q21: 129 | R21: 26 | S21: 263 | T21: 300 | U21: 247 | V21: 126 | W21: 62 | X21: 102 | Y21: 388 | Z21: 222 | AA21: 151 | AB21: ކ | AQ21: Marriage | AS21: Divorce
A22: AA | B22: 32 | C22: 110 | D22: 127 | E22: 116 | F22: 69 | H22: 13 | I22: 123 | J22: 123 | K22: 99 | L22: 68 | M22: 140 | N22: 7 | O22: 142 | P22: 102 | Q22: 71 | R22: 18 | S22: 120 | T22: 155 | U22: 86 | V22: 65 | W22: 15 | X22: 115 | Y22: 234 | Z22: 102 | AA22: 70 | AB22: އއ | AQ22: 2014 | AR22: 2015 | AS22: 2014 | AT22: 2015
A23: ADh | B23: 20 | C23: 104 | D23: 166 | E23: 169 | F23: 85 | H23: 18 | I23: 145 | J23: 141 | K23: 152 | L23: 74 | M23: 142 | N23: 20 | O23: 189 | P23: 148 | Q23: 110 | R23: 16 | S23: 253 | T23: 189 | U23: 139 | V23: 76 | W23: 25 | X23: 133 | Y23: 284 | Z23: 121 | AA23: 84 | AB23: އދ | AP23: Republic | AQ23: 5587 | AR23: 5763 | AS23: 3414 | AT23: 3358
A24: V | B24: 1 | C24: 21 | D24: 29 | E24: 14 | F24: 17 | H24: 1 | I24: 33 | J24: 19 | K24: 13 | L24: 12 | M24: 60 | N24: 9 | O24: 24 | P24: 24 | Q24: 16 | R24: 1 | S24: 55 | T24: 28 | U24: 18 | V24: 11 | W24: 0 | X24: 23 | Y24: 47 | Z24: 20 | AA24: 18 | AB24: ވ | AP24: Male' | AQ24: 2482 | AR24: 2610
A25: M | B25: 15 | C25: 136 | D25: 84 | E25: 82 | F25: 34 | H25: 4 | I25: 62 | J25: 72 | K25: 70 | L25: 32 | M25: 99 | N25: 24 | O25: 65 | P25: 69 | Q25: 30 | R25: 23 | S25: 75 | T25: 88 | U25: 66 | V25: 40 | W25: 5 | X25: 52 | Y25: 130 | Z25: 71 | AA25: 42 | AB25: މ | AP25: Atolls | AQ25: 3105 | AR25: 3153
A26: F | B26: 15 | C26: 86 | D26: 84 | E26: 94 | F26: 50 | H26: 14 | I26: 83 | J26: 70 | K26: 76 | L26: 33 | M26: 106 | N26: 12 | O26: 87 | P26: 87 | Q26: 39 | R26: 21 | S26: 74 | T26: 106 | U26: 62 | V26: 32 | W26: 4 | X26: 53 | Y26: 129 | Z26: 68 | AA26: 33 | AB26: ފ
A27: Dh | B27: 12 | C27: 134 | D27: 87 | E27: 92 | F27: 40 | H27: 4 | I27: 89 | J27: 85 | K27: 64 | L27: 44 | M27: 65 | N27: 20 | O27: 86 | P27: 80 | Q27: 33 | R27: 8 | S27: 80 | T27: 130 | U27: 71 | V27: 40 | W27: 4 | X27: 44 | Y27: 145 | Z27: 66 | AA27: 27 | AB27: ދ | AQ27: Divorce
A28: Th | B28: 34 | C28: 211 | D28: 155 | E28: 166 | F28: 80 | H28: 76 | I28: 177 | J28: 171 | K28: 146 | L28: 85 | M28: 184 | N28: 56 | O28: 152 | P28: 118 | Q28: 71 | R28: 66 | S28: 164 | T28: 213 | U28: 126 | V28: 97 | W28: 27 | X28: 101 | Y28: 277 | Z28: 135 | AA28: 102 | AB28: ތ | AQ28: 2014 | AR28: 2015
A29: L | B29: 75 | C29: 515 | D29: 331 | E29: 250 | F29: 142 | H29: 108 | I29: 374 | J29: 291 | K29: 242 | L29: 117 | M29: 289 | N29: 139 | O29: 347 | P29: 230 | Q29: 149 | R29: 113 | S29: 350 | T29: 502 | U29: 230 | V29: 152 | W29: 116 | X29: 224 | Y29: 633 | Z29: 256 | AA29: 173 | AB29: ލ | AP29: Republic | AQ29: =V6 -> 3414 | AR29: 3358
A30: GA | B30: 43 | C30: 470 | D30: 313 | E30: 149 | F30: 92 | H30: 48 | I30: 652 | J30: 238 | K30: 114 | L30: 74 | M30: 403 | N30: 90 | O30: 228 | P30: 135 | Q30: 73 | R30: 84 | S30: 587 | T30: 282 | U30: 130 | V30: 96 | W30: 97 | X30: 412 | Y30: 372 | Z30: 178 | AA30: 87 | AB30: ގއ | AP30: Male' | AQ30: =V7 -> 1524 | AR30: 1455
A31: GDh | B31: 33 | C31: 352 | D31: 370 | E31: 213 | F31: 141 | H31: 57 | I31: 381 | J31: 309 | K31: 192 | L31: 122 | M31: 325 | N31: 47 | O31: 358 | P31: 209 | Q31: 142 | R31: 92 | S31: 348 | T31: 477 | U31: 203 | V31: 135 | W31: 81 | X31: 180 | Y31: 505 | Z31: 182 | AA31: 116 | AB31: ގދ | AP31: Atolls | AQ31: =V13 -> 1890 | AR31: 1903
A32: Gn | B32: 138 | C32: 287 | D32: 278 | E32: 147 | F32: 92 | H32: 149 | I32: 295 | J32: 242 | K32: 146 | L32: 82 | M32: 279 | N32: 114 | O32: 213 | P32: 117 | Q32: 83 | R32: 105 | S32: 377 | T32: 348 | U32: 119 | V32: 115 | W32: 138 | X32: 212 | Y32: 356 | Z32: 160 | AA32: 87 | AB32: ޏ
A33: S | B33: 214 | C33: 527 | D33: 571 | E33: 389 | F33: 194 | H33: 244 | I33: 390 | J33: 428 | K33: 283 | L33: 178 | M33: 497 | N33: 185 | O33: 499 | P33: 286 | Q33: 201 | R33: 138 | S33: 560 | T33: 715 | U33: 332 | V33: 232 | W33: 250 | X33: 362 | Y33: 750 | Z33: 297 | AA33: 206 | AB33: ސ
A34: Source: Department of Judicial Administration | AB34: cnwxErcTcsinimcDea clwxiDuj cfoa cTcnwmcTWpiD : utWmUluAwm

Sheet 8.22
A1: ތާވަލު 8.22: ހުށަހެޅުނު ޖިނާޢީ މައްސަލަތަކުގެ އަދަދު، 2007 - 2015
A2: Table 8.22: NUMBER OF CRIMINAL CASES FILED BY CATERGORIES, 2007 - 2015
A3: Type of cases | B3: 2007 | C3: 2008 | D3: 2009 | E3: 2010 | F3: 2011 | G3: 2012 | H3: 2013 | I3: 2014 | J3: 2015 | K3: މައްސަލައިގެ ބާވަތް
A4: Total | B4: =SUM(B5:B14) -> 2910 | C4: =SUM(C5:C14) -> 2430 | D4: =SUM(D5:D14) -> 4094 | E4: =SUM(E5:E14) -> 3057 | F4: =SUM(F5:F14) -> 2766 | G4: =SUM(G5:G14) -> 2381 | H4: =SUM(H5:H14) -> 2971 | I4: =SUM(I5:I14) -> 2262 | J4: =SUM(J5:J14) -> 2033 | K4: ޖުމްލަ
A5: Disobeying Lawful Order | B5: 657 | C5: 484 | D5: 769 | E5: 412 | F5: 376 | G5: 297 | H5: 303 | I5: 246 | J5: 134 | K5: އަމުރަށް ނުކިޔަމަންތެރިވުން
A6: Traffic Violation | B6: 301 | C6: 339 | D6: 313 | E6: 39 | F6: 19 | G6: 5 | H6: 0 | I6: 0 | J6: 0 | K6: ޓްރެފިކް
A7: Unlawful Assembly | B7: 62 | C7: 38 | D7: 116 | E7: 90 | F7: 65 | G7: 42 | H7: 45 | I7: 49 | J7: 31 | K7: ޢައިރު ޤާނޫނީ އެއްވުން
A8: Supplying Drugs | B8: 101 | C8: 119 | D8: 127 | E8: 184 | F8: 242 | G8: 72 | H8: 61 | I8: 74 | J8: 57 | K8: މަސްތުވާތަކެތި ވިއްކުން
A9: Theft (minor) | B9: 136 | C9: 148 | D9: 387 | E9: 217 | F9: 208 | G9: 293 | H9: 374 | I9: 376 | J9: 297 | K9: ކުދި ވައްކަން
A10: Assault | B10: 194 | C10: 132 | D10: 348 | E10: 192 | F10: 207 | G10: 211 | H10: 228 | I10: 183 | J10: 118 | K10: މާރާމާރީ
A11: Cheque Bounce | B11: 96 | C11: 110 | D11: 190 | E11: 185 | F11: 132 | G11: 124 | H11: 55 | I11: 53 | J11: 38 | K11: ޗެކްބައުންސް
A12: Fornication | B12: 138 | C12: 120 | D12: 131 | E12: 116 | F12: 129 | G12: 78 | H12: 105 | I12: 68 | J12: 88 | K12: ޒިނޭކުރުން
A13: Drug Abuse | B13: 178 | C13: 262 | D13: 460 | E13: 591 | F13: 269 | G13: 103 | H13: 97 | I13: 25 | J13: 66 | K13: މަސްތުވާތަކެތި ބޭނުންކުރުން
A14: Others Criminal Cases | B14: 1047 | C14: 678 | D14: 1253 | E14: 1031 | F14: 1119 | G14: 1156 | H14: 1703 | I14: 1188 | J14: 1204 | K14: އެހެނިހެން ޖިނާޢީ މައްސަލަތައް
A15: Source: Department of Judicial Administration | K15: cnwxErcTcsinimcDea clwxiDuj cfoa cTcnwmcTWpiD : utWmUluAwm

Sheet 8.23
A1: ތާވަލު 8.23: ހުށަހެޅުނު މަދަނީ މައްސަލަތަކުގެ ޢަދަދު، 2007 - 2015
A2: Table 8.23: NUMBER OF CIVIL CASES FILED BY CATERGORIES, 2007 - 2015
A3: Type of cases | B3: 2007 | C3: 2008 | D3: 2009 | E3: 2010 | F3: 2011 | G3: 2012 | H3: 2013 | I3: 2014 | J3: 2015 | K3: މައްސަލައިގެ ބާވަތް
A4: Total | B4: =SUM(B5:B13) -> 5892 | C4: =SUM(C5:C13) -> 5775 | D4: =SUM(D5:D13) -> 7816 | E4: =SUM(E5:E13) -> 7370 | F4: =SUM(F5:F13) -> 7012 | G4: =SUM(G5:G13) -> 6873 | H4: =SUM(H5:H13) -> 6846 | I4: =SUM(I5:I13) -> 7414 | J4: =SUM(J5:J13) -> 5290 | K4: ޖުމްލަ
A5: Established Debt | B5: 376 | C5: 384 | D5: 782 | E5: 495 | F5: =[3]s41!$B$8 -> 450 | G5: 375 | H5: 358 | I5: 357 | J5: 524 | K5: ސާބިތު ދަރަނި
A6: Endowment | B6: 640 | C6: 680 | D6: 714 | E6: 675 | F6: =[3]s41!$B$12 -> 600 | G6: 582 | H6: 614 | I6: 696 | J6: 82 | K6: * ހިބައިން ދިނުން
A7: Separation of Property | B7: 34 | C7: 37 | D7: 52 | E7: 37 | F7: =[3]s41!$B$14 -> 23 | G7: 31 | H7: 33 | I7: 31 | J7: 44 | K7: މުދާވަކިކުރުން
A8: Claims for damages | B8: 66 | C8: 105 | D8: 178 | E8: 171 | F8: =[3]s41!$B$20 -> 186 | G8: 161 | H8: 191 | I8: 193 | J8: 106 | K8: ގެއްލުމުގެ ބަދަލު ހޯދުން
A9: Debt Enforcement | B9: 984 | C9: 931 | D9: 996 | E9: 1316 | F9: =[3]s41!$B$23 -> 1675 | G9: 1613 | H9: 1376 | I9: 1614 | J9: 1143 | K9: ދަރަނި / ފައިސާ ހޯދުން
A10: Collection of Rent | B10: 465 | C10: 431 | D10: 581 | E10: 496 | F10: =[3]s41!$B$32 -> 140 | G10: 191 | H10: 71 | I10: 164 | J10: 147 | K10: ކުލީ ފައިސާ ހޯދުން
A11: Breach of Agreement | B11: 432 | C11: 307 | D11: 537 | E11: 363 | F11: =[3]s41!$B$22 -> 212 | G11: 384 | H11: 357 | I11: 277 | J11: 254 | K11: އެގްރީމަންޓާއިބެހޭ މައްސަލަތައް
A12: Lost and Found Propoerty | B12: 28 | C12: 24 | D12: 12 | E12: 25 | F12: =[3]s41!$B$31 -> 5 | G12: 19 | H12: 5 | I12: 9 | J12: 5 | K12: ހޮވައިގެން ގެނެވޭ ތަކެތި
A13: Others Civil Cases | B13: 2867 | C13: 2876 | D13: 3964 | E13: 3792 | F13: 3721 | G13: 3517 | H13: 3841 | I13: 4073 | J13: 2985 | K13: އެހެނިހެން މަދަނީ މައްސަލަ
A14: ނޯޓް: * ފެބްރުވަރީ މަހުން ފެށިގެން މި ކެޓަގަރީގެ މައްސަލަތަކަކީ އާއިލީ މައްސަލަތަކެއް ކަމުގައި ސުޕްރީމް ކޯޓުން ވަނީ ކަނޑައަޅުއްވާފައި. (މިބައިގައި މިވާ 82 މައްސަލައަކީ އާއިލީ މައްސަލަތަކެއް ކަމުގައި ސުޕްރީމް ކޯޓުން ކަނޑައެޅުމުގެ ކުރިން ކޯޓުތަކަށް ހުށަހެޅިފައިވާ މައްސަލަތަކެވެ.
A15: Source: Department of Judicial Administration | K15: cnwxErcTcsinimcDea clwxiDuj cfoa cTcnwmcTWpiD : utWmUluAwm

Sheet 8.24
A2: ތާވަލު 8.24: ދައުލަތުގެފަރާތުން ޝަރީއަތަށް ހުށަހެޅުނު މައްސަލަތައް، 2013 - 2015
A3: TABLE 8.24: NUMBER OF CASES SENT TO COURT TRIAL, 2013 - 2015
B4: Details | C4: 2013 | D4: 2014 | E4: 2015 | F4: މައްސަލަތަކުގެ ތަފްސީލް
B5: Total | C5: 2086 | D5: 1497 | E5: 1999 | F5: ޖުމްލަ
A6: 1 | B6: Theft | C6: 328 | D6: 379 | E6: 203 | F6: ވައްކަން | G6: 1
A7: 2 | B7: use / consumption of cannabis | C7: 277 | D7: 111 | E7: 322 | F7: ކެނަބިސް ބޭނުން ކުރުން | G7: 2
A8: 3 | B8: use / consumption of diamorphine | C8: 220 | D8: 195 | E8: 647 | F8: ޑައިމޯފިން ބޭނުން ކުރުން | G8: 3
A9: 4 | B9: acts in contradiction to the laws and state orders | C9: 196 | D9: 146 | E9: 65 | F9: ޤާނޫނާއި ޚިލާފުވުމާއި ދަޢުލަތުގެ އަމުރަށް ނުކިޔަމަންތެރިވުން | G9: 4
A10: 5 | B10: refusing to provide urine sample | C10: 141 | D10: 11 | E10: 3 | F10: ކުޑަކަމުދާ ތަކެތި ދިނުމަށް އިންކާރު ކުރުން | G10: 5
A11: 6 | B11: Assault | C11: 135 | D11: 108 | E11: 74 | F11: މާރާމާރީ | G11: 6
A12: 7 | B12: hindering /obstructing /assaulting a police officer on duty | C12: 101 | D12: 42 | E12: 67 | F12: ފުލުހުންގެ ދައުރު އަދާކުރަން ހުރި މީހަކަށް ދަތިކުރުން/ހުރަސްއެޅުން/ޙަމަލާދިނުން | G12: 7
A13: 8 | B13: Fornication/adultery | C13: 59 | D13: 48 | E13: 53 | F13: ޒިނޭ | G13: 8
A14: 9 | B14: substance / drug abuse | C14: 56 | D14: 2 | E14: 2 | F14: މަސްތުވާތަކެތި ބޭނުންކުރުން | G14: 9
A15: 10 | B15: threatening | C15: 46 | D15: 6 | E15: 40 | F15: ބިރުދެއްކުމާއި އިންޒާރުދިނުން | G15: 10
A16: 11 | B16: dealing in diamorphine | C16: 42 | D16: 58 | E16: 135 | F16: ޑައިމޯފިނުން މުޢާމަލާތް ކުރުން | G16: 11
A17: 12 | B17: cheque bounce | C17: 41 | D17: 37 | E17: 34 | F17: އެކައުންޓުގައި ފައިސާނެތި ޗެކް ދޫކުރުން | G17: 12
... A47: 42 | B47: obstructing the duty of a government employee | C47: 3 | D47: 0 | E47: 0 | F47: ދައުލަތުގެ މުވައްޒަފެއްގެ ވާޖިބަށް ހުރަސްއެޅުން | G47: 42
A48: 43 | E48: 2 | F48: ކުޑަކުދިންނަށް ޖިންސީ ގުނަވަނެއް ދެއްކުން | G48: 43
A49: 44 | E49: 10 | F49: ޓެރަރިޒަމް | G49: 44
A50: 45 | E50: 2 | F50: ރޭޕްކުރުން | G50: 45
A51: 46 | E51: 2 | F51: ޓެކުން | G51: 46
A52: 47 | E52: 2 | F52: މީހެއްގެ މުދަލަށް ގެއްލުން ދިނުން | G52: 47
A53: 48 | E53: 1 | F53: މަސްމަރާބަޑި އުފެއްދުމާއި، ގެންގުޅުން | G53: 48
A54: 49 | E54: 1 | F54: ރައްކާތެރި ކުރުމުގެ އަމުރާ ޚިލާފްވުން | G54: 49
A55: 50 | E55: 1 | F55: ހަނގުރާމަވެރި ހަތިިޔާރު ގެންގުޅުން | G55: 50
A56: 43 | B56: Others | C56: 23 | D56: 94 | E56: 0 | G56: 51
A57: Note: since the total number of cases in table are categorized based on type of charge, the number of cases submitted to court (table 8.25) may differ since a single case submitted to court may have more than one charges associated.
A58: Source: Prosecutor General's office | F58: ޤާނޫނު ނަންބަރ 17/2011 އާއި ގުޅޭ | G58: *
F59: މަޢުލޫމާތު ދެއްވި ފަރާތް: ޕްރޮސިކިއުޓަރ ޖެނެރަލްގެ އޮފީސް

Sheet 8.25
A1: ތާވަލު: 8.25: ޕްރޮސިކިއުޓަރ ޖެނެރަލްގެ އޮފީހަށް ހުށަހެޅުނު އަދި ނިންމުނު މައްސަލަތައް، 2011 - 2015
A2: TABLE 8.25: NUMBER OF CASES SUBMITTED AND COMPLETED, 2011 - 2015
A4: Details | B4: 2011 | C4: 2012 | D4: 2013 | E4: 2014 | F4: 2015 | G4: ބެހިފައިވާ ގޮތް (އިން ސައްތަ) share % | H4: ތަފްސީލް
G5: 2015
A6: Total Number of cases | B6: 2874 | C6: 3362 | D6: 3551 | E6: 3396 | F6: 4509 | G6: 100 | H6: ދަޢްވާ ހުށަހަޅަން އޮފީސްތަކުން ފޮނުއްވި ޖުމްލަ
A7: Number of cases completed by PG office | B7: 2495 | C7: 2069 | D7: 2521 | E7: 2401 | F7: 3191 | G7: 70.769572 | H7: ޕްރޮސިކިއުޓަރ ޖެނެރަލްގެ އޮފީހުން ނިންމުނު މައްސަލައިގެ ޖުމްލަ
A8: Submitted to courts | B8: 1850 | C8: 1429 | D8: 1821 | E8: 1497 | F8: 1831 | G8: 40.607674 | H8: ކޯޓަށް ހުށަހެޅުނު
A9: send back to resend again | B9: 354 | C9: 334 | D9: 322 | E9: 283 | F9: 241 | G9: 5.3448658 | H9: އަލުން ހުށަޙެޅުމަށްޓަކައި އަނބުރާ ފޮނުވާލެވުނު
A10: send back due to no evidence | B10: 291 | C10: 284 | D10: 327 | E10: 227 | F10: 128 | G10: 2.8387669 | H10: ހެއްކާ ޤަރީނާ ލިބިފައިނުވާތީ އަނބުރާ ފޮނުވާލެވުނު
A11: send back due to other reasons | B11: 0 | C11: 22 | D11: 51 | E11: 102 | F11: 482 | G11: 10.689732 | H11: އެހެނިހެން ގޮތްގޮތުން އަނބުރާ ފޮނުވާލެވުނު
A12: Cases hold by PG Office | B12: - | C12: - | D12: - | E12: 175 | F12: 406 | G12: 9.0042138 | H12: މިއޮފީހުގައި ހިފެހެއްޓިފައިހުރި މައްސަލަ
A13: given another chance | B13: - | C13: - | D13: - | E13: 52 | F13: 101 | G13: 2.2399645 | H13: އިތުރު ފުރުސަތު
A14: No address in Male' | B14: - | C14: - | D14: - | E14: 65 | F14: 2 | G14: 0.044355733 | H14: މާލޭ އެޑްރެސްނެތިގެން
A15: Number of cases not sent to court | B15: 379 | C15: 1293 | D15: 1030 | E15: 995 | F15: 1318 | G15: 29.230428 | H15: ކޯޓަށް ހުށަނޭޅި ހުރި މައްސަލަ
A16: Source: Prosecutor General's office | H16: މަޢުލޫމާތު ދެއްވި ފަރާތް: ޕްރޮސިކިއުޓަރ ޖެނެރަލްގެ އޮފީސް
Q27: 2011 | R27: 2012 | S27: 2013 | T27: 2014 | U27: 2015
P28: Completion rate | Q28: 86.812804 | R28: 61.54075 | S28: 70.994086 | T28: 70.700824 | U28: 70.769572
P29: Submission rate to courts | Q29: 64.370216 | R29: 42.504462 | S29: 51.281329 | T29: 44.081272 | U29: 40.607674
Q31: 2011 | R31: 2012 | S31: 2013 | T31: 2014 | U31: 2015
P32: Completed | Q32: 2495 | R32: 2069 | S32: 2521 | T32: 2401 | U32: 3191
P33: Submitted to court | Q33: 1850 | R33: 1429 | S33: 1821 | T33: 1497 | U33: 1831
P34: Not sent to court | Q34: 379 | R34: 1293 | S34: 1030 | T34: 995 | U34: 1318
Q35: 2011 | R35: 2012 | S35: 2013 | T35: 2014 | U35: 2014
P36: Submitted to courts | Q36: 1850 | R36: 1429 | S36: 1821 | T36: 1821
P37: send back to resend again | Q37: 354 | R37: 334 | S37: 322 | T37: 322
P38: send back due to no evidence | Q38: 291 | R38: 284 | S38: 327 | T38: 327
P39: send back due to other reasons | Q39: 0 | R39: 22 | S39: 51 | T39: 51

Sheet 8.26
A2: ތާވަލު 8.26: ޕްރޮސިކިއުޓަރުންގެ އަދަދު އަދި ހިނގި ޚަރަދު، 2010 - 2015
A3: TABLE 8.26: PROSECUTION PERSONNEL BY SEX AND FINANCIAL RESOURCES, 2010 - 2015
A4: Details | B4: Year އަހަރު | H4: ތަފްސީލް
B5: 2010 | C5: 2011 | D5: 2012 | E5: 2013 | F5: 2014 | G5: 2015
A6: Total prosecution personnel (Lawyers) | B6: =B8+B7 -> 39 | C6: =C8+C7 -> 45 | D6: =D8+D7 -> 45 | E6: =E8+E7 -> 46 | F6: =F8+F7 -> 48 | G6: =G8+G7 -> 62 | H6: ޖުމްލަ ޕްރޮސިކިއުޓަރުންގެ އަދަދު
A7: Male | B7: 20 | C7: 21 | D7: 19 | E7: 24 | F7: 22 | G7: 30 | H7: ފިރިހެން
A8: Female | B8: 19 | C8: 24 | D8: 26 | E8: 22 | F8: 26 | G8: 32 | H8: އަންހެން
A9: Total Expenditure (million MVR) | B9: 21.2 | C9: 24 | D9: 24.5 | E9: 24.4 | F9: 25.9 | G9: 41.6 | H9: ޖުމްލަ ޚަރަދުވި ވަރު (މިލިއަން ރުފިޔާ)
A10: Source: Prosecutor General's office | H10: މަޢުލޫމާތު ދެއްވި ފަރާތް: ޕްރޮސިކިއުޓަރ ޖެނެރަލްގެ އޮފީސް

Sheet 8.27

Sheet 8.28
A1: ތާވަލު 8.28: ކޯޓުތަކުގައި ތިބި ފަނޑިޔާރުންގެ އަދަދު އަދި ކޯޓުތަކަށް ހިނގި ޚަރަދު، 2010 - 2015
A2: TABLE 8.28: JUDGES BY SEX AND FINANCIAL RESOURCES FOR COURTS , 2010 - 2015
A4: Category | B4: end year | H4: ތަފްސީލް
B5: 2010 | C5: 2011 | D5: 2012 | E5: 2013 | F5: 2014 | G5: 2015
A6: Total judges / Majistrates | B6: =SUM(B7:B8) -> 202 | C6: =SUM(C7:C8) -> 197 | D6: =SUM(D7:D8) -> 164 | E6: =SUM(E7:E8) -> 185 | F6: =SUM(F7:F8) -> 182 | H6: ޖުމްލަ ފުލުހުންގެ އަދަދު
A7: Male | B7: 198 | C7: 192 | D7: 159 | E7: 176 | F7: 174 | H7: ފިރިހެން
A8: Female | B8: 4 | C8: 5 | D8: 5 | E8: 9 | F8: 8 | H8: އަންހެން
A9: Total Expenditure for Courts (million MVR) | B9: 211.38208 | C9: 253.83249 | D9: 298.93866 | E9: 292.36569 | F9: 326.90535 | G9: 468.04599 | H9: ކޯޓުތަކަށް ޖުމްލަ ޚަރަދުވި ވަރު (މިލިއަން ރުފިޔާ)
A10: Source: Judicial Service Commission | H10: މަޢުލޫމާތު ދެއްވި ފަރާތް: ޖުޑީޝަލް ސަރވިސް ކޮމިޝަން
A11: Department of Judicial Administration | H11: ޑިޕާޓްމަންޓް އޮފް ޖުޑިޝަލް އެޑްމިނިސްޓްރޭޝަން
AA13: =AA15+AA16 -> 182
W14: 2010 | X14: 2011 | Y14: 2012 | Z14: 2013 | AA14: 2014 | AB14: % share 2014
V15: Male | W15: 198 | X15: 192 | Y15: 159 | Z15: =E7 -> 176 | AA15: =F7 -> 174 | AB15: =AA15/AA13*100 -> 95.604396
V16: Female | W16: 4 | X16: 5 | Y16: 5 | Z16: =E8 -> 9 | AA16: =F8 -> 8 | AB16: =AA16/AA13*100 -> 4.3956044
V17: % share of females | W17: =W16/B6*100 -> 1.980198 | X17: =X16/C6*100 -> 2.5380711 | Y17: =Y16/D6*100 -> 3.0487805 | Z17: =Z16/E6*100 -> 4.8648649 | AA17: =AA16/F6*100 -> 4.3956044
X22: Male | Y22: 96
X23: Female | Y23: 4
